Workbook

Sheet Resumen
A1: NIHON — BASE MAESTRA v2 / JAPÓN 2027
A2: Base normalizada y verificada al 2026-09-01; conserva alternativas y separa confirmados, patrones históricos y pendientes 2027.
A4: Métrica | B4: Valor | D4: Métrica | E4: Valor | G4: Métrica | H4: Valor
A5: Total de fichas | B5: =COUNTA('Lugares'!$A$2:$A$500) | D5: Tokio | E5: =COUNTIF('Lugares'!$B$2:$B$500,"Tokio") | G5: Saturación extrema | H5: =COUNTIF('Lugares'!$U$2:$U$500,"Extremo")
A6: Grado S | B6: =COUNTA(Lugares!A2:A500) | D6: Kioto | E6: =COUNTIF('Lugares'!$B$2:$B$500,"Kioto") | G6: Impacto visual 5 | H6: =COUNTIF('Lugares'!$AM$2:$AM$500,5)
A7: Grado A | B7: =COUNTIF(Lugares!M2:M500,"S") | D7: Osaka/Kansai | E7: =COUNTIF('Lugares'!$B$2:$B$500,"Osaka") | G7: Naturaleza/mar | H7: =COUNTIF('Lugares'!$K$2:$K$500,"🌿 Naturaleza")+COUNTIF('Lugares'!$K$2:$K$500,"🌊 Playa/mar/islas")
A8: Hidden gems | B8: =COUNTIF(Lugares!M2:M500,"A") | D8: Okinawa | E8: =COUNTIF('Lugares'!$B$2:$B$500,"Okinawa") | G8: Gaming/anime | H8: =COUNTIF('Lugares'!$K$2:$K$500,"🎮 Videojuegos")+COUNTIF('Lugares'!$K$2:$K$500,"👾 Anime/manga")
A9: Requieren/recomiendan reserva | B9: =COUNTIF(Lugares!M2:M500,"B") | D9: Clusters | E9: =COUNTA('Clusters'!$A$2:$A$200) | G9: Cambios 2026 vigilados | H9: =COUNTA('Cambios 2026'!$A$2:$A$100)
B10: =COUNTIF(Lugares!M2:M500,"C")
B11: =COUNTIF(Lugares!M2:M500,"D")
A12: Cómo usar esta base
A13: 1 | B13: =COUNTIF(Lugares!AS2:AS500,"Semi-hidden")
A14: 2 | B14: Consulta Clusters y Cercanos para la futura función ‘Si estás aquí…’.
A15: 3 | B15: Hidden Gems distingue joya real, semi-hidden y alternativa.
A16: 4 | B16: Comparativas evita duplicar miradores, mercados, teamLab, castillos u onsen.
A17: 5 | B17: Feb-Mar 2027 reúne cierres, aperturas, riesgos invernales y oportunidades estacionales.
A18: Nota | B18: Precios MXN usan 1 JPY = 0.1060 MXN (Banxico, 2026-09-01). Horarios y tarifas variables deben verificarse al fijar fechas.

Sheet Lugares
A1: ID | B1: Hub | C1: Región | D1: Prefectura | E1: Municipio | F1: Zona/barrio | G1: Cluster | H1: Nombre oficial | I1: Nombre japonés | J1: Título mapa | K1: Categoría | L1: Tipo | M1: Grado | N1: Razón del grado | O1: Descripción corta | P1: Qué lo hace diferente | Q1: Qué se hace/ve | R1: Duración | S1: Mejor momento | T1: Mejor época | U1: Aglomeración | V1: Qué tan turístico | W1: Precio JPY mín | X1: Precio JPY máx | Y1: Precio MXN mín | Z1: Precio MXN máx | AA1: Reserva | AB1: Anticipación | AC1: Horario | AD1: Días de cierre | AE1: Estación/transporte útil | AF1: Accesibilidad aproximada | AG1: Latitud | AH1: Longitud | AI1: Página oficial/fuente | AJ1: Estado de información | AK1: Etiqueta | AL1: Ideal para | AM1: Impacto visual 1–5 | AN1: Originalidad 1–5 | AO1: Valor/tiempo 1–5 | AP1: Turismo 1–5 | AQ1: Imagen recomendada | AR1: Si estás aquí... | AS1: Hidden Gem Status | AT1: Alternativa a | AU1: Google Maps | AV1: Actualizado | AW1: Estado Feb–Mar 2027 | AX1: Advertencia / oportunidad Feb–Mar 2027 | AY1: Acción recomendada Feb–Mar 2027
A2: JP-001 | B2: Tokio | C2: Kanto | D2: Tokio | E2: Shibuya | F2: Shibuya | G2: Shibuya | H2: Shibuya Crossing | I2: 渋谷スクランブル交差点 | J2: Shibuya Crossing | K2: 🏙️ Ciudad y barrios | L2: cruce urbano | M2: A | N2: Icono urbano único, pero la experiencia es breve y muy saturada. | O2: Cruce peatonal masivo rodeado de pantallas y flujo humano. | P2: El movimiento colectivo, más que un monumento, es la atracción. | Q2: Cruce peatonal masivo rodeado de pantallas y flujo humano. | R2: 20–40 min | S2: Noche | T2: Todo el año | U2: Extremo | V2: Extremo | W2: 0 | X2: 0 | Y2: =W2*'Configuración'!$B$4 | Z2: =X2*'Configuración'!$B$4 | AA2: No | AB2: — | AC2: Espacio público 24 h | AD2: Sin cierre | AE2: JR/Metro Shibuya; salida Hachikō | AF2: Buena en áreas principales; confirmar detalles con el recinto | AG2: 35.6595 | AH2: 139.7005 | AI2: https://www.gotokyo.org/en/index.html | AJ2: Cambiante | AK2: MUST SEE | AL2: pareja, fotografía, ciudad, noche | AM2: 5 | AN2: 3 | AO2: 4 | AP2: 5 | AQ2: Imagen ideal: el movimiento colectivo, más que un monumento, es la atracción. con luz de noche, sin multitudes dominando el encuadre. | AR2: SHIBUYA SKY (~3 min a pie) | Shibuya PARCO + Nintendo TOKYO (~4 min a pie) | Cat Street (~14 min a pie) | AS2: Popular / turístico | AU2: https://www.google.com/maps/search/?api=1&query=Shibuya%20Crossing%2C%20Shibuya%2C%20Japan | AV2: 2026-09-01 | AW2: CALENDARIO / CONDICIÓN PENDIENTE | AX2: No hay cierre específico confirmado para la ventana, pero horarios o acceso pueden variar. | AY2: Reconfirmar en la web oficial al fijar fechas.
A3: JP-002 | B3: Tokio | C3: Kanto | D3: Tokio | E3: Shibuya | F3: Shibuya | G3: Shibuya | H3: SHIBUYA SKY | I3: 渋谷スカイ | J3: SHIBUYA SKY | K3: 🌅 Miradores | L3: mirador | M3: A | N3: La vista abierta y la posición sobre Shibuya justifican reservarlo. Clasificación v2: excelente y muy recomendable, pero no justifica por sí sola adaptar la ruta. | O3: Observatorio interior y azotea a 229 m sobre el cruce. | P3: La cubierta al aire libre produce una sensación más intensa que otros miradores. | Q3: Observatorio interior y azotea a 229 m sobre el cruce. | R3: 1–2 h | S3: Atardecer | T3: Todo el año; mejor visibilidad en invierno | U3: Extremo | V3: Extremo | W3: 2200 | X3: 3400 | Y3: =W3*'Configuración'!$B$4 | Z3: =X3*'Configuración'!$B$4 | AA3: Sí | AB3: 2–4 semanas; atardecer antes | AC3: Variable por fecha | AD3: Cierres meteorológicos de azotea | AE3: JR/Metro Shibuya, acceso directo | AF3: Buena en áreas principales; confirmar detalles con el recinto | AG3: 35.6585 | AH3: 139.7022 | AI3: https://www.shibuya-scramble-square.com/sky/ticket/en/ | AJ3: Cambiante | AK3: MUST SEE | AL3: pareja, fotografía, arquitectura, noche | AM3: 5 | AN3: 4 | AO3: 4 | AP3: 5 | AQ3: Imagen ideal: la cubierta al aire libre produce una sensación más intensa que otros miradores. con luz de atardecer, sin multitudes dominando el encuadre. | AR3: Shibuya Crossing (~3 min a pie) | Shibuya PARCO + Nintendo TOKYO (~7 min a pie) | Cat Street (~13 min a pie) | AS3: Popular / turístico | AU3: https://www.google.com/maps/search/?api=1&query=SHIBUYA%20SKY%2C%20Shibuya%2C%20Japan | AV3: 2026-09-01 | AW3: CALENDARIO / CONDICIÓN PENDIENTE | AX3: No hay cierre específico confirmado para la ventana, pero horarios o acceso pueden variar. | AY3: Reconfirmar en la web oficial al fijar fechas.
A4: JP-003 | B4: Tokio | C4: Kanto | D4: Tokio | E4: Shibuya | F4: Harajuku | G4: Harajuku–Meiji | H4: Meiji Jingu | I4: 明治神宮 | J4: Meiji Jingu | K4: ⛩️ Templos y santuarios | L4: santuario | M4: A | N4: El bosque y la escala ceremonial ofrecen un contraste esencial con Tokio. Clasificación v2: excelente y muy recomendable, pero no justifica por sí sola adaptar la ruta. | O4: Gran santuario sintoísta dentro de un bosque urbano denso. | P4: La transición inmediata del ruido de Harajuku al silencio forestal. | Q4: Gran santuario sintoísta dentro de un bosque urbano denso. | R4: 1–2 h | S4: Mañana | T4: Todo el año | U4: Alto | V4: Alto | W4: 0 | X4: 0 | Y4: =W4*'Configuración'!$B$4 | Z4: =X4*'Configuración'!$B$4 | AA4: No | AB4: — | AC4: Amanecer–atardecer; varía por mes | AD4: Sin cierre ordinario | AE4: JR Harajuku / Metro Meiji-jingumae | AF4: Parcial; pueden existir escalones, grava o edificios sin elevador | AG4: 35.6764 | AH4: 139.6993 | AI4: https://www.meijijingu.or.jp/en/ | AJ4: Cambiante | AK4: MUST SEE | AL4: pareja, cultura, naturaleza, fotografía | AM4: 4 | AN4: 4 | AO4: 5 | AP4: 4 | AQ4: Imagen ideal: la transición inmediata del ruido de harajuku al silencio forestal. con luz de mañana, sin multitudes dominando el encuadre. | AR4: Takeshita Street (~9 min a pie) | Ota Memorial Museum of Art (~12 min a pie) | Shinjuku Gyoen National Garden (~19 min a pie) | AS4: Popular / turístico | AU4: https://www.google.com/maps/search/?api=1&query=Meiji%20Jingu%2C%20Shibuya%2C%20Japan | AV4: 2026-09-01 | AW4: CALENDARIO / CONDICIÓN PENDIENTE | AX4: No hay cierre específico confirmado para la ventana, pero horarios o acceso pueden variar. | AY4: Reconfirmar en la web oficial al fijar fechas.
A5: JP-004 | B5: Tokio | C5: Kanto | D5: Tokio | E5: Shibuya | F5: Harajuku | G5: Harajuku–Meiji | H5: Takeshita Street | I5: 竹下通り | J5: Takeshita Street | K5: 🛍️ Compras | L5: calle comercial | M5: C | N5: Es famosa, pero las multitudes y tiendas repetitivas reducen el valor. | O5: Eje juvenil de moda, dulces y souvenirs. | P5: Concentra la estética kawaii más comercial en pocos cientos de metros. | Q5: Eje juvenil de moda, dulces y souvenirs. | R5: 30–60 min | S5: Mañana | T5: Todo el año | U5: Extremo | V5: Extremo | W5: 0 | X5: 0 | Y5: =W5*'Configuración'!$B$4 | Z5: =X5*'Configuración'!$B$4 | AA5: No | AB5: — | AC5: Tiendas aprox. 10:00–20:00 | AD5: Según comercio | AE5: JR Harajuku, salida Takeshita | AF5: Buena en áreas principales; confirmar detalles con el recinto | AG5: 35.6715 | AH5: 139.703 | AI5: https://www.gotokyo.org/en/index.html | AJ5: Cambiante | AK5: VIRAL / OPTIONAL | AL5: compras, cultura pop, fotografía | AM5: 4 | AN5: 2 | AO5: 2 | AP5: 5 | AQ5: Imagen ideal: concentra la estética kawaii más comercial en pocos cientos de metros. con luz de mañana, sin multitudes dominando el encuadre. | AR5: Ota Memorial Museum of Art (~3 min a pie) | Meiji Jingu (~9 min a pie) | Cat Street (~12 min a pie) | AS5: Alternativa menos saturada | AT5: Cat Street / Koenji | AU5: https://www.google.com/maps/search/?api=1&query=Takeshita%20Street%2C%20Shibuya%2C%20Japan | AV5: 2026-09-01 | AW5: CALENDARIO / CONDICIÓN PENDIENTE | AX5: No hay cierre específico confirmado para la ventana, pero horarios o acceso pueden variar. | AY5: Reconfirmar en la web oficial al fijar fechas.
A6: JP-005 | B6: Tokio | C6: Kanto | D6: Tokio | E6: Shibuya | F6: Jingumae | G6: Harajuku–Meiji | H6: Cat Street | I6: キャットストリート | J6: Cat Street | K6: 🏙️ Ciudad y barrios | L6: calle/barrio | M6: A | N6: Mejor paseo de moda urbana que Takeshita si se busca diseño y ambiente. | O6: Calle peatonal y callejones entre Harajuku y Shibuya. | P6: Boutiques, arquitectura y cafés con menos teatralidad turística. | Q6: Calle peatonal y callejones entre Harajuku y Shibuya. | R6: 1–2 h | S6: Tarde | T6: Todo el año | U6: Alto | V6: Medio | W6: 0 | X6: 0 | Y6: =W6*'Configuración'!$B$4 | Z6: =X6*'Configuración'!$B$4 | AA6: No | AB6: — | AC6: Espacio público; comercios variables | AD6: Sin cierre | AE6: Metro Meiji-jingumae / Shibuya | AF6: Buena en áreas principales; confirmar detalles con el recinto | AG6: 35.6652 | AH6: 139.7088 | AI6: https://www.gotokyo.org/en/index.html | AJ6: Cambiante | AK6: ALTERNATIVE | AL6: pareja, diseño, compras, fotografía | AM6: 4 | AN6: 4 | AO6: 5 | AP6: 3 | AQ6: Imagen ideal: boutiques, arquitectura y cafés con menos teatralidad turística. con luz de tarde, sin multitudes dominando el encuadre. | AR6: Ota Memorial Museum of Art (~10 min a pie) | Nezu Museum (~11 min a pie) | Takeshita Street (~12 min a pie) | AS6: Alternativa menos saturada | AT6: Takeshita Street | AU6: https://www.google.com/maps/search/?api=1&query=Cat%20Street%2C%20Shibuya%2C%20Japan | AV6: 2026-09-01 | AW6: CALENDARIO / CONDICIÓN PENDIENTE | AX6: No hay cierre específico confirmado para la ventana, pero horarios o acceso pueden variar. | AY6: Reconfirmar en la web oficial al fijar fechas.
A7: JP-006 | B7: Tokio | C7: Kanto | D7: Tokio | E7: Minato | F7: Aoyama | G7: Aoyama–Omotesando | H7: Nezu Museum | I7: 根津美術館 | J7: Nezu Museum | K7: 🎨 Arte | L7: museo y jardín | M7: A | N7: Colección refinada y uno de los jardines museísticos más bellos de la ciudad. | O7: Arte japonés y asiático en un edificio de Kengo Kuma con jardín privado. | P7: Une arquitectura contemporánea, antigüedades y paisaje en una visita compacta. | Q7: Arte japonés y asiático en un edificio de Kengo Kuma con jardín privado. | R7: 1.5–2.5 h | S7: Mañana | T7: Primavera y otoño | U7: Medio | V7: Medio | W7: 1500 | X7: 1800 | Y7: =W7*'Configuración'!$B$4 | Z7: =X7*'Configuración'!$B$4 | AA7: Recomendable | AB7: Días o semanas para exposición popular | AC7: 10:00–17:00 aprox.; verificar exposición | AD7: Lunes y montaje; verificar | AE7: Metro Omote-sando, 8–10 min a pie | AF7: Parcial; pueden existir escalones, grava o edificios sin elevador | AG7: 35.6622 | AH7: 139.7171 | AI7: https://www.nezu-muse.or.jp/en/ | AJ7: Cambiante | AK7: ART / GARDEN | AL7: pareja, arte, arquitectura, jardines | AM7: 5 | AN7: 5 | AO7: 5 | AP7: 2 | AQ7: Imagen ideal: une arquitectura contemporánea, antigüedades y paisaje en una visita compacta. con luz de mañana, sin multitudes dominando el encuadre. | AR7: Cat Street (~11 min a pie) | The National Art Center, Tokyo (~13 min a pie) | Mori Art Museum + Tokyo City View (~16 min a pie) | AS7: Semi-hidden | AU7: https://www.google.com/maps/search/?api=1&query=Nezu%20Museum%2C%20Minato%2C%20Japan | AV7: 2026-09-01 | AW7: CALENDARIO / CONDICIÓN PENDIENTE | AX7: No hay cierre específico confirmado para la ventana, pero horarios o acceso pueden variar. | AY7: Reconfirmar en la web oficial al fijar fechas.
A8: JP-007 | B8: Tokio | C8: Kanto | D8: Tokio | E8: Shibuya | F8: Harajuku | G8: Harajuku–Meiji | H8: Ota Memorial Museum of Art | I8: 太田記念美術館 | J8: Ota Memorial Museum of Art | K8: 🎨 Arte | L8: museo | M8: A | N8: Pequeño, especializado y excelente para comprender el ukiyo-e sin invertir medio día. | O8: Museo íntimo dedicado a grabados ukiyo-e con exposiciones rotativas. | P8: Especialización y escala humana junto al caos de Harajuku. | Q8: Museo íntimo dedicado a grabados ukiyo-e con exposiciones rotativas. | R8: 45–75 min | S8: Tarde | T8: Todo el año | U8: Bajo | V8: Bajo | W8: 1000 | X8: 1400 | Y8: =W8*'Configuración'!$B$4 | Z8: =X8*'Configuración'!$B$4 | AA8: No | AB8: — | AC8: 10:30–17:30 aprox.; verificar muestra | AD8: Cierres entre exposiciones | AE8: Metro Meiji-jingumae | AF8: Buena en áreas principales; confirmar detalles con el recinto | AG8: 35.6708 | AH8: 139.7054 | AI8: http://www.ukiyoe-ota-muse.jp/eng | AJ8: Cambiante | AK8: HIDDEN GEM | AL8: arte, cultura, lluvia | AM8: 3 | AN8: 5 | AO8: 5 | AP8: 1 | AQ8: Imagen ideal: especialización y escala humana junto al caos de harajuku. con luz de tarde, sin multitudes dominando el encuadre. | AR8: Takeshita Street (~3 min a pie) | Cat Street (~10 min a pie) | Meiji Jingu (~12 min a pie) | AS8: Hidden Gem real | AU8: https://www.google.com/maps/search/?api=1&query=Ota%20Memorial%20Museum%20of%20Art%2C%20Shibuya%2C%20Japan | AV8: 2026-09-01 | AW8: CALENDARIO / CONDICIÓN PENDIENTE | AX8: No hay cierre específico confirmado para la ventana, pero horarios o acceso pueden variar. | AY8: Reconfirmar en la web oficial al fijar fechas.
A9: JP-008 | B9: Tokio | C9: Kanto | D9: Tokio | E9: Shibuya | F9: Shibuya | G9: Shibuya | H9: Shibuya PARCO + Nintendo TOKYO | I9: 渋谷PARCO・Nintendo TOKYO | J9: Shibuya PARCO + Nintendo TOKYO | K9: 🎮 Videojuegos | L9: centro de cultura pop | M9: A | N9: Concentra Nintendo, Pokémon, Capcom y diseño en un solo edificio. | O9: Complejo comercial con tiendas oficiales y cultura pop japonesa. | P9: Es el nodo más eficiente para varias franquicias sin desplazamientos. | Q9: Complejo comercial con tiendas oficiales y cultura pop japonesa. | R9: 1.5–3 h | S9: Tarde | T9: Todo el año | U9: Extremo | V9: Alto | W9: 0 | X9: 0 | Y9: =W9*'Configuración'!$B$4 | Z9: =X9*'Configuración'!$B$4 | AA9: No | AB9: — | AC9: Aprox. 11:00–21:00; verificar | AD9: Según edificio | AE9: JR/Metro Shibuya | AF9: Buena en áreas principales; confirmar detalles con el recinto | AG9: 35.662 | AH9: 139.6988 | AI9: https://shibuya.parco.jp.e.aiv.hp.transer.com/ | AJ9: Cambiante | AK9: GAMING | AL9: videojuegos, anime, compras | AM9: 4 | AN9: 4 | AO9: 4 | AP9: 5 | AQ9: Imagen ideal: es el nodo más eficiente para varias franquicias sin desplazamientos. con luz de tarde, sin multitudes dominando el encuadre. | AR9: Shibuya Crossing (~4 min a pie) | SHIBUYA SKY (~7 min a pie) | Cat Street (~14 min a pie) | AS9: Popular / turístico | AU9: https://www.google.com/maps/search/?api=1&query=Shibuya%20PARCO%20%2B%20Nintendo%20TOKYO%2C%20Shibuya%2C%20Japan | AV9: 2026-09-01 | AW9: CALENDARIO / CONDICIÓN PENDIENTE | AX9: No hay cierre específico confirmado para la ventana, pero horarios o acceso pueden variar. | AY9: Reconfirmar en la web oficial al fijar fechas.
A10: JP-009 | B10: Tokio | C10: Kanto | D10: Tokio | E10: Shibuya | F10: Daikanyama | G10: Daikanyama–Ebisu | H10: Daikanyama T-SITE | I10: 代官山T-SITE | J10: Daikanyama T-SITE | K10: 🧩 Extraño/peculiar/único | L10: librería/arquitectura | M10: A | N10: Gran pausa de diseño, libros y café fuera de los circuitos más ruidosos. | O10: Conjunto de librerías y pabellones de arquitectura contemporánea. | P10: La experiencia de curaduría y espacio importa tanto como comprar. | Q10: Conjunto de librerías y pabellones de arquitectura contemporánea. | R10: 1–2 h | S10: Tarde | T10: Todo el año | U10: Medio | V10: Bajo | W10: 0 | X10: 0 | Y10: =W10*'Configuración'!$B$4 | Z10: =X10*'Configuración'!$B$4 | AA10: No | AB10: — | AC10: Aprox. 07:00–23:00; comercios varían | AD10: Sin cierre ordinario | AE10: Tokyu Daikanyama, 5 min | AF10: Buena en áreas principales; confirmar detalles con el recinto | AG10: 35.6488 | AH10: 139.6997 | AI10: https://store.tsite.jp/daikanyama/english/ | AJ10: Cambiante | AK10: HIDDEN GEM | AL10: pareja, diseño, libros, café | AM10: 4 | AN10: 5 | AO10: 5 | AP10: 2 | AQ10: Imagen ideal: la experiencia de curaduría y espacio importa tanto como comprar. con luz de tarde, sin multitudes dominando el encuadre. | AR10: SHIBUYA SKY (~15 min a pie) | Shibuya Crossing (~17 min a pie) | Shibuya PARCO + Nintendo TOKYO (~21 min a pie) | AS10: Semi-hidden | AU10: https://www.google.com/maps/search/?api=1&query=Daikanyama%20T-SITE%2C%20Shibuya%2C%20Japan | AV10: 2026-09-01 | AW10: CALENDARIO / CONDICIÓN PENDIENTE | AX10: No hay cierre específico confirmado para la ventana, pero horarios o acceso pueden variar. | AY10: Reconfirmar en la web oficial al fijar fechas.
A11: JP-010 | B11: Tokio | C11: Kanto | D11: Tokio | E11: Shinjuku | F11: Shinjuku | G11: Shinjuku | H11: Shinjuku Gyoen National Garden | I11: 新宿御苑 | J11: Shinjuku Gyoen National Garden | K11: 🌸 Jardines y paisajes | L11: jardín | M11: A | N11: El mejor gran jardín central para entender la escala y el contraste de Tokio. Clasificación v2: excelente y muy recomendable, pero no justifica por sí sola adaptar la ruta. | O11: Jardines japonés, inglés y francés bajo el skyline de Shinjuku. | P11: Combina paisaje formal y rascacielos con espacio suficiente para descansar. | Q11: Jardines japonés, inglés y francés bajo el skyline de Shinjuku. | R11: 2–3 h | S11: Mañana | T11: Sakura y otoño; bueno todo el año | U11: Alto | V11: Alto | W11: 500 | X11: 500 | Y11: =W11*'Configuración'!$B$4 | Z11: =X11*'Configuración'!$B$4 | AA11: No | AB11: — | AC11: 09:00–16:00/17:30 según temporada | AD11: Lunes y fechas especiales; verificar | AE11: Shinjuku-gyoemmae / Sendagaya | AF11: Parcial; pueden existir escalones, grava o edificios sin elevador | AG11: 35.6852 | AH11: 139.7101 | AI11: https://fng.or.jp/shinjuku/en/ | AJ11: Cambiante | AK11: MUST SEE | AL11: pareja, naturaleza, fotografía, descanso | AM11: 5 | AN11: 4 | AO11: 5 | AP11: 4 | AQ11: Imagen ideal: combina paisaje formal y rascacielos con espacio suficiente para descansar. con luz de mañana, sin multitudes dominando el encuadre. | AR11: Golden Gai (~15 min a pie) | Kabukicho (~17 min a pie) | Omoide Yokocho (~18 min a pie) | AS11: Popular / turístico | AU11: https://www.google.com/maps/search/?api=1&query=Shinjuku%20Gyoen%20National%20Garden%2C%20Shinjuku%2C%20Japan | AV11: 2026-09-01 | AW11: ABIERTO; FLORACIÓN NO GARANTIZADA | AX11: En Japón central la floración plena suele ser más tardía; finales de marzo es incierto. | AY11: No basar la visita en sakura hasta el pronóstico 2027.
A12: JP-011 | B12: Tokio | C12: Kanto | D12: Tokio | E12: Shinjuku | F12: Nishi-Shinjuku | G12: Shinjuku | H12: Tokyo Metropolitan Government Observatory | I12: 東京都庁展望室 | J12: Tokyo Metropolitan Government Observatory | K12: 🌅 Miradores | L12: mirador | M12: A | N12: La mejor vista gratuita de la ciudad y excelente respaldo si otros miradores se agotan. | O12: Observatorios gratuitos en las torres del gobierno metropolitano. | P12: Costo cero, vista amplia y proyección mapping nocturno cercana. | Q12: Observatorios gratuitos en las torres del gobierno metropolitano. | R12: 45–90 min | S12: Atardecer | T12: Invierno para Fuji | U12: Alto | V12: Medio | W12: 0 | X12: 0 | Y12: =W12*'Configuración'!$B$4 | Z12: =X12*'Configuración'!$B$4 | AA12: No | AB12: — | AC12: Variable; comprobar torre abierta | AD12: Cierres variables | AE12: Tochomae, acceso subterráneo | AF12: Buena en áreas principales; confirmar detalles con el recinto | AG12: 35.6896 | AH12: 139.6921 | AI12: https://www.yokoso.metro.tokyo.lg.jp/en/tenbou/ | AJ12: Cambiante | AK12: VALUE | AL12: fotografía, arquitectura, presupuesto | AM12: 4 | AN12: 3 | AO12: 5 | AP12: 3 | AQ12: Imagen ideal: costo cero, vista amplia y proyección mapping nocturno cercana. con luz de atardecer, sin multitudes dominando el encuadre. | AR12: Omoide Yokocho (~11 min a pie) | Kabukicho (~15 min a pie) | Golden Gai (~18 min a pie) | AS12: Alternativa menos saturada | AT12: SHIBUYA SKY | AU12: https://www.google.com/maps/search/?api=1&query=Tokyo%20Metropolitan%20Government%20Observatory%2C%20Shinjuku%2C%20Japan | AV12: 2026-09-01 | AW12: CALENDARIO / CONDICIÓN PENDIENTE | AX12: No hay cierre específico confirmado para la ventana, pero horarios o acceso pueden variar. | AY12: Reconfirmar en la web oficial al fijar fechas.
A13: JP-012 | B13: Tokio | C13: Kanto | D13: Tokio | E13: Shinjuku | F13: Kabukicho | G13: Shinjuku | H13: Kabukicho | I13: 歌舞伎町 | J13: Kabukicho | K13: 🌃 Nocturno | L13: barrio nocturno | M13: B | N13: Visualmente potente, pero conviene por ambiente y fotografía, no por atracciones concretas. | O13: Distrito de neón, ocio, cines, bares y enorme densidad peatonal. | P13: Es el Tokio nocturno más teatral y caótico. | Q13: Distrito de neón, ocio, cines, bares y enorme densidad peatonal. | R13: 1–2 h | S13: Noche | T13: Todo el año | U13: Extremo | V13: Extremo | W13: 0 | X13: 0 | Y13: =W13*'Configuración'!$B$4 | Z13: =X13*'Configuración'!$B$4 | AA13: No | AB13: — | AC13: Espacio público 24 h | AD13: Sin cierre | AE13: JR/Metro Shinjuku / Seibu-Shinjuku | AF13: Buena en áreas principales; confirmar detalles con el recinto | AG13: 35.6944 | AH13: 139.7028 | AI13: https://www.gotokyo.org/en/index.html | AJ13: Cambiante | AK13: NIGHT | AL13: pareja, fotografía, noche | AM13: 5 | AN13: 3 | AO13: 3 | AP13: 5 | AQ13: Imagen ideal: es el tokio nocturno más teatral y caótico. con luz de noche, sin multitudes dominando el encuadre. | AR13: Golden Gai (~3 min a pie) | Omoide Yokocho (~5 min a pie) | Tokyo Metropolitan Government Observatory (~15 min a pie) | AS13: Popular / turístico | AU13: https://www.google.com/maps/search/?api=1&query=Kabukicho%2C%20Shinjuku%2C%20Japan | AV13: 2026-09-01 | AW13: CALENDARIO / CONDICIÓN PENDIENTE | AX13: No hay cierre específico confirmado para la ventana, pero horarios o acceso pueden variar. | AY13: Reconfirmar en la web oficial al fijar fechas.
A14: JP-013 | B14: Tokio | C14: Kanto | D14: Tokio | E14: Shinjuku | F14: Kabukicho | G14: Shinjuku | H14: Golden Gai | I14: 新宿ゴールデン街 | J14: Golden Gai | K14: 🌃 Nocturno | L14: microbarrio de bares | M14: A | N14: Conserva una escala diminuta y un paisaje nocturno irrepetible. | O14: Red de callejones con cientos de bares minúsculos. | P14: La arquitectura apretada y el trato de barra no se replican en un distrito moderno. | Q14: Red de callejones con cientos de bares minúsculos. | R14: 1.5–3 h | S14: Noche | T14: Todo el año | U14: Alto | V14: Alto | W14: 1000 | X14: 5000 | Y14: =W14*'Configuración'!$B$4 | Z14: =X14*'Configuración'!$B$4 | AA14: Recomendable | AB14: Mismo día o pocos días en bares populares | AC14: Desde tarde hasta madrugada | AD14: Según bar | AE14: Shinjuku-sanchome / Seibu-Shinjuku | AF14: Buena en áreas principales; confirmar detalles con el recinto | AG14: 35.6941 | AH14: 139.7048 | AI14: https://www.gotokyo.org/en/index.html | AJ14: Cambiante | AK14: NIGHT | AL14: pareja, noche, fotografía, cultura local | AM14: 5 | AN14: 5 | AO14: 4 | AP14: 4 | AQ14: Imagen ideal: la arquitectura apretada y el trato de barra no se replican en un distrito moderno. con luz de noche, sin multitudes dominando el encuadre. | AR14: Kabukicho (~3 min a pie) | Omoide Yokocho (~7 min a pie) | Shinjuku Gyoen National Garden (~15 min a pie) | AS14: Popular / turístico | AU14: https://www.google.com/maps/search/?api=1&query=Golden%20Gai%2C%20Shinjuku%2C%20Japan | AV14: 2026-09-01 | AW14: CALENDARIO / CONDICIÓN PENDIENTE | AX14: No hay cierre específico confirmado para la ventana, pero horarios o acceso pueden variar. | AY14: Reconfirmar en la web oficial al fijar fechas.
A15: JP-014 | B15: Tokio | C15: Kanto | D15: Tokio | E15: Shinjuku | F15: Nishi-Shinjuku | G15: Shinjuku | H15: Omoide Yokocho | I15: 思い出横丁 | J15: Omoide Yokocho | K15: 🍜 Gastronomía | L15: callejón gastronómico | M15: B | N15: Atmosférico y cómodo, aunque hoy es muy turístico y pequeño. | O15: Callejones de yakitori y tabernas junto a las vías. | P15: Humo, escala y densidad visual de posguerra en pleno Shinjuku. | Q15: Callejones de yakitori y tabernas junto a las vías. | R15: 45–90 min | S15: Noche | T15: Todo el año | U15: Extremo | V15: Extremo | W15: 1500 | X15: 5000 | Y15: =W15*'Configuración'!$B$4 | Z15: =X15*'Configuración'!$B$4 | AA15: No | AB15: — | AC15: Según local, tarde–noche | AD15: Según local | AE15: JR Shinjuku, salida oeste | AF15: Buena en áreas principales; confirmar detalles con el recinto | AG15: 35.6929 | AH15: 139.6996 | AI15: https://www.gotokyo.org/en/index.html | AJ15: Cambiante | AK15: FOOD / NIGHT | AL15: comida, noche, fotografía | AM15: 5 | AN15: 3 | AO15: 3 | AP15: 5 | AQ15: Imagen ideal: humo, escala y densidad visual de posguerra en pleno shinjuku. con luz de noche, sin multitudes dominando el encuadre. | AR15: Kabukicho (~5 min a pie) | Golden Gai (~7 min a pie) | Tokyo Metropolitan Government Observatory (~11 min a pie) | AS15: Popular / turístico | AU15: https://www.google.com/maps/search/?api=1&query=Omoide%20Yokocho%2C%20Shinjuku%2C%20Japan | AV15: 2026-09-01 | AW15: CALENDARIO / CONDICIÓN PENDIENTE | AX15: No hay cierre específico confirmado para la ventana, pero horarios o acceso pueden variar. | AY15: Reconfirmar en la web oficial al fijar fechas.
A16: JP-015 | B16: Tokio | C16: Kanto | D16: Tokio | E16: Shinjuku | F16: Kagurazaka | G16: Kagurazaka | H16: Kagurazaka backstreets | I16: 神楽坂 | J16: Kagurazaka backstreets | K16: 🏙️ Ciudad y barrios | L16: barrio | M16: A | N16: Alternativa elegante y menos obvia a los barrios tradicionales más saturados. | O16: Pendiente principal y callejones de piedra con restaurantes y antiguas casas de geisha. | P16: Mezcla herencia japonesa, influencia francesa y vida residencial. | Q16: Pendiente principal y callejones de piedra con restaurantes y antiguas casas de geisha. | R16: 2–3 h | S16: Tarde | T16: Todo el año | U16: Medio | V16: Bajo | W16: 0 | X16: 0 | Y16: =W16*'Configuración'!$B$4 | Z16: =X16*'Configuración'!$B$4 | AA16: No | AB16: — | AC16: Espacio público; negocios variables | AD16: Sin cierre | AE16: Iidabashi / Kagurazaka | AF16: Buena en áreas principales; confirmar detalles con el recinto | AG16: 35.7016 | AH16: 139.7403 | AI16: https://www.gotokyo.org/en/index.html | AJ16: Cambiante | AK16: HIDDEN GEM | AL16: pareja, comida, arquitectura, noche | AM16: 4 | AN16: 5 | AO16: 5 | AP16: 2 | AQ16: Imagen ideal: mezcla herencia japonesa, influencia francesa y vida residencial. con luz de tarde, sin multitudes dominando el encuadre. | AR16: Jimbocho Book Town (~24 min a pie) | Imperial Palace East Gardens (~30 min en transporte) | Kanda Myojin (~35 min en transporte) | AS16: Semi-hidden | AU16: https://www.google.com/maps/search/?api=1&query=Kagurazaka%20backstreets%2C%20Shinjuku%2C%20Japan | AV16: 2026-09-01 | AW16: CALENDARIO / CONDICIÓN PENDIENTE | AX16: No hay cierre específico confirmado para la ventana, pero horarios o acceso pueden variar. | AY16: Reconfirmar en la web oficial al fijar fechas.
A17: JP-016 | B17: Tokio | C17: Kanto | D17: Tokio | E17: Taito | F17: Asakusa | G17: Asakusa | H17: Sensō-ji | I17: 浅草寺 | J17: Sensō-ji | K17: ⛩️ Templos y santuarios | L17: templo | M17: A | N17: Icono histórico con escala, rituales y vida de barrio que justifican la multitud. Clasificación v2: excelente y muy recomendable, pero no justifica por sí sola adaptar la ruta. | O17: El templo budista más antiguo de Tokio, con Kaminarimon y gran recinto. | P17: La experiencia cambia radicalmente antes de abrir comercios y por la noche. | Q17: El templo budista más antiguo de Tokio, con Kaminarimon y gran recinto. | R17: 1–2 h | S17: Mañana | T17: Todo el año | U17: Extremo | V17: Extremo | W17: 0 | X17: 0 | Y17: =W17*'Configuración'!$B$4 | Z17: =X17*'Configuración'!$B$4 | AA17: No | AB17: — | AC17: Recinto exterior 24 h; salón aprox. 06:00–17:00 | AD17: Sin cierre ordinario | AE17: Metro Asakusa | AF17: Parcial; pueden existir escalones, grava o edificios sin elevador | AG17: 35.7148 | AH17: 139.7967 | AI17: https://www.senso-ji.jp/english/ | AJ17: Cambiante | AK17: MUST SEE | AL17: cultura, fotografía, historia | AM17: 5 | AN17: 4 | AO17: 5 | AP17: 5 | AQ17: Imagen ideal: la experiencia cambia radicalmente antes de abrir comercios y por la noche. con luz de mañana, sin multitudes dominando el encuadre. | AR17: Asakusa Culture Tourist Information Center (~6 min a pie) | Kappabashi Kitchen Town (~10 min a pie) | Tokyo Skytree (~19 min a pie) | AS17: Popular / turístico | AU17: https://www.google.com/maps/search/?api=1&query=Sens%C5%8D-ji%2C%20Taito%2C%20Japan | AV17: 2026-09-01 | AW17: CALENDARIO / CONDICIÓN PENDIENTE | AX17: No hay cierre específico confirmado para la ventana, pero horarios o acceso pueden variar. | AY17: Reconfirmar en la web oficial al fijar fechas.
A18: JP-017 | B18: Tokio | C18: Kanto | D18: Tokio | E18: Taito | F18: Asakusa | G18: Asakusa | H18: Asakusa Culture Tourist Information Center | I18: 浅草文化観光センター | J18: Asakusa Culture Tourist Information Center | K18: 🌅 Miradores | L18: centro/mirador | M18: A | N18: Vista gratuita y perfectamente situada sobre Kaminarimon y Nakamise. | O18: Centro de información de Kengo Kuma con terraza panorámica. | P18: Permite leer la geometría de Asakusa sin pagar observatorio. | Q18: Centro de información de Kengo Kuma con terraza panorámica. | R18: 20–45 min | S18: Atardecer | T18: Todo el año | U18: Medio | V18: Medio | W18: 0 | X18: 0 | Y18: =W18*'Configuración'!$B$4 | Z18: =X18*'Configuración'!$B$4 | AA18: No | AB18: — | AC18: Aprox. 09:00–20:00 | AD18: Sin cierre ordinario | AE18: Metro Asakusa, frente a Kaminarimon | AF18: Buena en áreas principales; confirmar detalles con el recinto | AG18: 35.7107 | AH18: 139.7966 | AI18: https://www.city.taito.lg.jp/bunka_kanko/kankoinfo/info/oyakudachi/kankocenter/a-tic-gaiyo.html | AJ18: Cambiante | AK18: VALUE | AL18: arquitectura, fotografía, presupuesto | AM18: 4 | AN18: 4 | AO18: 5 | AP18: 2 | AQ18: Imagen ideal: permite leer la geometría de asakusa sin pagar observatorio. con luz de atardecer, sin multitudes dominando el encuadre. | AR18: Sensō-ji (~6 min a pie) | Kappabashi Kitchen Town (~13 min a pie) | Tokyo Skytree (~18 min a pie) | AS18: Hidden Gem real | AU18: https://www.google.com/maps/search/?api=1&query=Asakusa%20Culture%20Tourist%20Information%20Center%2C%20Taito%2C%20Japan | AV18: 2026-09-01 | AW18: CALENDARIO / CONDICIÓN PENDIENTE | AX18: No hay cierre específico confirmado para la ventana, pero horarios o acceso pueden variar. | AY18: Reconfirmar en la web oficial al fijar fechas.
A19: JP-018 | B19: Tokio | C19: Kanto | D19: Tokio | E19: Taito | F19: Kappabashi | G19: Asakusa | H19: Kappabashi Kitchen Town | I19: かっぱ橋道具街 | J19: Kappabashi Kitchen Town | K19: 🛍️ Compras | L19: calle comercial especializada | M19: A | N19: Especialización real y objetos japoneses útiles, no solo recuerdos genéricos. | O19: Distrito de cuchillos, cerámica, utensilios y comida de plástico. | P19: Muestra la infraestructura de la gastronomía japonesa. | Q19: Distrito de cuchillos, cerámica, utensilios y comida de plástico. | R19: 1.5–3 h | S19: Tarde | T19: Días laborables | U19: Medio | V19: Medio | W19: 0 | X19: 0 | Y19: =W19*'Configuración'!$B$4 | Z19: =X19*'Configuración'!$B$4 | AA19: No | AB19: — | AC19: Mayoría 09:00–17:00 | AD19: Muchos domingos/festivos | AE19: Tawaramachi / Asakusa | AF19: Buena en áreas principales; confirmar detalles con el recinto | AG19: 35.7157 | AH19: 139.7885 | AI19: https://www.kappabashi.or.jp/en/ | AJ19: Cambiante | AK19: HIDDEN GEM | AL19: comida, compras, diseño | AM19: 4 | AN19: 5 | AO19: 5 | AP19: 2 | AQ19: Imagen ideal: muestra la infraestructura de la gastronomía japonesa. con luz de tarde, sin multitudes dominando el encuadre. | AR19: Sensō-ji (~10 min a pie) | Asakusa Culture Tourist Information Center (~13 min a pie) | Tokyo National Museum (~16 min a pie) | AS19: Semi-hidden | AU19: https://www.google.com/maps/search/?api=1&query=Kappabashi%20Kitchen%20Town%2C%20Taito%2C%20Japan | AV19: 2026-09-01 | AW19: CALENDARIO / CONDICIÓN PENDIENTE | AX19: No hay cierre específico confirmado para la ventana, pero horarios o acceso pueden variar. | AY19: Reconfirmar en la web oficial al fijar fechas.
A20: JP-019 | B20: Tokio | C20: Kanto | D20: Tokio | E20: Sumida | F20: Oshiage | G20: Skytree–Sumida | H20: Tokyo Skytree | I20: 東京スカイツリー | J20: Tokyo Skytree | K20: 🌅 Miradores | L20: torre/mirador | M20: B | N20: La mayor altura y vistas lejanas compensan el entorno comercial, pero no es la más emocional. Clasificación v2: recomendable si encaja; su valor depende más de interés, saturación o logística. | O20: Torre de radiodifusión con dos observatorios a 350 y 450 m. | P20: Ningún otro mirador urbano del país alcanza su altura. | Q20: Torre de radiodifusión con dos observatorios a 350 y 450 m. | R20: 1.5–2.5 h | S20: Atardecer | T20: Invierno | U20: Extremo | V20: Extremo | W20: 2100 | X20: 3400 | Y20: =W20*'Configuración'!$B$4 | Z20: =X20*'Configuración'!$B$4 | AA20: Recomendable | AB20: 1–2 semanas | AC20: Variable por fecha | AD20: Sin cierre ordinario; clima | AE20: Oshiage / Tokyo Skytree | AF20: Buena en áreas principales; confirmar detalles con el recinto | AG20: 35.7101 | AH20: 139.8107 | AI20: https://www.tokyo-skytree.jp/en/ | AJ20: Cambiante | AK20: ICON | AL20: fotografía, arquitectura, altura | AM20: 5 | AN20: 4 | AO20: 3 | AP20: 5 | AQ20: Imagen ideal: ningún otro mirador urbano del país alcanza su altura. con luz de atardecer, sin multitudes dominando el encuadre. | AR20: Asakusa Culture Tourist Information Center (~18 min a pie) | Sensō-ji (~19 min a pie) | The Sumida Hokusai Museum (~25 min a pie) | AS20: Popular / turístico | AU20: https://www.google.com/maps/search/?api=1&query=Tokyo%20Skytree%2C%20Sumida%2C%20Japan | AV20: 2026-09-01 | AW20: CALENDARIO / CONDICIÓN PENDIENTE | AX20: No hay cierre específico confirmado para la ventana, pero horarios o acceso pueden variar. | AY20: Reconfirmar en la web oficial al fijar fechas.
A21: JP-020 | B21: Tokio | C21: Kanto | D21: Tokio | E21: Sumida | F21: Ryogoku | G21: Skytree–Sumida | H21: The Sumida Hokusai Museum | I21: すみだ北斎美術館 | J21: The Sumida Hokusai Museum | K21: 🎨 Arte | L21: museo | M21: A | N21: Museo especializado con gran arquitectura y relación directa con el barrio natal de Hokusai. | O21: Colección y exposiciones sobre Katsushika Hokusai. | P21: Contexto local y edificio de Kazuyo Sejima. | Q21: Colección y exposiciones sobre Katsushika Hokusai. | R21: 1–2 h | S21: Tarde | T21: Todo el año | U21: Bajo | V21: Bajo | W21: 400 | X21: 1500 | Y21: =W21*'Configuración'!$B$4 | Z21: =X21*'Configuración'!$B$4 | AA21: No | AB21: — | AC21: 09:30–17:30 aprox. | AD21: Lunes; verificar | AE21: JR/Toei Ryogoku | AF21: Buena en áreas principales; confirmar detalles con el recinto | AG21: 35.6963 | AH21: 139.8005 | AI21: https://hokusai-museum.jp/?lang=en | AJ21: Cambiante | AK21: HIDDEN GEM | AL21: arte, arquitectura, cultura | AM21: 4 | AN21: 5 | AO21: 5 | AP21: 1 | AQ21: Imagen ideal: contexto local y edificio de kazuyo sejima. con luz de tarde, sin multitudes dominando el encuadre. | AR21: Edo-Tokyo Museum (~5 min a pie) | Asakusa Culture Tourist Information Center (~23 min a pie) | Tokyo Skytree (~25 min a pie) | AS21: Hidden Gem real | AU21: https://www.google.com/maps/search/?api=1&query=The%20Sumida%20Hokusai%20Museum%2C%20Sumida%2C%20Japan | AV21: 2026-09-01 | AW21: CALENDARIO / CONDICIÓN PENDIENTE | AX21: No hay cierre específico confirmado para la ventana, pero horarios o acceso pueden variar. | AY21: Reconfirmar en la web oficial al fijar fechas.
A22: JP-021 | B22: Tokio | C22: Kanto | D22: Tokio | E22: Taito | F22: Ueno | G22: Ueno–Yanaka | H22: Tokyo National Museum | I22: 東京国立博物館 | J22: Tokyo National Museum | K22: 🏛️ Museos | L22: museo nacional | M22: S | N22: La mejor introducción concentrada al arte y patrimonio material japonés. | O22: El museo más antiguo de Japón con colecciones nacionales y asiáticas. | P22: Calidad y amplitud muy superiores a una visita rápida de templo en templo. | Q22: El museo más antiguo de Japón con colecciones nacionales y asiáticas. | R22: 3–5 h | S22: Mañana | T22: Todo el año | U22: Alto | V22: Alto | W22: 1000 | X22: 2200 | Y22: =W22*'Configuración'!$B$4 | Z22: =X22*'Configuración'!$B$4 | AA22: Recomendable | AB22: Días/semanas para exposiciones | AC22: 09:30–17:00 aprox. | AD22: Lunes; verificar | AE22: JR/Metro Ueno | AF22: Buena en áreas principales; confirmar detalles con el recinto | AG22: 35.7188 | AH22: 139.7765 | AI22: https://www.tnm.jp/?lang=en | AJ22: Cambiante | AK22: MUST SEE | AL22: historia, arte, cultura, lluvia | AM22: 4 | AN22: 5 | AO22: 5 | AP22: 4 | AQ22: Imagen ideal: calidad y amplitud muy superiores a una visita rápida de templo en templo. con luz de mañana, sin multitudes dominando el encuadre. | AR22: Ameyoko (~14 min a pie) | Kappabashi Kitchen Town (~16 min a pie) | Yanaka Ginza and cemetery lanes (~18 min a pie) | AS22: Popular / turístico | AU22: https://www.google.com/maps/search/?api=1&query=Tokyo%20National%20Museum%2C%20Taito%2C%20Japan | AV22: 2026-09-01 | AW22: CALENDARIO / CONDICIÓN PENDIENTE | AX22: No hay cierre específico confirmado para la ventana, pero horarios o acceso pueden variar. | AY22: Reconfirmar en la web oficial al fijar fechas.
A23: JP-022 | B23: Tokio | C23: Kanto | D23: Tokio | E23: Taito | F23: Ueno | G23: Ueno–Yanaka | H23: Ameyoko | I23: アメ横 | J23: Ameyoko | K23: 🛍️ Compras | L23: mercado/calle | M23: B | N23: Gran energía popular, aunque parte de la oferta es genérica y muy turística. | O23: Mercado callejero bajo y junto a las vías entre Ueno y Okachimachi. | P23: Mezcla alimentos, ropa, tiendas asiáticas y ruido urbano. | Q23: Mercado callejero bajo y junto a las vías entre Ueno y Okachimachi. | R23: 1–2 h | S23: Tarde | T23: Todo el año | U23: Extremo | V23: Alto | W23: 0 | X23: 0 | Y23: =W23*'Configuración'!$B$4 | Z23: =X23*'Configuración'!$B$4 | AA23: No | AB23: — | AC23: Según comercio | AD23: Según comercio | AE23: Ueno / Okachimachi | AF23: Buena en áreas principales; confirmar detalles con el recinto | AG23: 35.7102 | AH23: 139.7748 | AI23: https://www.gotokyo.org/en/index.html | AJ23: Cambiante | AK23: STREET | AL23: comida, compras, fotografía | AM23: 4 | AN23: 3 | AO23: 4 | AP23: 4 | AQ23: Imagen ideal: mezcla alimentos, ropa, tiendas asiáticas y ruido urbano. con luz de tarde, sin multitudes dominando el encuadre. | AR23: Tokyo National Museum (~14 min a pie) | Kanda Myojin (~15 min a pie) | Retro game hunt: Super Potato + Mandarake (~16 min a pie) | AS23: Popular / turístico | AU23: https://www.google.com/maps/search/?api=1&query=Ameyoko%2C%20Taito%2C%20Japan | AV23: 2026-09-01 | AW23: CALENDARIO / CONDICIÓN PENDIENTE | AX23: No hay cierre específico confirmado para la ventana, pero horarios o acceso pueden variar. | AY23: Reconfirmar en la web oficial al fijar fechas.
A24: JP-023 | B24: Tokio | C24: Kanto | D24: Tokio | E24: Taito | F24: Yanaka | G24: Ueno–Yanaka | H24: Yanaka Ginza and cemetery lanes | I24: 谷中銀座・谷中霊園 | J24: Yanaka Ginza and cemetery lanes | K24: 🏙️ Ciudad y barrios | L24: barrio/paseo | M24: A | N24: Shitamachi tranquilo, vivido y fotogénico sin parecer un decorado. | O24: Calle comercial baja, templos, cementerio y casas antiguas. | P24: Conserva escala residencial previa a los rascacielos. | Q24: Calle comercial baja, templos, cementerio y casas antiguas. | R24: 2–3 h | S24: Tarde | T24: Primavera y otoño | U24: Medio | V24: Medio | W24: 0 | X24: 0 | Y24: =W24*'Configuración'!$B$4 | Z24: =X24*'Configuración'!$B$4 | AA24: No | AB24: — | AC24: Espacio público; tiendas variables | AD24: Sin cierre | AE24: Nippori / Sendagi | AF24: Buena en áreas principales; confirmar detalles con el recinto | AG24: 35.7275 | AH24: 139.7668 | AI24: https://www.gotokyo.org/en/index.html | AJ24: Cambiante | AK24: HIDDEN GEM | AL24: pareja, fotografía, barrios, comida | AM24: 4 | AN24: 5 | AO24: 5 | AP24: 2 | AQ24: Imagen ideal: conserva escala residencial previa a los rascacielos. con luz de tarde, sin multitudes dominando el encuadre. | AR24: Nezu Shrine (~14 min a pie) | Tokyo National Museum (~18 min a pie) | Ameyoko (~29 min en transporte) | AS24: Semi-hidden | AU24: https://www.google.com/maps/search/?api=1&query=Yanaka%20Ginza%20and%20cemetery%20lanes%2C%20Taito%2C%20Japan | AV24: 2026-09-01 | AW24: CALENDARIO / CONDICIÓN PENDIENTE | AX24: No hay cierre específico confirmado para la ventana, pero horarios o acceso pueden variar. | AY24: Reconfirmar en la web oficial al fijar fechas.
A25: JP-024 | B25: Tokio | C25: Kanto | D25: Tokio | E25: Bunkyo | F25: Nezu | G25: Ueno–Yanaka | H25: Nezu Shrine | I25: 根津神社 | J25: Nezu Shrine | K25: ⛩️ Templos y santuarios | L25: santuario | M25: A | N25: Santuario histórico con túnel de torii y azaleas, mucho menos saturado que Fushimi Inari. | O25: Recinto Edo con estanques, torii rojos y jardín de azaleas. | P25: Ofrece imágenes de torii en un entorno local compacto. | Q25: Recinto Edo con estanques, torii rojos y jardín de azaleas. | R25: 45–90 min | S25: Mañana | T25: Abril–mayo para azaleas | U25: Medio | V25: Bajo | W25: 0 | X25: 500 | Y25: =W25*'Configuración'!$B$4 | Z25: =X25*'Configuración'!$B$4 | AA25: No | AB25: — | AC25: Aprox. 06:00–17:00 | AD25: Sin cierre ordinario | AE25: Nezu / Sendagi | AF25: Parcial; pueden existir escalones, grava o edificios sin elevador | AG25: 35.7202 | AH25: 139.7609 | AI25: https://www.nedujinja.or.jp/ | AJ25: Cambiante | AK25: ALTERNATIVE | AL25: cultura, fotografía, flores | AM25: 4 | AN25: 5 | AO25: 5 | AP25: 2 | AQ25: Imagen ideal: ofrece imágenes de torii en un entorno local compacto. con luz de mañana, sin multitudes dominando el encuadre. | AR25: Yanaka Ginza and cemetery lanes (~14 min a pie) | Tokyo National Museum (~20 min a pie) | Ameyoko (~23 min a pie) | AS25: Alternativa menos saturada | AT25: Fushimi Inari (escala mucho menor) | AU25: https://www.google.com/maps/search/?api=1&query=Nezu%20Shrine%2C%20Bunkyo%2C%20Japan | AV25: 2026-09-01 | AW25: CALENDARIO / CONDICIÓN PENDIENTE | AX25: No hay cierre específico confirmado para la ventana, pero horarios o acceso pueden variar. | AY25: Reconfirmar en la web oficial al fijar fechas.
A26: JP-025 | B26: Tokio | C26: Kanto | D26: Tokio | E26: Chiyoda | F26: Akihabara | G26: Akihabara–Kanda | H26: Akihabara Electric Town | I26: 秋葉原電気街 | J26: Akihabara Electric Town | K26: 👾 Anime/manga | L26: barrio | M26: S | N26: Sigue siendo el ecosistema pop más denso y singular para gaming, anime y electrónica. | O26: Calles de tiendas, arcades, figuras, manga, PC y cultura otaku. | P26: La variedad exige explorar edificios y callejones, no solo Chuo-dori. | Q26: Calles de tiendas, arcades, figuras, manga, PC y cultura otaku. | R26: 3–6 h | S26: Tarde | T26: Todo el año | U26: Extremo | V26: Extremo | W26: 0 | X26: 0 | Y26: =W26*'Configuración'!$B$4 | Z26: =X26*'Configuración'!$B$4 | AA26: No | AB26: — | AC26: Tiendas aprox. 10:00–21:00 | AD26: Según comercio | AE26: JR/Metro Akihabara | AF26: Buena en áreas principales; confirmar detalles con el recinto | AG26: 35.6984 | AH26: 139.7731 | AI26: https://www.gotokyo.org/en/spot/55/index.html | AJ26: Cambiante | AK26: MUST SEE / ANIME | AL26: videojuegos, anime, compras, tecnología | AM26: 5 | AN26: 5 | AO26: 4 | AP26: 5 | AQ26: Imagen ideal: la variedad exige explorar edificios y callejones, no solo chuo-dori. con luz de tarde, sin multitudes dominando el encuadre. | AR26: Retro game hunt: Super Potato + Mandarake (~4 min a pie) | Kanda Myojin (~9 min a pie) | Ameyoko (~18 min a pie) | AS26: Popular / turístico | AU26: https://www.google.com/maps/search/?api=1&query=Akihabara%20Electric%20Town%2C%20Chiyoda%2C%20Japan | AV26: 2026-09-01 | AW26: CALENDARIO / CONDICIÓN PENDIENTE | AX26: No hay cierre específico confirmado para la ventana, pero horarios o acceso pueden variar. | AY26: Reconfirmar en la web oficial al fijar fechas.
A27: JP-026 | B27: Tokio | C27: Kanto | D27: Tokio | E27: Chiyoda | F27: Akihabara | G27: Akihabara–Kanda | H27: Retro game hunt: Super Potato + Mandarake | I27: スーパーポテト・まんだらけ | J27: Retro game hunt: Super Potato + Mandarake | K27: 🎮 Videojuegos | L27: experiencia de compras | M27: A | N27: Excelente para historia material del videojuego, aunque precios de coleccionista pueden ser altos. | O27: Búsqueda de consolas, cartuchos, revistas, figuras y memorabilia retro. | P27: Permite comparar varias generaciones de cultura de juego japonesa. | Q27: Búsqueda de consolas, cartuchos, revistas, figuras y memorabilia retro. | R27: 1.5–3 h | S27: Tarde | T27: Todo el año | U27: Alto | V27: Alto | W27: 0 | X27: 0 | Y27: =W27*'Configuración'!$B$4 | Z27: =X27*'Configuración'!$B$4 | AA27: No | AB27: — | AC27: Según tienda, aprox. 11:00–20:00 | AD27: Según tienda | AE27: JR Akihabara | AF27: Buena en áreas principales; confirmar detalles con el recinto | AG27: 35.7005 | AH27: 139.7714 | AI27: https://www.gotokyo.org/en/index.html | AJ27: Cambiante | AK27: GAMING | AL27: videojuegos, compras, nostalgia | AM27: 4 | AN27: 5 | AO27: 4 | AP27: 4 | AQ27: Imagen ideal: permite comparar varias generaciones de cultura de juego japonesa. con luz de tarde, sin multitudes dominando el encuadre. | AR27: Akihabara Electric Town (~4 min a pie) | Kanda Myojin (~5 min a pie) | Ameyoko (~16 min a pie) | AS27: Popular / turístico | AU27: https://www.google.com/maps/search/?api=1&query=Retro%20game%20hunt%3A%20Super%20Potato%20%2B%20Mandarake%2C%20Chiyoda%2C%20Japan | AV27: 2026-09-01 | AW27: CALENDARIO / CONDICIÓN PENDIENTE | AX27: No hay cierre específico confirmado para la ventana, pero horarios o acceso pueden variar. | AY27: Reconfirmar en la web oficial al fijar fechas.
A28: JP-027 | B28: Tokio | C28: Kanto | D28: Tokio | E28: Chiyoda | F28: Kanda | G28: Akihabara–Kanda | H28: Kanda Myojin | I28: 神田明神 | J28: Kanda Myojin | K28: ⛩️ Templos y santuarios | L28: santuario | M28: A | N28: Puente convincente entre tradición, negocios y cultura anime. | O28: Santuario histórico protector de Kanda y Akihabara. | P28: Vende amuletos de tecnología y colabora con franquicias pop. | Q28: Santuario histórico protector de Kanda y Akihabara. | R28: 45–75 min | S28: Mañana | T28: Todo el año | U28: Medio | V28: Medio | W28: 0 | X28: 0 | Y28: =W28*'Configuración'!$B$4 | Z28: =X28*'Configuración'!$B$4 | AA28: No | AB28: — | AC28: Recinto amplio; oficinas diurnas | AD28: Sin cierre ordinario | AE28: Ochanomizu / Suehirocho | AF28: Parcial; pueden existir escalones, grava o edificios sin elevador | AG28: 35.702 | AH28: 139.7679 | AI28: https://www.kandamyoujin.or.jp/english/ | AJ28: Cambiante | AK28: CULTURE + TECH | AL28: anime, cultura, fotografía | AM28: 4 | AN28: 5 | AO28: 5 | AP28: 2 | AQ28: Imagen ideal: vende amuletos de tecnología y colabora con franquicias pop. con luz de mañana, sin multitudes dominando el encuadre. | AR28: Retro game hunt: Super Potato + Mandarake (~5 min a pie) | Akihabara Electric Town (~9 min a pie) | Ameyoko (~15 min a pie) | AS28: Semi-hidden | AU28: https://www.google.com/maps/search/?api=1&query=Kanda%20Myojin%2C%20Chiyoda%2C%20Japan | AV28: 2026-09-01 | AW28: CALENDARIO / CONDICIÓN PENDIENTE | AX28: No hay cierre específico confirmado para la ventana, pero horarios o acceso pueden variar. | AY28: Reconfirmar en la web oficial al fijar fechas.
A29: JP-028 | B29: Tokio | C29: Kanto | D29: Tokio | E29: Chiyoda | F29: Jimbocho | G29: Jimbocho | H29: Jimbocho Book Town | I29: 神保町古書店街 | J29: Jimbocho Book Town | K29: 🛍️ Compras | L29: barrio de librerías | M29: A | N29: Especialización y atmósfera intelectual difíciles de encontrar en otra megaciudad. | O29: Centenares de librerías nuevas, usadas, mapas, cine y arte. | P29: Los escaparates y cafés conservan una cultura urbana no diseñada para turistas. | Q29: Centenares de librerías nuevas, usadas, mapas, cine y arte. | R29: 2–4 h | S29: Tarde | T29: Días laborables/sábado | U29: Bajo | V29: Bajo | W29: 0 | X29: 0 | Y29: =W29*'Configuración'!$B$4 | Z29: =X29*'Configuración'!$B$4 | AA29: No | AB29: — | AC29: Tiendas aprox. 10:00–19:00 | AD29: Muchos domingos | AE29: Metro Jimbocho | AF29: Buena en áreas principales; confirmar detalles con el recinto | AG29: 35.6956 | AH29: 139.7576 | AI29: https://www.gotokyo.org/en/index.html | AJ29: Cambiante | AK29: HIDDEN GEM | AL29: libros, arte, cafés, lluvia | AM29: 3 | AN29: 5 | AO29: 5 | AP29: 1 | AQ29: Imagen ideal: los escaparates y cafés conservan una cultura urbana no diseñada para turistas. con luz de tarde, sin multitudes dominando el encuadre. | AR29: Kanda Myojin (~16 min a pie) | Imperial Palace East Gardens (~17 min a pie) | Retro game hunt: Super Potato + Mandarake (~19 min a pie) | AS29: Hidden Gem real | AU29: https://www.google.com/maps/search/?api=1&query=Jimbocho%20Book%20Town%2C%20Chiyoda%2C%20Japan | AV29: 2026-09-01 | AW29: CALENDARIO / CONDICIÓN PENDIENTE | AX29: No hay cierre específico confirmado para la ventana, pero horarios o acceso pueden variar. | AY29: Reconfirmar en la web oficial al fijar fechas.
A30: JP-029 | B30: Tokio | C30: Kanto | D30: Tokio | E30: Chiyoda | F30: Marunouchi | G30: Marunouchi–Ginza | H30: Imperial Palace East Gardens | I30: 皇居東御苑 | J30: Imperial Palace East Gardens | K30: 🌸 Jardines y paisajes | L30: jardín histórico | M30: A | N30: Paisaje, murallas y vacío urbano de gran escala sin costo. | O30: Jardines del antiguo Edo Castle dentro del recinto imperial. | P30: Permite entender la topografía política de Tokio. | Q30: Jardines del antiguo Edo Castle dentro del recinto imperial. | R30: 1.5–2.5 h | S30: Mañana | T30: Primavera y otoño | U30: Medio | V30: Medio | W30: 0 | X30: 0 | Y30: =W30*'Configuración'!$B$4 | Z30: =X30*'Configuración'!$B$4 | AA30: No | AB30: — | AC30: 09:00–16:30/17:00 según temporada | AD30: Lunes, viernes y actos; verificar | AE30: Otemachi / Takebashi | AF30: Parcial; pueden existir escalones, grava o edificios sin elevador | AG30: 35.6852 | AH30: 139.7528 | AI30: https://www.kunaicho.go.jp/e-event/higashigyoen.html | AJ30: Cambiante | AK30: HISTORY | AL30: historia, jardines, fotografía | AM30: 4 | AN30: 4 | AO30: 5 | AP30: 2 | AQ30: Imagen ideal: permite entender la topografía política de tokio. con luz de mañana, sin multitudes dominando el encuadre. | AR30: Jimbocho Book Town (~17 min a pie) | Tokyo Station Marunouchi Building (~19 min a pie) | Kagurazaka backstreets (~30 min en transporte) | AS30: Lugar conocido pero excelente | AU30: https://www.google.com/maps/search/?api=1&query=Imperial%20Palace%20East%20Gardens%2C%20Chiyoda%2C%20Japan | AV30: 2026-09-01 | AW30: CALENDARIO / CONDICIÓN PENDIENTE | AX30: No hay cierre específico confirmado para la ventana, pero horarios o acceso pueden variar. | AY30: Reconfirmar en la web oficial al fijar fechas.
A31: JP-030 | B31: Tokio | C31: Kanto | D31: Tokio | E31: Chiyoda | F31: Marunouchi | G31: Marunouchi–Ginza | H31: Tokyo Station Marunouchi Building | I31: 東京駅丸の内駅舎 | J31: Tokyo Station Marunouchi Building | K31: 🏙️ Ciudad y barrios | L31: arquitectura/estación | M31: A | N31: Nodo funcional y monumento urbano; excelente punto visual de día y noche. | O31: Fachada histórica restaurada, cúpulas y eje hacia el Palacio Imperial. | P31: Combina infraestructura ferroviaria viva con arquitectura de 1914. | Q31: Fachada histórica restaurada, cúpulas y eje hacia el Palacio Imperial. | R31: 30–75 min | S31: Noche | T31: Todo el año | U31: Extremo | V31: Alto | W31: 0 | X31: 0 | Y31: =W31*'Configuración'!$B$4 | Z31: =X31*'Configuración'!$B$4 | AA31: No | AB31: — | AC31: Estación 24 h; comercios variables | AD31: Sin cierre | AE31: JR/Metro Tokyo | AF31: Buena en áreas principales; confirmar detalles con el recinto | AG31: 35.6812 | AH31: 139.7671 | AI31: https://www.tokyostationcity.com/en/ | AJ31: Cambiante | AK31: ARCHITECTURE | AL31: arquitectura, trenes, fotografía | AM31: 5 | AN31: 4 | AO31: 5 | AP31: 4 | AQ31: Imagen ideal: combina infraestructura ferroviaria viva con arquitectura de 1914. con luz de noche, sin multitudes dominando el encuadre. | AR31: Imperial Palace East Gardens (~19 min a pie) | Tsukiji Outer Market (~25 min a pie) | Jimbocho Book Town (~25 min en transporte) | AS31: Popular / turístico | AU31: https://www.google.com/maps/search/?api=1&query=Tokyo%20Station%20Marunouchi%20Building%2C%20Chiyoda%2C%20Japan | AV31: 2026-09-01 | AW31: CALENDARIO / CONDICIÓN PENDIENTE | AX31: No hay cierre específico confirmado para la ventana, pero horarios o acceso pueden variar. | AY31: Reconfirmar en la web oficial al fijar fechas.
A32: JP-031 | B32: Tokio | C32: Kanto | D32: Tokio | E32: Chuo | F32: Shiodome | G32: Marunouchi–Ginza | H32: Hama-rikyu Gardens | I32: 浜離宮恩賜庭園 | J32: Hama-rikyu Gardens | K32: 🌸 Jardines y paisajes | L32: jardín | M32: A | N32: Uno de los mejores contrastes entre jardín feudal, agua salada y rascacielos. | O32: Jardín daimyō con estanque mareal y casa de té. | P32: La marea de la bahía altera el paisaje interior. | Q32: Jardín daimyō con estanque mareal y casa de té. | R32: 1.5–2.5 h | S32: Mañana | T32: Colza, peonías y otoño | U32: Medio | V32: Medio | W32: 300 | X32: 300 | Y32: =W32*'Configuración'!$B$4 | Z32: =X32*'Configuración'!$B$4 | AA32: No | AB32: — | AC32: 09:00–17:00 | AD32: Fin de año; verificar | AE32: Shiodome / Tsukijishijo | AF32: Parcial; pueden existir escalones, grava o edificios sin elevador | AG32: 35.6597 | AH32: 139.7635 | AI32: https://www.tokyo-park.or.jp/park/hama-rikyu/ | AJ32: Cambiante | AK32: GARDEN | AL32: pareja, jardines, cultura, fotografía | AM32: 5 | AN32: 5 | AO32: 5 | AP32: 2 | AQ32: Imagen ideal: la marea de la bahía altera el paisaje interior. con luz de mañana, sin multitudes dominando el encuadre. | AR32: Tsukiji Outer Market (~13 min a pie) | Zōjō-ji + Tokyo Tower view (~20 min a pie) | teamLab Borderless (~29 min en transporte) | AS32: Semi-hidden | AU32: https://www.google.com/maps/search/?api=1&query=Hama-rikyu%20Gardens%2C%20Chuo%2C%20Japan | AV32: 2026-09-01 | AW32: CALENDARIO / CONDICIÓN PENDIENTE | AX32: No hay cierre específico confirmado para la ventana, pero horarios o acceso pueden variar. | AY32: Reconfirmar en la web oficial al fijar fechas.
A33: JP-032 | B33: Tokio | C33: Kanto | D33: Tokio | E33: Chuo | F33: Tsukiji | G33: Marunouchi–Ginza | H33: Tsukiji Outer Market | I33: 築地場外市場 | J33: Tsukiji Outer Market | K33: 🍜 Gastronomía | L33: mercado gastronómico | M33: C | N33: Sigue teniendo buenos especialistas, pero filas, sobreprecio y oferta viral reducen el valor. | O33: Calles de pescaderías, desayunos, cuchillos y productos secos. | P33: El antiguo mercado mayorista ya no opera aquí; conviene seleccionar negocios concretos. | Q33: Calles de pescaderías, desayunos, cuchillos y productos secos. | R33: 1–2 h | S33: Mañana | T33: Días laborables/sábado | U33: Extremo | V33: Extremo | W33: 1000 | X33: 6000 | Y33: =W33*'Configuración'!$B$4 | Z33: =X33*'Configuración'!$B$4 | AA33: No | AB33: — | AC33: Muchos locales 06:00–14:00 | AD33: Miércoles/domingo variable | AE33: Tsukiji / Tsukijishijo | AF33: Buena en áreas principales; confirmar detalles con el recinto | AG33: 35.6655 | AH33: 139.7707 | AI33: https://www.tsukiji.or.jp/english/ | AJ33: Cambiante | AK33: FOOD / TOURISTY | AL33: comida, mercado | AM33: 3 | AN33: 2 | AO33: 2 | AP33: 5 | AQ33: Imagen ideal: el antiguo mercado mayorista ya no opera aquí; conviene seleccionar negocios concretos. con luz de mañana, sin multitudes dominando el encuadre. | AR33: Hama-rikyu Gardens (~13 min a pie) | Tokyo Station Marunouchi Building (~25 min a pie) | Zōjō-ji + Tokyo Tower view (~31 min en transporte) | AS33: Popular / turístico | AU33: https://www.google.com/maps/search/?api=1&query=Tsukiji%20Outer%20Market%2C%20Chuo%2C%20Japan | AV33: 2026-09-01 | AW33: CALENDARIO / CONDICIÓN PENDIENTE | AX33: No hay cierre específico confirmado para la ventana, pero horarios o acceso pueden variar. | AY33: Reconfirmar en la web oficial al fijar fechas.
A34: JP-033 | B34: Tokio | C34: Kanto | D34: Tokio | E34: Minato | F34: Azabudai | G34: Roppongi–Azabudai | H34: teamLab Borderless | I34: チームラボボーダレス | J34: teamLab Borderless | K34: 🎨 Arte | L34: museo inmersivo | M34: S | N34: La experiencia digital más libre y exploratoria de Tokio. | O34: Museo sin mapa de instalaciones audiovisuales interconectadas. | P34: Las obras migran entre salas y premian perderse, a diferencia de un recorrido lineal. | Q34: Museo sin mapa de instalaciones audiovisuales interconectadas. | R34: 2.5–4 h | S34: Mañana | T34: Todo el año | U34: Extremo | V34: Extremo | W34: 3600 | X34: 5600 | Y34: =W34*'Configuración'!$B$4 | Z34: =X34*'Configuración'!$B$4 | AA34: Sí | AB34: 2–4 semanas | AC34: Horario variable por fecha | AD34: Variable | AE34: Kamiyacho / Roppongi-itchome | AF34: Buena en áreas principales; confirmar detalles con el recinto | AG34: 35.6605 | AH34: 139.7405 | AI34: https://www.teamlab.art/e/tokyo/ | AJ34: Cambiante | AK34: MUST SEE / ART | AL34: pareja, arte, tecnología, fotografía | AM34: 5 | AN34: 5 | AO34: 4 | AP34: 5 | AQ34: Imagen ideal: las obras migran entre salas y premian perderse, a diferencia de un recorrido lineal. con luz de mañana, sin multitudes dominando el encuadre. | AR34: Zōjō-ji + Tokyo Tower view (~11 min a pie) | Mori Art Museum + Tokyo City View (~14 min a pie) | 21_21 DESIGN SIGHT (~17 min a pie) | AS34: Popular / turístico | AU34: https://www.google.com/maps/search/?api=1&query=teamLab%20Borderless%2C%20Minato%2C%20Japan | AV34: 2026-09-01 | AW34: ABIERTO CONFIRMADO | AX34: Sede permanente en Azabudai Hills desde 2024; no es la antigua sede de Odaiba y no fue sustituida por Planets. | AY34: Comprar franja horaria y reconfirmar horario/precio de la fecha.
A35: JP-034 | B35: Tokio | C35: Kanto | D35: Tokio | E35: Minato | F35: Roppongi | G35: Roppongi–Azabudai | H35: Mori Art Museum + Tokyo City View | I35: 森美術館・東京シティビュー | J35: Mori Art Museum + Tokyo City View | K35: 🎨 Arte | L35: museo y mirador | M35: A | N35: Gran combinación de arte contemporáneo y skyline; depende de la exposición. | O35: Museo en altura con observatorio en Roppongi Hills. | P35: Permite convertir una sola reserva en arte y vista nocturna. | Q35: Museo en altura con observatorio en Roppongi Hills. | R35: 2.5–4 h | S35: Atardecer | T35: Todo el año | U35: Alto | V35: Alto | W35: 2200 | X35: 3200 | Y35: =W35*'Configuración'!$B$4 | Z35: =X35*'Configuración'!$B$4 | AA35: Recomendable | AB35: 1–2 semanas | AC35: Variable por exposición | AD35: Durante montaje | AE35: Roppongi | AF35: Buena en áreas principales; confirmar detalles con el recinto | AG35: 35.6604 | AH35: 139.7292 | AI35: https://www.mori.art.museum/en/ | AJ35: Cambiante | AK35: ART + VIEW | AL35: pareja, arte, fotografía, noche | AM35: 5 | AN35: 4 | AO35: 4 | AP35: 4 | AQ35: Imagen ideal: permite convertir una sola reserva en arte y vista nocturna. con luz de atardecer, sin multitudes dominando el encuadre. | AR35: The National Art Center, Tokyo (~8 min a pie) | 21_21 DESIGN SIGHT (~11 min a pie) | teamLab Borderless (~14 min a pie) | AS35: Popular / turístico | AU35: https://www.google.com/maps/search/?api=1&query=Mori%20Art%20Museum%20%2B%20Tokyo%20City%20View%2C%20Minato%2C%20Japan | AV35: 2026-09-01 | AW35: CALENDARIO / CONDICIÓN PENDIENTE | AX35: No hay cierre específico confirmado para la ventana, pero horarios o acceso pueden variar. | AY35: Reconfirmar en la web oficial al fijar fechas.
A36: JP-035 | B36: Tokio | C36: Kanto | D36: Tokio | E36: Minato | F36: Roppongi | G36: Roppongi–Azabudai | H36: The National Art Center, Tokyo | I36: 国立新美術館 | J36: The National Art Center, Tokyo | K36: 🎨 Arte | L36: museo/arquitectura | M36: A | N36: Edificio extraordinario y exposiciones temporales de alto nivel; no tiene colección permanente. | O36: Museo de Kisho Kurokawa con gran fachada ondulante. | P36: La arquitectura y programación cambiante son el contenido. | Q36: Museo de Kisho Kurokawa con gran fachada ondulante. | R36: 1.5–3 h | S36: Tarde | T36: Todo el año | U36: Medio | V36: Medio | W36: 0 | X36: 2500 | Y36: =W36*'Configuración'!$B$4 | Z36: =X36*'Configuración'!$B$4 | AA36: Recomendable | AB36: Según exposición | AC36: 10:00–18:00 aprox. | AD36: Martes y montaje | AE36: Nogizaka / Roppongi | AF36: Buena en áreas principales; confirmar detalles con el recinto | AG36: 35.6653 | AH36: 139.7264 | AI36: https://www.nact.jp/english/ | AJ36: Cambiante | AK36: ART / ARCHITECTURE | AL36: arte, arquitectura, lluvia | AM36: 5 | AN36: 4 | AO36: 4 | AP36: 2 | AQ36: Imagen ideal: la arquitectura y programación cambiante son el contenido. con luz de tarde, sin multitudes dominando el encuadre. | AR36: 21_21 DESIGN SIGHT (~6 min a pie) | Mori Art Museum + Tokyo City View (~8 min a pie) | Nezu Museum (~13 min a pie) | AS36: Lugar conocido pero excelente | AU36: https://www.google.com/maps/search/?api=1&query=The%20National%20Art%20Center%2C%20Tokyo%2C%20Minato%2C%20Japan | AV36: 2026-09-01 | AW36: CALENDARIO / CONDICIÓN PENDIENTE | AX36: No hay cierre específico confirmado para la ventana, pero horarios o acceso pueden variar. | AY36: Reconfirmar en la web oficial al fijar fechas.
A37: JP-036 | B37: Tokio | C37: Kanto | D37: Tokio | E37: Minato | F37: Akasaka | G37: Roppongi–Azabudai | H37: 21_21 DESIGN SIGHT | I37: 21_21 DESIGN SIGHT | J37: 21_21 DESIGN SIGHT | K37: 🎨 Arte | L37: galería de diseño | M37: A | N37: Pequeña pero conceptualmente fuerte; ideal para amantes de diseño. | O37: Espacio de Tadao Ando con exposiciones sobre diseño y vida cotidiana. | P37: No intenta ser un museo generalista: cada muestra plantea una idea. | Q37: Espacio de Tadao Ando con exposiciones sobre diseño y vida cotidiana. | R37: 1–2 h | S37: Tarde | T37: Todo el año | U37: Bajo | V37: Bajo | W37: 1400 | X37: 1400 | Y37: =W37*'Configuración'!$B$4 | Z37: =X37*'Configuración'!$B$4 | AA37: No | AB37: — | AC37: 10:00–19:00 aprox. | AD37: Martes y montaje | AE37: Nogizaka / Roppongi | AF37: Buena en áreas principales; confirmar detalles con el recinto | AG37: 35.6675 | AH37: 139.7302 | AI37: https://www.2121designsight.jp/en/ | AJ37: Cambiante | AK37: HIDDEN GEM | AL37: diseño, arquitectura, arte | AM37: 4 | AN37: 5 | AO37: 5 | AP37: 1 | AQ37: Imagen ideal: no intenta ser un museo generalista: cada muestra plantea una idea. con luz de tarde, sin multitudes dominando el encuadre. | AR37: The National Art Center, Tokyo (~6 min a pie) | Mori Art Museum + Tokyo City View (~11 min a pie) | teamLab Borderless (~17 min a pie) | AS37: Hidden Gem real | AU37: https://www.google.com/maps/search/?api=1&query=21_21%20DESIGN%20SIGHT%2C%20Minato%2C%20Japan | AV37: 2026-09-01 | AW37: CALENDARIO / CONDICIÓN PENDIENTE | AX37: No hay cierre específico confirmado para la ventana, pero horarios o acceso pueden variar. | AY37: Reconfirmar en la web oficial al fijar fechas.
A38: JP-037 | B38: Tokio | C38: Kanto | D38: Tokio | E38: Minato | F38: Shibakoen | G38: Tokyo Tower | H38: Zōjō-ji + Tokyo Tower view | I38: 増上寺・東京タワー | J38: Zōjō-ji + Tokyo Tower view | K38: 📷 Fotografía | L38: templo y paisaje urbano | M38: A | N38: Una de las composiciones visuales más claras entre Edo y Tokio moderno. | O38: Templo Tokugawa frente a la torre roja. | P38: La vista exterior suele ser más memorable que subir a la torre. | Q38: Templo Tokugawa frente a la torre roja. | R38: 1–2 h | S38: Atardecer | T38: Todo el año | U38: Alto | V38: Alto | W38: 0 | X38: 3000 | Y38: =W38*'Configuración'!$B$4 | Z38: =X38*'Configuración'!$B$4 | AA38: No | AB38: — | AC38: Templo diurno; torre variable | AD38: Sin cierre ordinario | AE38: Onarimon / Daimon | AF38: Parcial; pueden existir escalones, grava o edificios sin elevador | AG38: 35.6575 | AH38: 139.7483 | AI38: https://www.zojoji.or.jp/en/ | AJ38: Cambiante | AK38: PHOTO ICON | AL38: fotografía, historia, arquitectura | AM38: 5 | AN38: 4 | AO38: 5 | AP38: 4 | AQ38: Imagen ideal: la vista exterior suele ser más memorable que subir a la torre. con luz de atardecer, sin multitudes dominando el encuadre. | AR38: teamLab Borderless (~11 min a pie) | Hama-rikyu Gardens (~20 min a pie) | Mori Art Museum + Tokyo City View (~25 min a pie) | AS38: Alternativa menos saturada | AT38: Subir a Tokyo Tower | AU38: https://www.google.com/maps/search/?api=1&query=Z%C5%8Dj%C5%8D-ji%20%2B%20Tokyo%20Tower%20view%2C%20Minato%2C%20Japan | AV38: 2026-09-01 | AW38: CALENDARIO / CONDICIÓN PENDIENTE | AX38: No hay cierre específico confirmado para la ventana, pero horarios o acceso pueden variar. | AY38: Reconfirmar en la web oficial al fijar fechas.
A39: JP-038 | B39: Tokio | C39: Kanto | D39: Tokio | E39: Koto | F39: Toyosu | G39: Toyosu–Odaiba | H39: teamLab Planets TOKYO | I39: チームラボプラネッツ | J39: teamLab Planets TOKYO | K39: 🎨 Arte | L39: museo inmersivo | M39: A | N39: Muy físico y fotogénico, aunque más lineal y turístico que Borderless. | O39: Instalaciones inmersivas que se recorren descalzo, con agua y jardines. | P39: El cuerpo entra literalmente en el material de las obras. | Q39: Instalaciones inmersivas que se recorren descalzo, con agua y jardines. | R39: 2–3 h | S39: Mañana | T39: Hasta fin de 2027 según sitio oficial | U39: Extremo | V39: Extremo | W39: 3600 | X39: 5000 | Y39: =W39*'Configuración'!$B$4 | Z39: =X39*'Configuración'!$B$4 | AA39: Sí | AB39: 2–6 semanas | AC39: Variable; última entrada 1 h antes | AD39: Cierres puntuales | AE39: Shin-Toyosu | AF39: Buena en áreas principales; confirmar detalles con el recinto | AG39: 35.6491 | AH39: 139.7898 | AI39: https://www.teamlab.art/e/planets/ | AJ39: Cambiante | AK39: ART / IMMERSIVE | AL39: pareja, fotografía, tecnología | AM39: 5 | AN39: 4 | AO39: 3 | AP39: 5 | AQ39: Imagen ideal: el cuerpo entra literalmente en el material de las obras. con luz de mañana, sin multitudes dominando el encuadre. | AR39: Toyosu Market (~8 min a pie) | SMALL WORLDS Miniature Museum (~15 min a pie) | Odaiba Seaside Park + Rainbow Bridge (~35 min en transporte) | AS39: Popular / turístico | AU39: https://www.google.com/maps/search/?api=1&query=teamLab%20Planets%20TOKYO%2C%20Koto%2C%20Japan | AV39: 2026-09-01 | AW39: ABIERTO CONFIRMADO | AX39: Experiencia independiente en Toyosu; la web oficial anuncia operación hasta finales de 2027. | AY39: Comprar franja horaria cuando se definan fechas.
A40: JP-039 | B40: Tokio | C40: Kanto | D40: Tokio | E40: Koto | F40: Toyosu | G40: Toyosu–Odaiba | H40: Toyosu Market | I40: 豊洲市場 | J40: Toyosu Market | K40: 🍜 Gastronomía | L40: mercado mayorista | M40: B | N40: Interesante por la operación real y restaurantes, pero menos atmosférico que Tsukiji. | O40: Mercado mayorista moderno con plataformas de observación y restaurantes. | P40: Permite ver logística de atún y cadena alimentaria sin convertirla en decorado. | Q40: Mercado mayorista moderno con plataformas de observación y restaurantes. | R40: 2–3 h | S40: Mañana | T40: Días de mercado | U40: Medio | V40: Medio | W40: 0 | X40: 7000 | Y40: =W40*'Configuración'!$B$4 | Z40: =X40*'Configuración'!$B$4 | AA40: Recomendable | AB40: Para subasta, consultar reglas | AC40: Muy temprano–14:00 aprox. | AD40: Domingos/festivos y calendario mercado | AE40: Shijomae | AF40: Buena en áreas principales; confirmar detalles con el recinto | AG40: 35.6456 | AH40: 139.7857 | AI40: https://www.shijou.metro.tokyo.lg.jp/english/toyosu/ | AJ40: Cambiante | AK40: FOOD | AL40: comida, mercado, fotografía | AM40: 3 | AN40: 4 | AO40: 4 | AP40: 2 | AQ40: Imagen ideal: permite ver logística de atún y cadena alimentaria sin convertirla en decorado. con luz de mañana, sin multitudes dominando el encuadre. | AR40: teamLab Planets TOKYO (~8 min a pie) | SMALL WORLDS Miniature Museum (~10 min a pie) | Odaiba Seaside Park + Rainbow Bridge (~28 min en transporte) | AS40: No aplica | AU40: https://www.google.com/maps/search/?api=1&query=Toyosu%20Market%2C%20Koto%2C%20Japan | AV40: 2026-09-01 | AW40: CALENDARIO / CONDICIÓN PENDIENTE | AX40: No hay cierre específico confirmado para la ventana, pero horarios o acceso pueden variar. | AY40: Reconfirmar en la web oficial al fijar fechas.
A41: JP-040 | B41: Tokio | C41: Kanto | D41: Tokio | E41: Koto | F41: Odaiba | G41: Toyosu–Odaiba | H41: Miraikan | I41: 日本科学未来館 | J41: Miraikan | K41: 🤖 Tecnología | L41: museo de ciencia | M41: A | N41: El mejor museo general de ciencia y futuro para conectar robótica, espacio y sociedad. | O41: Museo interactivo nacional de ciencia emergente e innovación. | P41: Combina demostraciones, investigación real y preguntas éticas. | Q41: Museo interactivo nacional de ciencia emergente e innovación. | R41: 2.5–4 h | S41: Tarde | T41: Todo el año | U41: Medio | V41: Medio | W41: 630 | X41: 940 | Y41: =W41*'Configuración'!$B$4 | Z41: =X41*'Configuración'!$B$4 | AA41: No | AB41: — | AC41: 10:00–17:00 aprox. | AD41: Martes; verificar | AE41: Tokyo International Cruise Terminal / Telecom Center | AF41: Buena en áreas principales; confirmar detalles con el recinto | AG41: 35.6193 | AH41: 139.7765 | AI41: https://www.miraikan.jst.go.jp/en/ | AJ41: Cambiante | AK41: TECH | AL41: tecnología, ciencia, familia, lluvia | AM41: 4 | AN41: 5 | AO41: 5 | AP41: 2 | AQ41: Imagen ideal: combina demostraciones, investigación real y preguntas éticas. con luz de tarde, sin multitudes dominando el encuadre. | AR41: Unicorn Gundam at DiverCity (~9 min a pie) | Odaiba Seaside Park + Rainbow Bridge (~17 min a pie) | SMALL WORLDS Miniature Museum (~35 min en transporte) | AS41: Lugar conocido pero excelente | AU41: https://www.google.com/maps/search/?api=1&query=Miraikan%2C%20Koto%2C%20Japan | AV41: 2026-09-01 | AW41: CALENDARIO / CONDICIÓN PENDIENTE | AX41: No hay cierre específico confirmado para la ventana, pero horarios o acceso pueden variar. | AY41: Reconfirmar en la web oficial al fijar fechas.
A42: JP-041 | B42: Tokio | C42: Kanto | D42: Tokio | E42: Koto | F42: Odaiba | G42: Toyosu–Odaiba | H42: Unicorn Gundam at DiverCity | I42: 実物大ユニコーンガンダム立像 | J42: Unicorn Gundam at DiverCity | K42: 👾 Anime/manga | L42: monumento pop | M42: B | N42: Espectacular para fans y fotografía nocturna; breve para quien no conoce Gundam. | O42: Estatua a escala real con transformaciones programadas. | P42: Convierte un mecha ficticio en pieza urbana monumental. | Q42: Estatua a escala real con transformaciones programadas. | R42: 30–60 min | S42: Noche | T42: Todo el año | U42: Alto | V42: Alto | W42: 0 | X42: 0 | Y42: =W42*'Configuración'!$B$4 | Z42: =X42*'Configuración'!$B$4 | AA42: No | AB42: — | AC42: Exterior 24 h; shows variables | AD42: Sin cierre ordinario | AE42: Tokyo Teleport | AF42: Buena en áreas principales; confirmar detalles con el recinto | AG42: 35.6252 | AH42: 139.7756 | AI42: https://www.unicorn-gundam-statue.jp/ | AJ42: Cambiante | AK42: ANIME | AL42: anime, fotografía, noche | AM42: 5 | AN42: 4 | AO42: 4 | AP42: 4 | AQ42: Imagen ideal: convierte un mecha ficticio en pieza urbana monumental. con luz de noche, sin multitudes dominando el encuadre. | AR42: Odaiba Seaside Park + Rainbow Bridge (~8 min a pie) | Miraikan (~9 min a pie) | SMALL WORLDS Miniature Museum (~28 min en transporte) | AS42: Popular / turístico | AU42: https://www.google.com/maps/search/?api=1&query=Unicorn%20Gundam%20at%20DiverCity%2C%20Koto%2C%20Japan | AV42: 2026-09-01 | AW42: CALENDARIO / CONDICIÓN PENDIENTE | AX42: No hay cierre específico confirmado para la ventana, pero horarios o acceso pueden variar. | AY42: Reconfirmar en la web oficial al fijar fechas.
A43: JP-042 | B43: Tokio | C43: Kanto | D43: Tokio | E43: Koto | F43: Odaiba | G43: Toyosu–Odaiba | H43: Odaiba Seaside Park + Rainbow Bridge | I43: お台場海浜公園・レインボーブリッジ | J43: Odaiba Seaside Park + Rainbow Bridge | K43: 🌃 Nocturno | L43: paseo costero | M43: B | N43: Gran paseo gratuito para skyline, bahía y puesta de sol. Clasificación v2: recomendable si encaja; su valor depende más de interés, saturación o logística. | O43: Playa urbana, paseo marítimo y vistas del puente iluminado. | P43: Ofrece horizonte abierto, raro en el centro de Tokio. | Q43: Playa urbana, paseo marítimo y vistas del puente iluminado. | R43: 1.5–3 h | S43: Atardecer | T43: Todo el año | U43: Medio | V43: Medio | W43: 0 | X43: 0 | Y43: =W43*'Configuración'!$B$4 | Z43: =X43*'Configuración'!$B$4 | AA43: No | AB43: — | AC43: Espacio público 24 h | AD43: Pasarela del puente tiene horario/cierres | AE43: Odaiba-kaihinkoen / Tokyo Teleport | AF43: Buena en áreas principales; confirmar detalles con el recinto | AG43: 35.63 | AH43: 139.775 | AI43: https://www.gotokyo.org/en/index.html | AJ43: Cambiante | AK43: NIGHT / VIEW | AL43: pareja, fotografía, noche, mar | AM43: 5 | AN43: 3 | AO43: 5 | AP43: 2 | AQ43: Imagen ideal: ofrece horizonte abierto, raro en el centro de tokio. con luz de atardecer, sin multitudes dominando el encuadre. | AR43: Unicorn Gundam at DiverCity (~8 min a pie) | Miraikan (~17 min a pie) | SMALL WORLDS Miniature Museum (~23 min a pie) | AS43: No aplica | AU43: https://www.google.com/maps/search/?api=1&query=Odaiba%20Seaside%20Park%20%2B%20Rainbow%20Bridge%2C%20Koto%2C%20Japan | AV43: 2026-09-01 | AW43: CALENDARIO / CONDICIÓN PENDIENTE | AX43: No hay cierre específico confirmado para la ventana, pero horarios o acceso pueden variar. | AY43: Reconfirmar en la web oficial al fijar fechas.
A44: JP-043 | B44: Tokio | C44: Kanto | D44: Tokio | E44: Koto | F44: Ariake | G44: Toyosu–Odaiba | H44: SMALL WORLDS Miniature Museum | I44: スモールワールズ | J44: SMALL WORLDS Miniature Museum | K44: 🧩 Extraño/peculiar/único | L44: museo de miniaturas | M44: A | N44: Muy visual, detallado y diferente de los grandes museos convencionales. | O44: Enormes dioramas móviles de ciudades, espacio y Evangelion. | P44: La escala diminuta crea fotografía macro y narrativa interactiva. | Q44: Enormes dioramas móviles de ciudades, espacio y Evangelion. | R44: 2–3 h | S44: Tarde | T44: Todo el año | U44: Medio | V44: Bajo | W44: 3200 | X44: 3700 | Y44: =W44*'Configuración'!$B$4 | Z44: =X44*'Configuración'!$B$4 | AA44: Recomendable | AB44: Días | AC44: 09:00–19:00 aprox.; verificar | AD44: Variable | AE44: Ariake-Tennis-no-mori | AF44: Buena en áreas principales; confirmar detalles con el recinto | AG44: 35.6396 | AH44: 139.7884 | AI44: https://smallworlds.jp/en/ | AJ44: Cambiante | AK44: UNIQUE | AL44: anime, fotografía, miniaturas, familia | AM44: 5 | AN44: 5 | AO44: 4 | AP44: 2 | AQ44: Imagen ideal: la escala diminuta crea fotografía macro y narrativa interactiva. con luz de tarde, sin multitudes dominando el encuadre. | AR44: Toyosu Market (~10 min a pie) | teamLab Planets TOKYO (~15 min a pie) | Odaiba Seaside Park + Rainbow Bridge (~23 min a pie) | AS44: Semi-hidden | AU44: https://www.google.com/maps/search/?api=1&query=SMALL%20WORLDS%20Miniature%20Museum%2C%20Koto%2C%20Japan | AV44: 2026-09-01 | AW44: CALENDARIO / CONDICIÓN PENDIENTE | AX44: No hay cierre específico confirmado para la ventana, pero horarios o acceso pueden variar. | AY44: Reconfirmar en la web oficial al fijar fechas.
A45: JP-044 | B45: Tokio | C45: Kanto | D45: Tokio | E45: Mitaka | F45: Shimorenjaku | G45: Kichijoji–Mitaka | H45: Ghibli Museum, Mitaka | I45: 三鷹の森ジブリ美術館 | J45: Ghibli Museum, Mitaka | K45: 👾 Anime/manga | L45: museo | M45: S | N45: Experiencia autoral irrepetible para fans de Ghibli, con cortos exclusivos. | O45: Museo laberíntico diseñado por Hayao Miyazaki junto a Inokashira Park. | P45: No permite fotografiar interiores y prioriza descubrimiento sobre mercancía. | Q45: Museo laberíntico diseñado por Hayao Miyazaki junto a Inokashira Park. | R45: 2–3 h | S45: Mañana | T45: Todo el año | U45: Alto | V45: Alto | W45: 1000 | X45: 1000 | Y45: =W45*'Configuración'!$B$4 | Z45: =X45*'Configuración'!$B$4 | AA45: Sí | AB45: Venta mensual; comprar al abrir | AC45: 10:00–18:00 | AD45: Martes y cierres de mantenimiento | AE45: JR Mitaka + 15 min a pie/bus | AF45: Buena en áreas principales; confirmar detalles con el recinto | AG45: 35.6962 | AH45: 139.5704 | AI45: https://www.ghibli-museum.jp/en/tickets/ | AJ45: Cambiante | AK45: MUST SEE / ANIME | AL45: pareja, anime, arte, cine | AM45: 5 | AN45: 5 | AO45: 5 | AP45: 4 | AQ45: Imagen ideal: no permite fotografiar interiores y prioriza descubrimiento sobre mercancía. con luz de mañana, sin multitudes dominando el encuadre. | AR45: Kichijoji + Inokashira Park (~13 min a pie) | AS45: Popular / turístico | AU45: https://www.google.com/maps/search/?api=1&query=Ghibli%20Museum%2C%20Mitaka%2C%20Mitaka%2C%20Japan | AV45: 2026-09-01 | AW45: CALENDARIO 2027 PENDIENTE | AX45: Reserva obligatoria y posibles cierres de mantenimiento; febrero–marzo de 2027 no está publicado. | AY45: Vigilar la venta mensual y comprar al abrir.
A46: JP-045 | B46: Tokio | C46: Kanto | D46: Tokio | E46: Musashino | F46: Kichijoji | G46: Kichijoji–Mitaka | H46: Kichijoji + Inokashira Park | I46: 吉祥寺・井の頭恩賜公園 | J46: Kichijoji + Inokashira Park | K46: 🏙️ Ciudad y barrios | L46: barrio/parque | M46: A | N46: Uno de los barrios con mejor equilibrio entre vida local, comida, tiendas y naturaleza. | O46: Calles comerciales, Harmonica Yokocho y gran parque con lago. | P46: Funciona como destino completo, no solo apéndice del museo Ghibli. | Q46: Calles comerciales, Harmonica Yokocho y gran parque con lago. | R46: 3–5 h | S46: Tarde | T46: Sakura y otoño | U46: Alto | V46: Medio | W46: 0 | X46: 0 | Y46: =W46*'Configuración'!$B$4 | Z46: =X46*'Configuración'!$B$4 | AA46: No | AB46: — | AC46: Espacio público; negocios variables | AD46: Sin cierre | AE46: JR/Keio Kichijoji | AF46: Buena en áreas principales; confirmar detalles con el recinto | AG46: 35.7003 | AH46: 139.5797 | AI46: https://www.gotokyo.org/en/index.html | AJ46: Cambiante | AK46: LOCAL FAVORITE | AL46: pareja, comida, barrios, naturaleza | AM46: 4 | AN46: 5 | AO46: 5 | AP46: 3 | AQ46: Imagen ideal: funciona como destino completo, no solo apéndice del museo ghibli. con luz de tarde, sin multitudes dominando el encuadre. | AR46: Ghibli Museum, Mitaka (~13 min a pie) | AS46: Semi-hidden | AU46: https://www.google.com/maps/search/?api=1&query=Kichijoji%20%2B%20Inokashira%20Park%2C%20Musashino%2C%20Japan | AV46: 2026-09-01 | AW46: ABIERTO; FLORACIÓN NO GARANTIZADA | AX46: En Japón central la floración plena suele ser más tardía; finales de marzo es incierto. | AY46: No basar la visita en sakura hasta el pronóstico 2027.
A47: JP-046 | B47: Tokio | C47: Kanto | D47: Tokio | E47: Nakano | F47: Nakano | G47: Nakano | H47: Nakano Broadway | I47: 中野ブロードウェイ | J47: Nakano Broadway | K47: 👾 Anime/manga | L47: centro comercial especializado | M47: A | N47: Mejor para coleccionismo profundo y rarezas que muchos edificios de Akihabara. | O47: Galerías de Mandarake, relojes, arte, juguetes y cultura subterránea. | P47: Menos espectáculo exterior; más densidad de nichos y segunda mano. | Q47: Galerías de Mandarake, relojes, arte, juguetes y cultura subterránea. | R47: 2–4 h | S47: Tarde | T47: Todo el año | U47: Alto | V47: Medio | W47: 0 | X47: 0 | Y47: =W47*'Configuración'!$B$4 | Z47: =X47*'Configuración'!$B$4 | AA47: No | AB47: — | AC47: Aprox. 12:00–20:00; tiendas varían | AD47: Según tienda | AE47: JR/Metro Nakano | AF47: Buena en áreas principales; confirmar detalles con el recinto | AG47: 35.7092 | AH47: 139.6657 | AI47: https://nakano-broadway.com/ | AJ47: Cambiante | AK47: HIDDEN GEM / ANIME | AL47: anime, compras, coleccionismo | AM47: 3 | AN47: 5 | AO47: 5 | AP47: 3 | AQ47: Imagen ideal: menos espectáculo exterior; más densidad de nichos y segunda mano. con luz de tarde, sin multitudes dominando el encuadre. | AS47: Alternativa menos saturada | AT47: Akihabara | AU47: https://www.google.com/maps/search/?api=1&query=Nakano%20Broadway%2C%20Nakano%2C%20Japan | AV47: 2026-09-01 | AW47: CALENDARIO / CONDICIÓN PENDIENTE | AX47: No hay cierre específico confirmado para la ventana, pero horarios o acceso pueden variar. | AY47: Reconfirmar en la web oficial al fijar fechas.
A48: JP-047 | B48: Tokio | C48: Kanto | D48: Tokio | E48: Koganei | F48: Sakuracho | G48: West Tokyo | H48: Edo-Tokyo Open Air Architectural Museum | I48: 江戸東京たてもの園 | J48: Edo-Tokyo Open Air Architectural Museum | K48: 🏛️ Museos | L48: museo al aire libre | M48: A | N48: La mejor inmersión arquitectónica en el Tokio desaparecido. Clasificación v2: excelente y muy recomendable, pero no justifica por sí sola adaptar la ruta. | O48: Edificios históricos trasladados y restaurados dentro de un parque. | P48: Se camina dentro de casas, comercios y baños públicos reales de distintas eras. | Q48: Edificios históricos trasladados y restaurados dentro de un parque. | R48: 3–5 h | S48: Mañana | T48: Primavera y otoño | U48: Bajo | V48: Bajo | W48: 400 | X48: 400 | Y48: =W48*'Configuración'!$B$4 | Z48: =X48*'Configuración'!$B$4 | AA48: No | AB48: — | AC48: 09:30–17:30 según temporada | AD48: Lunes; verificar | AE48: Musashi-Koganei + bus | AF48: Buena en áreas principales; confirmar detalles con el recinto | AG48: 35.7154 | AH48: 139.5125 | AI48: https://www.tatemonoen.jp/english/ | AJ48: Cambiante | AK48: HIDDEN GEM | AL48: arquitectura, historia, fotografía | AM48: 5 | AN48: 5 | AO48: 5 | AP48: 1 | AQ48: Imagen ideal: se camina dentro de casas, comercios y baños públicos reales de distintas eras. con luz de mañana, sin multitudes dominando el encuadre. | AS48: Hidden Gem real | AU48: https://www.google.com/maps/search/?api=1&query=Edo-Tokyo%20Open%20Air%20Architectural%20Museum%2C%20Koganei%2C%20Japan | AV48: 2026-09-01 | AW48: CALENDARIO / CONDICIÓN PENDIENTE | AX48: No hay cierre específico confirmado para la ventana, pero horarios o acceso pueden variar. | AY48: Reconfirmar en la web oficial al fijar fechas.
A49: JP-048 | B49: Tokio | C49: Kanto | D49: Tokio | E49: Setagaya | F49: Shimokitazawa | G49: Shimokitazawa | H49: Shimokitazawa | I49: 下北沢 | J49: Shimokitazawa | K49: 🏙️ Ciudad y barrios | L49: barrio | M49: A | N49: Cultura independiente, segunda mano y música sin la escala corporativa de Shibuya. | O49: Barrio de tiendas vintage, teatros, cafés y salas pequeñas. | P49: Su atractivo es explorar, no completar una lista de monumentos. | Q49: Barrio de tiendas vintage, teatros, cafés y salas pequeñas. | R49: 2–4 h | S49: Tarde | T49: Todo el año | U49: Alto | V49: Medio | W49: 0 | X49: 0 | Y49: =W49*'Configuración'!$B$4 | Z49: =X49*'Configuración'!$B$4 | AA49: No | AB49: — | AC49: Negocios variables | AD49: Sin cierre | AE49: Odakyu/Keio Shimokitazawa | AF49: Buena en áreas principales; confirmar detalles con el recinto | AG49: 35.6616 | AH49: 139.6681 | AI49: https://www.gotokyo.org/en/index.html | AJ49: Cambiante | AK49: LOCAL | AL49: pareja, compras, música, cafés | AM49: 4 | AN49: 5 | AO49: 5 | AP49: 3 | AQ49: Imagen ideal: su atractivo es explorar, no completar una lista de monumentos. con luz de tarde, sin multitudes dominando el encuadre. | AS49: Semi-hidden | AU49: https://www.google.com/maps/search/?api=1&query=Shimokitazawa%2C%20Setagaya%2C%20Japan | AV49: 2026-09-01 | AW49: CALENDARIO / CONDICIÓN PENDIENTE | AX49: No hay cierre específico confirmado para la ventana, pero horarios o acceso pueden variar. | AY49: Reconfirmar en la web oficial al fijar fechas.
A50: JP-049 | B50: Tokio | C50: Kanto | D50: Tokio | E50: Toshima | F50: Ikebukuro | G50: Ikebukuro | H50: Ikebukuro anime district | I50: 池袋アニメ街 | J50: Ikebukuro anime district | K50: 👾 Anime/manga | L50: barrio/tiendas | M50: A | N50: Es la alternativa más completa a Akihabara para fandom femenino, Pokémon y gashapon. | O50: Animate flagship, Otome Road, Sunshine City y tiendas de personajes. | P50: Especialización distinta a Akihabara y grandes espacios interiores. | Q50: Animate flagship, Otome Road, Sunshine City y tiendas de personajes. | R50: 3–5 h | S50: Tarde | T50: Todo el año | U50: Extremo | V50: Alto | W50: 0 | X50: 0 | Y50: =W50*'Configuración'!$B$4 | Z50: =X50*'Configuración'!$B$4 | AA50: No | AB50: — | AC50: Centros aprox. 10:00–20:00 | AD50: Según comercio | AE50: JR/Metro Ikebukuro | AF50: Buena en áreas principales; confirmar detalles con el recinto | AG50: 35.7295 | AH50: 139.7199 | AI50: https://www.gotokyo.org/en/index.html | AJ50: Cambiante | AK50: ANIME | AL50: anime, compras, Pokémon, lluvia | AM50: 4 | AN50: 5 | AO50: 4 | AP50: 4 | AQ50: Imagen ideal: especialización distinta a akihabara y grandes espacios interiores. con luz de tarde, sin multitudes dominando el encuadre. | AS50: Alternativa menos saturada | AT50: Akihabara | AU50: https://www.google.com/maps/search/?api=1&query=Ikebukuro%20anime%20district%2C%20Toshima%2C%20Japan | AV50: 2026-09-01 | AW50: CALENDARIO / CONDICIÓN PENDIENTE | AX50: No hay cierre específico confirmado para la ventana, pero horarios o acceso pueden variar. | AY50: Reconfirmar en la web oficial al fijar fechas.
A51: JP-050 | B51: Tokio | C51: Kanto | D51: Tokio | E51: Inagi | F51: Yanokuchi | G51: West Tokyo | H51: PokéPark KANTO | I51: ポケパーク カントー | J51: PokéPark KANTO | K51: 🎢 Entretenimiento | L51: parque temático | M51: A | N51: Primera gran experiencia Pokémon permanente al aire libre; justifica el desplazamiento para fans. Clasificación v2: excelente y muy recomendable, pero no justifica por sí sola adaptar la ruta. | O51: Área temática dentro de Yomiuriland con Pokémon Forest y Sedge Town. | P51: Más de 600 representaciones a escala natural en un recorrido forestal. | Q51: Área temática dentro de Yomiuriland con Pokémon Forest y Sedge Town. | R51: Medio día–día completo | S51: Mañana | T51: Todo el año; evitar calor/lluvia | U51: Extremo | V51: Extremo | W51: 7900 | X51: 14000 | Y51: =W51*'Configuración'!$B$4 | Z51: =X51*'Configuración'!$B$4 | AA51: Sí | AB51: Lotería/venta controlada; meses | AC51: Calendario oficial variable | AD51: Fechas de cierre programadas | AE51: Keio Yomiuriland + transporte interno | AF51: Buena en áreas principales; confirmar detalles con el recinto | AG51: 35.6258 | AH51: 139.5176 | AI51: https://www.pokepark-kanto.co.jp/ppark/top/index?languageKind=en_US | AJ51: Cambiante | AK51: MUST SEE / POKÉMON | AL51: pareja, Pokémon, fotografía, entretenimiento | AM51: 5 | AN51: 5 | AO51: 3 | AP51: 5 | AQ51: Imagen ideal: más de 600 representaciones a escala natural en un recorrido forestal. con luz de mañana, sin multitudes dominando el encuadre. | AS51: Popular / turístico | AU51: https://www.google.com/maps/search/?api=1&query=Pok%C3%A9Park%20KANTO%2C%20Inagi%2C%20Japan | AV51: 2026-09-01 | AW51: VENTA FUTURA / CUPO LIMITADO | AX51: Opera con entradas controladas, calendario y app. | AY51: Revisar lotería/venta cuando abra 2027.
A52: JP-051 | B52: Tokio | C52: Kanto | D52: Tokio | E52: Hachioji | F52: Takaomachi | G52: West Tokyo | H52: Mount Takao | I52: 高尾山 | J52: Mount Takao | K52: 🥾 Senderismo/aventura | L52: montaña/sendero | M52: A | N52: Naturaleza muy accesible con opciones desde paseo fácil hasta ascenso completo. | O52: Montaña de 599 m con senderos, teleférico, templo y vistas de Fuji. | P52: Empieza casi directamente en una estación de tren metropolitano. | Q52: Montaña de 599 m con senderos, teleférico, templo y vistas de Fuji. | R52: Medio día–día completo | S52: Mañana | T52: Otoño e invierno despejado | U52: Alto | V52: Alto | W52: 0 | X52: 1200 | Y52: =W52*'Configuración'!$B$4 | Z52: =X52*'Configuración'!$B$4 | AA52: No | AB52: — | AC52: Senderos abiertos; transporte con horario | AD52: Clima/mantenimiento | AE52: Keio Takaosanguchi | AF52: Parcial o baja; terreno irregular y condiciones naturales | AG52: 35.6252 | AH52: 139.2437 | AI52: https://www.takaotozan.co.jp/english/ | AJ52: Cambiante | AK52: NATURE | AL52: senderismo, naturaleza, fotografía | AM52: 5 | AN52: 4 | AO52: 5 | AP52: 4 | AQ52: Imagen ideal: empieza casi directamente en una estación de tren metropolitano. con luz de mañana, sin multitudes dominando el encuadre. | AS52: Popular / turístico | AU52: https://www.google.com/maps/search/?api=1&query=Mount%20Takao%2C%20Hachioji%2C%20Japan | AV52: 2026-09-01 | AW52: RIESGO ESTACIONAL | AX52: Posibles nieve, hielo, barro, viento, cierres y menos horas de luz. | AY52: Revisar clima, sendero y último transporte 24–48 h antes.
A53: JP-052 | B53: Tokio | C53: Kanto | D53: Tokio | E53: Ome | F53: Mitake | G53: Okutama–Mitake | H53: Mount Mitake and Musashi Mitake Shrine | I53: 御岳山・武蔵御嶽神社 | J53: Mount Mitake and Musashi Mitake Shrine | K53: 🥾 Senderismo/aventura | L53: montaña/santuario | M53: A | N53: Más espiritual, boscoso y menos internacional que Takao. | O53: Caminos de montaña, aldea en la cima y santuario antiguo. | P53: Combina senderismo, cascadas y hospedajes shukubo cerca de Tokio. | Q53: Caminos de montaña, aldea en la cima y santuario antiguo. | R53: Día completo | S53: Mañana | T53: Primavera y otoño | U53: Medio | V53: Bajo | W53: 0 | X53: 1200 | Y53: =W53*'Configuración'!$B$4 | Z53: =X53*'Configuración'!$B$4 | AA53: No | AB53: — | AC53: Senderos abiertos; cablecar variable | AD53: Clima/mantenimiento | AE53: JR Mitake + bus + cablecar | AF53: Parcial o baja; terreno irregular y condiciones naturales | AG53: 35.7827 | AH53: 139.1491 | AI53: https://www.gotokyo.org/en/index.html | AJ53: Cambiante | AK53: HIDDEN GEM / NATURE | AL53: senderismo, naturaleza, cultura | AM53: 5 | AN53: 5 | AO53: 4 | AP53: 2 | AQ53: Imagen ideal: combina senderismo, cascadas y hospedajes shukubo cerca de tokio. con luz de mañana, sin multitudes dominando el encuadre. | AS53: Semi-hidden | AT53: Mount Takao | AU53: https://www.google.com/maps/search/?api=1&query=Mount%20Mitake%20and%20Musashi%20Mitake%20Shrine%2C%20Ome%2C%20Japan | AV53: 2026-09-01 | AW53: RIESGO ESTACIONAL | AX53: Posibles nieve, hielo, barro, viento, cierres y menos horas de luz. | AY53: Revisar clima, sendero y último transporte 24–48 h antes.
A54: JP-053 | B54: Tokio | C54: Kanto | D54: Tokio | E54: Ryogoku | F54: Ryogoku | G54: Ryogoku | H54: Edo-Tokyo Museum | I54: 江戸東京博物館 | J54: Edo-Tokyo Museum | K54: 🏛️ Museos | L54: museo | M54: A | N54: Reabrió renovado en 2026 y vuelve a ser la mejor lectura de la historia urbana de Tokio. Clasificación v2: excelente y muy recomendable, pero no justifica por sí sola adaptar la ruta. | O54: Gran museo con reconstrucciones, maquetas y objetos de Edo y Tokio. | P54: Explica la ciudad como sistema social y material, no como colección de postales. | Q54: Gran museo con reconstrucciones, maquetas y objetos de Edo y Tokio. | R54: 3–5 h | S54: Mañana | T54: Todo el año | U54: Alto | V54: Alto | W54: 800 | X54: 2740 | Y54: =W54*'Configuración'!$B$4 | Z54: =X54*'Configuración'!$B$4 | AA54: Recomendable | AB54: Días para fecha específica/exposición | AC54: 09:30–17:30 aprox. | AD54: Lunes; verificar | AE54: JR/Toei Ryogoku | AF54: Buena en áreas principales; confirmar detalles con el recinto | AG54: 35.6966 | AH54: 139.7967 | AI54: https://www.edo-tokyo-museum.or.jp/en/ | AJ54: Cambiante | AK54: REOPENED 2026 | AL54: historia, arquitectura, lluvia | AM54: 5 | AN54: 5 | AO54: 5 | AP54: 4 | AQ54: Imagen ideal: explica la ciudad como sistema social y material, no como colección de postales. con luz de mañana, sin multitudes dominando el encuadre. | AR54: The Sumida Hokusai Museum (~5 min a pie) | Asakusa Culture Tourist Information Center (~22 min a pie) | Tokyo Skytree (~27 min en transporte) | AS54: Popular / turístico | AU54: https://www.google.com/maps/search/?api=1&query=Edo-Tokyo%20Museum%2C%20Ryogoku%2C%20Japan | AV54: 2026-09-01 | AW54: CALENDARIO / CONDICIÓN PENDIENTE | AX54: No hay cierre específico confirmado para la ventana, pero horarios o acceso pueden variar. | AY54: Reconfirmar en la web oficial al fijar fechas.
A55: JP-054 | B55: Kioto | C55: Kansai | D55: Kioto | E55: Kyoto | F55: Higashiyama | G55: Kiyomizu–Gion | H55: Kiyomizu-dera | I55: 清水寺 | J55: Kiyomizu-dera | K55: ⛩️ Templos y santuarios | L55: templo | M55: S | N55: La terraza, el relieve y la relación con Higashiyama justifican la saturación. | O55: Gran templo de madera sobre la ladera oriental. | P55: La ciudad se descubre desde una arquitectura integrada al bosque. | Q55: Gran templo de madera sobre la ladera oriental. | R55: 1.5–2.5 h | S55: Mañana | T55: Sakura y otoño; bueno todo el año | U55: Extremo | V55: Extremo | W55: 500 | X55: 500 | Y55: =W55*'Configuración'!$B$4 | Z55: =X55*'Configuración'!$B$4 | AA55: No | AB55: — | AC55: Abre desde 06:00; cierre variable | AD55: Sin cierre ordinario | AE55: Bus + subida; Keihan Kiyomizu-Gojo | AF55: Parcial; pueden existir escalones, grava o edificios sin elevador | AG55: 34.9949 | AH55: 135.785 | AI55: https://www.kiyomizudera.or.jp/en/ | AJ55: Cambiante | AK55: MUST SEE | AL55: pareja, historia, fotografía, cultura | AM55: 5 | AN55: 4 | AO55: 5 | AP55: 5 | AQ55: Imagen ideal: la ciudad se descubre desde una arquitectura integrada al bosque. con luz de mañana, sin multitudes dominando el encuadre. | AR55: Sannenzaka and Ninenzaka (~5 min a pie) | Yasaka Kōshin-dō (~9 min a pie) | Kōdai-ji (~10 min a pie) | AS55: Popular / turístico | AU55: https://www.google.com/maps/search/?api=1&query=Kiyomizu-dera%2C%20Kyoto%2C%20Japan | AV55: 2026-09-01 | AW55: ABIERTO; FLORACIÓN NO GARANTIZADA | AX55: En Japón central la floración plena suele ser más tardía; finales de marzo es incierto. | AY55: No basar la visita en sakura hasta el pronóstico 2027.
A56: JP-055 | B56: Kioto | C56: Kansai | D56: Kioto | E56: Kyoto | F56: Higashiyama | G56: Kiyomizu–Gion | H56: Sannenzaka and Ninenzaka | I56: 産寧坂・二寧坂 | J56: Sannenzaka and Ninenzaka | K56: 🏙️ Ciudad y barrios | L56: calles históricas | M56: B | N56: Bellísimas, pero la experiencia cae mucho en horas punta y parte del comercio es repetitivo. | O56: Pendientes de casas machiya entre Kiyomizu y Gion. | P56: El trazado y las cubiertas producen la postal urbana clásica de Kioto. | Q56: Pendientes de casas machiya entre Kiyomizu y Gion. | R56: 1–2 h | S56: Mañana | T56: Todo el año | U56: Extremo | V56: Extremo | W56: 0 | X56: 0 | Y56: =W56*'Configuración'!$B$4 | Z56: =X56*'Configuración'!$B$4 | AA56: No | AB56: — | AC56: Espacio público; comercios variables | AD56: Sin cierre | AE56: Kiyomizu-michi / Gojozaka | AF56: Buena en áreas principales; confirmar detalles con el recinto | AG56: 34.9976 | AH56: 135.7829 | AI56: https://kyoto.travel/en/ | AJ56: Cambiante | AK56: ICON / TOURISTY | AL56: fotografía, compras, arquitectura | AM56: 5 | AN56: 3 | AO56: 3 | AP56: 5 | AQ56: Imagen ideal: el trazado y las cubiertas producen la postal urbana clásica de kioto. con luz de mañana, sin multitudes dominando el encuadre. | AR56: Yasaka Kōshin-dō (~4 min a pie) | Kiyomizu-dera (~5 min a pie) | Kōdai-ji (~5 min a pie) | AS56: Popular / turístico | AU56: https://www.google.com/maps/search/?api=1&query=Sannenzaka%20and%20Ninenzaka%2C%20Kyoto%2C%20Japan | AV56: 2026-09-01 | AW56: CALENDARIO / CONDICIÓN PENDIENTE | AX56: No hay cierre específico confirmado para la ventana, pero horarios o acceso pueden variar. | AY56: Reconfirmar en la web oficial al fijar fechas.
A57: JP-056 | B57: Kioto | C57: Kansai | D57: Kioto | E57: Kyoto | F57: Higashiyama | G57: Kiyomizu–Gion | H57: Yasaka Kōshin-dō | I57: 八坂庚申堂 | J57: Yasaka Kōshin-dō | K57: ⛩️ Templos y santuarios | L57: templo | M57: D | N57: El atractivo viral de colores no compensa por sí solo el desvío ni la congestión. | O57: Pequeño templo cubierto de amuletos textiles de colores. | P57: Es fotogénico, pero la visita material es muy breve. | Q57: Pequeño templo cubierto de amuletos textiles de colores. | R57: 10–25 min | S57: Mañana | T57: Todo el año | U57: Extremo | V57: Extremo | W57: 0 | X57: 0 | Y57: =W57*'Configuración'!$B$4 | Z57: =X57*'Configuración'!$B$4 | AA57: No | AB57: — | AC57: Diurno | AD57: Sin cierre ordinario | AE57: Higashiyama; a pie desde Kiyomizu | AF57: Parcial; pueden existir escalones, grava o edificios sin elevador | AG57: 34.9995 | AH57: 135.7807 | AI57: https://kyoto.travel/en/ | AJ57: Cambiante | AK57: VIRAL / SKIP | AL57: fotografía | AM57: 4 | AN57: 2 | AO57: 1 | AP57: 5 | AQ57: Imagen ideal: es fotogénico, pero la visita material es muy breve. con luz de mañana, sin multitudes dominando el encuadre. | AR57: Kōdai-ji (~3 min a pie) | Sannenzaka and Ninenzaka (~4 min a pie) | Gion Corner (~7 min a pie) | AS57: Popular / turístico | AU57: https://www.google.com/maps/search/?api=1&query=Yasaka%20K%C5%8Dshin-d%C5%8D%2C%20Kyoto%2C%20Japan | AV57: 2026-09-01 | AW57: CALENDARIO / CONDICIÓN PENDIENTE | AX57: No hay cierre específico confirmado para la ventana, pero horarios o acceso pueden variar. | AY57: Reconfirmar en la web oficial al fijar fechas.
A58: JP-057 | B58: Kioto | C58: Kansai | D58: Kioto | E58: Kyoto | F58: Gion | G58: Kiyomizu–Gion | H58: Gion Shirakawa | I58: 祇園白川 | J58: Gion Shirakawa | K58: 🏙️ Ciudad y barrios | L58: barrio histórico | M58: A | N58: El canal y las fachadas ofrecen un Gion más legible que Hanamikoji en hora punta. | O58: Canal bordeado de sauces, puentes y ochaya tradicionales. | P58: Agua y baja escala suavizan la experiencia del distrito. | Q58: Canal bordeado de sauces, puentes y ochaya tradicionales. | R58: 45–90 min | S58: Atardecer | T58: Sakura y todo el año | U58: Alto | V58: Alto | W58: 0 | X58: 0 | Y58: =W58*'Configuración'!$B$4 | Z58: =X58*'Configuración'!$B$4 | AA58: No | AB58: — | AC58: Espacio público; respetar propiedades | AD58: Sin cierre | AE58: Keihan Gion-Shijo / Sanjo | AF58: Buena en áreas principales; confirmar detalles con el recinto | AG58: 35.0054 | AH58: 135.7733 | AI58: https://kyoto.travel/en/ | AJ58: Cambiante | AK58: CULTURE | AL58: pareja, fotografía, arquitectura | AM58: 5 | AN58: 4 | AO58: 4 | AP58: 4 | AQ58: Imagen ideal: agua y baja escala suavizan la experiencia del distrito. con luz de atardecer, sin multitudes dominando el encuadre. | AR58: Kennin-ji (~7 min a pie) | Gion Corner (~9 min a pie) | Nishiki Market (~11 min a pie) | AS58: Popular / turístico | AU58: https://www.google.com/maps/search/?api=1&query=Gion%20Shirakawa%2C%20Kyoto%2C%20Japan | AV58: 2026-09-01 | AW58: ABIERTO; FLORACIÓN NO GARANTIZADA | AX58: En Japón central la floración plena suele ser más tardía; finales de marzo es incierto. | AY58: No basar la visita en sakura hasta el pronóstico 2027.
A59: JP-058 | B59: Kioto | C59: Kansai | D59: Kioto | E59: Kyoto | F59: Gion | G59: Kiyomizu–Gion | H59: Kennin-ji | I59: 建仁寺 | J59: Kennin-ji | K59: ⛩️ Templos y santuarios | L59: templo zen | M59: A | N59: Excelente arte y jardines en pleno Gion con menos presión que los iconos mayores. | O59: Templo zen con dragones pintados, biombos y jardines secos. | P59: Ofrece interior, arte y contemplación, no solo una fachada. | Q59: Templo zen con dragones pintados, biombos y jardines secos. | R59: 1–1.5 h | S59: Mañana | T59: Todo el año | U59: Medio | V59: Medio | W59: 600 | X59: 600 | Y59: =W59*'Configuración'!$B$4 | Z59: =X59*'Configuración'!$B$4 | AA59: No | AB59: — | AC59: 10:00–16:30 aprox. | AD59: Variable | AE59: Gion-Shijo | AF59: Parcial; pueden existir escalones, grava o edificios sin elevador | AG59: 35.0007 | AH59: 135.7739 | AI59: https://www.kenninji.jp/english/ | AJ59: Cambiante | AK59: HIDDEN GEM | AL59: arte, cultura, jardines | AM59: 4 | AN59: 5 | AO59: 5 | AP59: 2 | AQ59: Imagen ideal: ofrece interior, arte y contemplación, no solo una fachada. con luz de mañana, sin multitudes dominando el encuadre. | AR59: Gion Corner (~3 min a pie) | Gion Shirakawa (~7 min a pie) | Yasaka Kōshin-dō (~9 min a pie) | AS59: Semi-hidden | AU59: https://www.google.com/maps/search/?api=1&query=Kennin-ji%2C%20Kyoto%2C%20Japan | AV59: 2026-09-01 | AW59: CALENDARIO / CONDICIÓN PENDIENTE | AX59: No hay cierre específico confirmado para la ventana, pero horarios o acceso pueden variar. | AY59: Reconfirmar en la web oficial al fijar fechas.
A60: JP-059 | B60: Kioto | C60: Kansai | D60: Kioto | E60: Kyoto | F60: Higashiyama | G60: Kiyomizu–Gion | H60: Kōdai-ji | I60: 高台寺 | J60: Kōdai-ji | K60: ⛩️ Templos y santuarios | L60: templo/jardín | M60: A | N60: Buen equilibrio de jardín, arquitectura, bambú y aperturas nocturnas. | O60: Complejo asociado a Nene, esposa de Toyotomi Hideyoshi. | P60: Concentra varios paisajes sin la escala industrial de Arashiyama. | Q60: Complejo asociado a Nene, esposa de Toyotomi Hideyoshi. | R60: 1–2 h | S60: Atardecer | T60: Otoño y eventos nocturnos | U60: Alto | V60: Alto | W60: 600 | X60: 600 | Y60: =W60*'Configuración'!$B$4 | Z60: =X60*'Configuración'!$B$4 | AA60: No | AB60: — | AC60: 09:00–17:30; iluminaciones variables | AD60: Sin cierre ordinario | AE60: Higashiyama; bus Higashiyama Yasui | AF60: Parcial; pueden existir escalones, grava o edificios sin elevador | AG60: 35.0007 | AH60: 135.781 | AI60: https://www.kodaiji.com/e_index.html | AJ60: Cambiante | AK60: CULTURE | AL60: pareja, jardines, historia, noche | AM60: 5 | AN60: 4 | AO60: 5 | AP60: 4 | AQ60: Imagen ideal: concentra varios paisajes sin la escala industrial de arashiyama. con luz de atardecer, sin multitudes dominando el encuadre. | AR60: Yasaka Kōshin-dō (~3 min a pie) | Sannenzaka and Ninenzaka (~5 min a pie) | Gion Corner (~7 min a pie) | AS60: Popular / turístico | AU60: https://www.google.com/maps/search/?api=1&query=K%C5%8Ddai-ji%2C%20Kyoto%2C%20Japan | AV60: 2026-09-01 | AW60: CALENDARIO / CONDICIÓN PENDIENTE | AX60: No hay cierre específico confirmado para la ventana, pero horarios o acceso pueden variar. | AY60: Reconfirmar en la web oficial al fijar fechas.
A61: JP-060 | B61: Kioto | C61: Kansai | D61: Kioto | E61: Kyoto | F61: Higashiyama | G61: Okazaki–Philosopher | H61: Nanzen-ji | I61: 南禅寺 | J61: Nanzen-ji | K61: ⛩️ Templos y santuarios | L61: templo zen | M61: A | N61: Escala, jardines y acueducto crean uno de los complejos más ricos de Kioto. Clasificación v2: excelente y muy recomendable, pero no justifica por sí sola adaptar la ruta. | O61: Gran monasterio zen con puerta monumental, subtemplos y acueducto Meiji. | P61: La yuxtaposición de ladrillo industrial y arquitectura religiosa es única. | Q61: Gran monasterio zen con puerta monumental, subtemplos y acueducto Meiji. | R61: 2–3 h | S61: Mañana | T61: Otoño | U61: Alto | V61: Alto | W61: 0 | X61: 1200 | Y61: =W61*'Configuración'!$B$4 | Z61: =X61*'Configuración'!$B$4 | AA61: No | AB61: — | AC61: Recinto diurno; subtemplos variables | AD61: Sin cierre ordinario | AE61: Keage | AF61: Parcial; pueden existir escalones, grava o edificios sin elevador | AG61: 35.0114 | AH61: 135.7945 | AI61: https://www.nanzenji.or.jp/en/ | AJ61: Cambiante | AK61: MUST SEE | AL61: arquitectura, jardines, historia, fotografía | AM61: 5 | AN61: 5 | AO61: 5 | AP61: 4 | AQ61: Imagen ideal: la yuxtaposición de ladrillo industrial y arquitectura religiosa es única. con luz de mañana, sin multitudes dominando el encuadre. | AR61: Eikan-dō (~5 min a pie) | Murin-an (~7 min a pie) | Hōnen-in (~18 min a pie) | AS61: Popular / turístico | AU61: https://www.google.com/maps/search/?api=1&query=Nanzen-ji%2C%20Kyoto%2C%20Japan | AV61: 2026-09-01 | AW61: CALENDARIO / CONDICIÓN PENDIENTE | AX61: No hay cierre específico confirmado para la ventana, pero horarios o acceso pueden variar. | AY61: Reconfirmar en la web oficial al fijar fechas.
A62: JP-061 | B62: Kioto | C62: Kansai | D62: Kioto | E62: Kyoto | F62: Keage | G62: Okazaki–Philosopher | H62: Murin-an | I62: 無鄰菴 | J62: Murin-an | K62: 🌸 Jardines y paisajes | L62: jardín | M62: A | N62: Uno de los jardines más refinados y tranquilos del centro, con control de aforo. Clasificación v2: excelente y muy recomendable, pero no justifica por sí sola adaptar la ruta. | O62: Villa Meiji y jardín de Ogawa Jihei alimentado por el canal Biwa. | P62: Paisaje naturalista íntimo diseñado para mirarse sentado. | Q62: Villa Meiji y jardín de Ogawa Jihei alimentado por el canal Biwa. | R62: 1–1.5 h | S62: Mañana | T62: Todo el año; otoño | U62: Bajo | V62: Bajo | W62: 600 | X62: 1200 | Y62: =W62*'Configuración'!$B$4 | Z62: =X62*'Configuración'!$B$4 | AA62: Recomendable | AB62: Días; temporada alta antes | AC62: Horario variable por temporada | AD62: 29–31 dic; verificar | AE62: Keage | AF62: Parcial; pueden existir escalones, grava o edificios sin elevador | AG62: 35.0101 | AH62: 135.7895 | AI62: https://murin-an.jp/en/ | AJ62: Cambiante | AK62: HIDDEN GEM | AL62: pareja, jardines, arquitectura | AM62: 5 | AN62: 5 | AO62: 5 | AP62: 1 | AQ62: Imagen ideal: paisaje naturalista íntimo diseñado para mirarse sentado. con luz de mañana, sin multitudes dominando el encuadre. | AR62: Nanzen-ji (~7 min a pie) | Eikan-dō (~9 min a pie) | Kōdai-ji (~18 min a pie) | AS62: Hidden Gem real | AU62: https://www.google.com/maps/search/?api=1&query=Murin-an%2C%20Kyoto%2C%20Japan | AV62: 2026-09-01 | AW62: CALENDARIO / CONDICIÓN PENDIENTE | AX62: No hay cierre específico confirmado para la ventana, pero horarios o acceso pueden variar. | AY62: Reconfirmar en la web oficial al fijar fechas.
A63: JP-062 | B63: Kioto | C63: Kansai | D63: Kioto | E63: Kyoto | F63: Eikando | G63: Okazaki–Philosopher | H63: Eikan-dō | I63: 永観堂 | J63: Eikan-dō | K63: ⛩️ Templos y santuarios | L63: templo/jardín | M63: A | N63: Uno de los mejores paisajes de otoño, aunque extremadamente concurrido en pico. | O63: Templo de ladera con corredor, pagoda y célebre arce. | P63: El recorrido vertical ofrece vistas y secuencias espaciales variadas. | Q63: Templo de ladera con corredor, pagoda y célebre arce. | R63: 1.5–2 h | S63: Mañana | T63: Otoño | U63: Extremo | V63: Alto | W63: 600 | X63: 1000 | Y63: =W63*'Configuración'!$B$4 | Z63: =X63*'Configuración'!$B$4 | AA63: No | AB63: — | AC63: 09:00–17:00 aprox. | AD63: Sin cierre ordinario | AE63: Keage + 15 min | AF63: Parcial; pueden existir escalones, grava o edificios sin elevador | AG63: 35.0144 | AH63: 135.7944 | AI63: https://www.eikando.or.jp/English/index_eng.html | AJ63: Cambiante | AK63: AUTUMN | AL63: jardines, cultura, fotografía | AM63: 5 | AN63: 4 | AO63: 4 | AP63: 5 | AQ63: Imagen ideal: el recorrido vertical ofrece vistas y secuencias espaciales variadas. con luz de mañana, sin multitudes dominando el encuadre. | AR63: Nanzen-ji (~5 min a pie) | Murin-an (~9 min a pie) | Hōnen-in (~13 min a pie) | AS63: Popular / turístico | AU63: https://www.google.com/maps/search/?api=1&query=Eikan-d%C5%8D%2C%20Kyoto%2C%20Japan | AV63: 2026-09-01 | AW63: CALENDARIO / CONDICIÓN PENDIENTE | AX63: No hay cierre específico confirmado para la ventana, pero horarios o acceso pueden variar. | AY63: Reconfirmar en la web oficial al fijar fechas.
A64: JP-063 | B64: Kioto | C64: Kansai | D64: Kioto | E64: Kyoto | F64: Sakyo | G64: Okazaki–Philosopher | H64: Philosopher's Path | I64: 哲学の道 | J64: Philosopher's Path | K64: 🌸 Jardines y paisajes | L64: paseo | M64: B | N64: Agradable con floración; fuera de temporada puede sentirse ordinario. | O64: Sendero junto a un canal entre Nanzen-ji y Ginkaku-ji. | P64: Conecta templos menores y vida residencial a ritmo lento. | Q64: Sendero junto a un canal entre Nanzen-ji y Ginkaku-ji. | R64: 1–2 h | S64: Mañana | T64: Sakura y otoño | U64: Extremo | V64: Alto | W64: 0 | X64: 0 | Y64: =W64*'Configuración'!$B$4 | Z64: =X64*'Configuración'!$B$4 | AA64: No | AB64: — | AC64: Espacio público 24 h | AD64: Sin cierre | AE64: Ginkakuji-mae / Keage | AF64: Buena en áreas principales; confirmar detalles con el recinto | AG64: 35.0268 | AH64: 135.7982 | AI64: https://kyoto.travel/en/ | AJ64: Cambiante | AK64: SEASONAL | AL64: pareja, caminar, fotografía | AM64: 4 | AN64: 3 | AO64: 3 | AP64: 4 | AQ64: Imagen ideal: conecta templos menores y vida residencial a ritmo lento. con luz de mañana, sin multitudes dominando el encuadre. | AR64: Ginkaku-ji (~3 min a pie) | Hōnen-in (~7 min a pie) | Eikan-dō (~20 min a pie) | AS64: Popular / turístico | AU64: https://www.google.com/maps/search/?api=1&query=Philosopher's%20Path%2C%20Kyoto%2C%20Japan | AV64: 2026-09-01 | AW64: ABIERTO; FLORACIÓN NO GARANTIZADA | AX64: En Japón central la floración plena suele ser más tardía; finales de marzo es incierto. | AY64: No basar la visita en sakura hasta el pronóstico 2027.
A65: JP-064 | B65: Kioto | C65: Kansai | D65: Kioto | E65: Kyoto | F65: Sakyo | G65: Okazaki–Philosopher | H65: Hōnen-in | I65: 法然院 | J65: Hōnen-in | K65: ⛩️ Templos y santuarios | L65: templo | M65: A | N65: Pequeño, musgoso y genuinamente tranquilo a metros del eje turístico. | O65: Puerta de paja, montículos de arena y bosque en la ladera. | P65: Su atmósfera depende del silencio, no de una gran obra icónica. | Q65: Puerta de paja, montículos de arena y bosque en la ladera. | R65: 30–60 min | S65: Mañana | T65: Primavera y otoño | U65: Bajo | V65: Bajo | W65: 0 | X65: 0 | Y65: =W65*'Configuración'!$B$4 | Z65: =X65*'Configuración'!$B$4 | AA65: No | AB65: — | AC65: 06:00–16:00 aprox.; interiores especiales | AD65: Interiores limitados | AE65: Bus Ginkakuji-mae + paseo | AF65: Parcial; pueden existir escalones, grava o edificios sin elevador | AG65: 35.0222 | AH65: 135.7985 | AI65: https://kyoto.travel/en/ | AJ65: Cambiante | AK65: HIDDEN GEM | AL65: pareja, cultura, fotografía | AM65: 4 | AN65: 5 | AO65: 5 | AP65: 1 | AQ65: Imagen ideal: su atmósfera depende del silencio, no de una gran obra icónica. con luz de mañana, sin multitudes dominando el encuadre. | AR65: Philosopher's Path (~7 min a pie) | Ginkaku-ji (~7 min a pie) | Eikan-dō (~13 min a pie) | AS65: Hidden Gem real | AU65: https://www.google.com/maps/search/?api=1&query=H%C5%8Dnen-in%2C%20Kyoto%2C%20Japan | AV65: 2026-09-01 | AW65: CALENDARIO / CONDICIÓN PENDIENTE | AX65: No hay cierre específico confirmado para la ventana, pero horarios o acceso pueden variar. | AY65: Reconfirmar en la web oficial al fijar fechas.
... A70: JP-069 | B70: Kioto | C70: Kansai | D70: Kioto | E70: Kyoto | F70: Yamashina | G70: Yamashina | H70: Bishamon-dō | I70: 毘沙門堂 | J70: Bishamon-dō | K70: ⛩️ Templos y santuarios | L70: templo | M70: A | N70: Templo estacional excelente con muy poco turismo internacional. | O70: Templo de montaña con arces, cerezos llorones y pinturas interiores. | P70: Ofrece gran color y escala íntima sin excursión larga. | Q70: Templo de montaña con arces, cerezos llorones y pinturas interiores. | R70: 1–1.5 h | S70: Mañana | T70: Otoño y primavera | U70: Medio | V70: Bajo | W70: 500 | X70: 500 | Y70: =W70*'Configuración'!$B$4 | Z70: =X70*'Configuración'!$B$4 | AA70: No | AB70: — | AC70: 09:00–17:00 aprox. | AD70: Sin cierre ordinario | AE70: JR/Metro Yamashina + 20 min | AF70: Parcial; pueden existir escalones, grava o edificios sin elevador | AG70: 35.0067 | AH70: 135.8176 | AI70: https://kyoto.travel/en/hidden-gems/yamashina/ | AJ70: Cambiante | AK70: HIDDEN GEM | AL70: fotografía, cultura, naturaleza | AM70: 5 | AN70: 5 | AO70: 5 | AP70: 1 | AQ70: Imagen ideal: ofrece gran color y escala íntima sin excursión larga. con luz de mañana, sin multitudes dominando el encuadre. | AR70: Yamashina Canal (~5 min a pie) | Nanzen-ji (~30 min en transporte) | Eikan-dō (~32 min en transporte) | AS70: Hidden Gem real | AU70: https://www.google.com/maps/search/?api=1&query=Bishamon-d%C5%8D%2C%20Kyoto%2C%20Japan | AV70: 2026-09-01 | AW70: CALENDARIO / CONDICIÓN PENDIENTE | AX70: No hay cierre específico confirmado para la ventana, pero horarios o acceso pueden variar. | AY70: Reconfirmar en la web oficial al fijar fechas.
A71: JP-070 | B71: Kioto | C71: Kansai | D71: Kioto | E71: Kyoto | F71: Yamashina | G71: Yamashina | H71: Yamashina Canal | I71: 山科疏水 | J71: Yamashina Canal | K71: 🌿 Naturaleza | L71: paseo/canal | M71: A | N71: Paseo local sencillo y bello, especialmente en floración. | O71: Tramo arbolado del canal del lago Biwa con senderos tranquilos. | P71: Une ingeniería Meiji, paisaje y barrios no turísticos. | Q71: Tramo arbolado del canal del lago Biwa con senderos tranquilos. | R71: 1.5–3 h | S71: Mañana | T71: Sakura y otoño | U71: Bajo | V71: Bajo | W71: 0 | X71: 0 | Y71: =W71*'Configuración'!$B$4 | Z71: =X71*'Configuración'!$B$4 | AA71: No | AB71: — | AC71: Espacio público 24 h | AD71: Sin cierre | AE71: JR/Metro Yamashina | AF71: Buena en áreas principales; confirmar detalles con el recinto | AG71: 35.008 | AH71: 135.814 | AI71: https://kyoto.travel/en/hidden-gems/yamashina/ | AJ71: Cambiante | AK71: HIDDEN GEM | AL71: pareja, caminar, naturaleza, fotografía | AM71: 4 | AN71: 5 | AO71: 5 | AP71: 1 | AQ71: Imagen ideal: une ingeniería meiji, paisaje y barrios no turísticos. con luz de mañana, sin multitudes dominando el encuadre. | AR71: Bishamon-dō (~5 min a pie) | Nanzen-ji (~25 min en transporte) | Eikan-dō (~27 min en transporte) | AS71: Hidden Gem real | AT71: Philosopher's Path | AU71: https://www.google.com/maps/search/?api=1&query=Yamashina%20Canal%2C%20Kyoto%2C%20Japan | AV71: 2026-09-01 | AW71: ABIERTO; FLORACIÓN NO GARANTIZADA | AX71: En Japón central la floración plena suele ser más tardía; finales de marzo es incierto. | AY71: No basar la visita en sakura hasta el pronóstico 2027.
A72: JP-071 | B72: Kioto | C72: Kansai | D72: Kioto | E72: Kyoto | F72: Arashiyama | G72: Arashiyama | H72: Arashiyama Bamboo Grove | I72: 嵯峨野竹林の小径 | J72: Arashiyama Bamboo Grove | K72: 🌿 Naturaleza | L72: bosque/paseo | M72: C | N72: La imagen es icónica, pero el tramo es corto y la saturación extrema. | O72: Camino entre altos bambúes junto a Tenryu-ji. | P72: Funciona mejor como conexión dentro de Arashiyama que como destino aislado. | Q72: Camino entre altos bambúes junto a Tenryu-ji. | R72: 20–45 min | S72: Muy temprano | T72: Todo el año | U72: Extremo | V72: Extremo | W72: 0 | X72: 0 | Y72: =W72*'Configuración'!$B$4 | Z72: =X72*'Configuración'!$B$4 | AA72: No | AB72: — | AC72: Espacio público 24 h | AD72: Sin cierre | AE72: JR Saga-Arashiyama / Randen Arashiyama | AF72: Parcial o baja; terreno irregular y condiciones naturales | AG72: 35.017 | AH72: 135.6713 | AI72: https://kyoto.travel/en/ | AJ72: Verificado | AK72: VIRAL / OPTIONAL | AL72: fotografía, naturaleza | AM72: 5 | AN72: 2 | AO72: 2 | AP72: 5 | AQ72: Imagen ideal: funciona mejor como conexión dentro de arashiyama que como destino aislado. con luz de muy temprano, sin multitudes dominando el encuadre. | AR72: Ōkōchi Sansō Garden (~3 min a pie) | Tenryū-ji (~4 min a pie) | Giō-ji (~10 min a pie) | AS72: Popular / turístico | AU72: https://www.google.com/maps/search/?api=1&query=Arashiyama%20Bamboo%20Grove%2C%20Kyoto%2C%20Japan | AV72: 2026-09-01 | AW72: ABIERTO PREVISTO | AX72: No se conoce un cierre específico para febrero–marzo de 2027 al corte. | AY72: Revisar horario final 2–4 semanas antes.
A73: JP-072 | B73: Kioto | C73: Kansai | D73: Kioto | E73: Kyoto | F73: Arashiyama | G73: Arashiyama | H73: Tenryū-ji | I73: 天龍寺 | J73: Tenryū-ji | K73: ⛩️ Templos y santuarios | L73: templo/jardín | M73: A | N73: El jardín histórico sí justifica Arashiyama aun si el bambusal decepciona. | O73: Templo zen con jardín Sogenchi y montañas prestadas. | P73: El paisaje integra estanque, templo y Arashiyama como una sola composición. | Q73: Templo zen con jardín Sogenchi y montañas prestadas. | R73: 1–1.5 h | S73: Mañana | T73: Otoño y primavera | U73: Extremo | V73: Extremo | W73: 500 | X73: 800 | Y73: =W73*'Configuración'!$B$4 | Z73: =X73*'Configuración'!$B$4 | AA73: No | AB73: — | AC73: 08:30–17:00 aprox. | AD73: Sin cierre ordinario | AE73: Randen Arashiyama | AF73: Parcial; pueden existir escalones, grava o edificios sin elevador | AG73: 35.0157 | AH73: 135.6738 | AI73: https://www.tenryuji.com/en/ | AJ73: Cambiante | AK73: GARDEN | AL73: jardines, cultura, fotografía | AM73: 5 | AN73: 4 | AO73: 5 | AP73: 5 | AQ73: Imagen ideal: el paisaje integra estanque, templo y arashiyama como una sola composición. con luz de mañana, sin multitudes dominando el encuadre. | AR73: Arashiyama Bamboo Grove (~4 min a pie) | Ōkōchi Sansō Garden (~6 min a pie) | Giō-ji (~13 min a pie) | AS73: Popular / turístico | AU73: https://www.google.com/maps/search/?api=1&query=Tenry%C5%AB-ji%2C%20Kyoto%2C%20Japan | AV73: 2026-09-01 | AW73: CALENDARIO / CONDICIÓN PENDIENTE | AX73: No hay cierre específico confirmado para la ventana, pero horarios o acceso pueden variar. | AY73: Reconfirmar en la web oficial al fijar fechas.
A74: JP-073 | B74: Kioto | C74: Kansai | D74: Kioto | E74: Kyoto | F74: Arashiyama | G74: Arashiyama | H74: Ōkōchi Sansō Garden | I74: 大河内山荘庭園 | J74: Ōkōchi Sansō Garden | K74: 🌸 Jardines y paisajes | L74: jardín/villa | M74: A | N74: La mejor recompensa tras el bambusal: vistas, senderos y aforo moderado. | O74: Antigua villa del actor Ōkōchi Denjirō con jardines en ladera. | P74: Tiene panoramas de Kyoto y montañas que el bambusal no ofrece. | Q74: Antigua villa del actor Ōkōchi Denjirō con jardines en ladera. | R74: 1–1.5 h | S74: Mañana | T74: Otoño | U74: Medio | V74: Medio | W74: 1000 | X74: 1000 | Y74: =W74*'Configuración'!$B$4 | Z74: =X74*'Configuración'!$B$4 | AA74: No | AB74: — | AC74: 09:00–17:00 aprox. | AD74: Sin cierre ordinario | AE74: Arashiyama; salida norte del bambusal | AF74: Parcial; pueden existir escalones, grava o edificios sin elevador | AG74: 35.0168 | AH74: 135.6689 | AI74: https://kyoto.travel/en/ | AJ74: Cambiante | AK74: ALTERNATIVE | AL74: pareja, jardines, fotografía | AM74: 5 | AN74: 5 | AO74: 5 | AP74: 2 | AQ74: Imagen ideal: tiene panoramas de kyoto y montañas que el bambusal no ofrece. con luz de mañana, sin multitudes dominando el encuadre. | AR74: Arashiyama Bamboo Grove (~3 min a pie) | Tenryū-ji (~6 min a pie) | Giō-ji (~9 min a pie) | AS74: Alternativa menos saturada | AT74: Arashiyama Bamboo Grove | AU74: https://www.google.com/maps/search/?api=1&query=%C5%8Ck%C5%8Dchi%20Sans%C5%8D%20Garden%2C%20Kyoto%2C%20Japan | AV74: 2026-09-01 | AW74: CALENDARIO / CONDICIÓN PENDIENTE | AX74: No hay cierre específico confirmado para la ventana, pero horarios o acceso pueden variar. | AY74: Reconfirmar en la web oficial al fijar fechas.
A75: JP-074 | B75: Kioto | C75: Kansai | D75: Kioto | E75: Kyoto | F75: Saga-Toriimoto | G75: Arashiyama North | H75: Giō-ji | I75: 祇王寺 | J75: Giō-ji | K75: ⛩️ Templos y santuarios | L75: templo/jardín de musgo | M75: A | N75: Uno de los recintos de musgo más íntimos y emocionales de Arashiyama. | O75: Pequeño templo de monjas con jardín de musgo y bambú. | P75: La escala y silencio son opuestos al corredor turístico principal. | Q75: Pequeño templo de monjas con jardín de musgo y bambú. | R75: 45–75 min | S75: Mañana | T75: Temporada húmeda y otoño | U75: Bajo | V75: Bajo | W75: 300 | X75: 300 | Y75: =W75*'Configuración'!$B$4 | Z75: =X75*'Configuración'!$B$4 | AA75: No | AB75: — | AC75: 09:00–16:30 aprox. | AD75: Inicio de año; verificar | AE75: Bus Saga Shakado-mae + paseo | AF75: Parcial; pueden existir escalones, grava o edificios sin elevador | AG75: 35.0222 | AH75: 135.6669 | AI75: https://www.giouji.or.jp/en/ | AJ75: Cambiante | AK75: HIDDEN GEM | AL75: pareja, jardines, cultura | AM75: 4 | AN75: 5 | AO75: 5 | AP75: 1 | AQ75: Imagen ideal: la escala y silencio son opuestos al corredor turístico principal. con luz de mañana, sin multitudes dominando el encuadre. | AR75: Adashino Nenbutsu-ji (~8 min a pie) | Ōkōchi Sansō Garden (~9 min a pie) | Arashiyama Bamboo Grove (~10 min a pie) | AS75: Hidden Gem real | AU75: https://www.google.com/maps/search/?api=1&query=Gi%C5%8D-ji%2C%20Kyoto%2C%20Japan | AV75: 2026-09-01 | AW75: CALENDARIO / CONDICIÓN PENDIENTE | AX75: No hay cierre específico confirmado para la ventana, pero horarios o acceso pueden variar. | AY75: Reconfirmar en la web oficial al fijar fechas.
A76: JP-075 | B76: Kioto | C76: Kansai | D76: Kioto | E76: Kyoto | F76: Saga-Toriimoto | G76: Arashiyama North | H76: Otagi Nenbutsu-ji | I76: 愛宕念仏寺 | J76: Otagi Nenbutsu-ji | K76: ⛩️ Templos y santuarios | L76: templo | M76: A | N76: Más de mil rakan expresivos crean una experiencia artística y espiritual singular. Clasificación v2: excelente y muy recomendable, pero no justifica por sí sola adaptar la ruta. | O76: Templo de montaña con 1,200 estatuas de discípulos talladas por visitantes. | P76: Cada rostro es distinto; mezcla humor, oficio y memoria comunitaria. | Q76: Templo de montaña con 1,200 estatuas de discípulos talladas por visitantes. | R76: 1–1.5 h | S76: Mañana | T76: Todo el año; otoño | U76: Bajo | V76: Bajo | W76: 500 | X76: 500 | Y76: =W76*'Configuración'!$B$4 | Z76: =X76*'Configuración'!$B$4 | AA76: No | AB76: — | AC76: 08:00–16:30 aprox. | AD76: Sin cierre ordinario | AE76: Bus Otagidera-mae | AF76: Parcial; pueden existir escalones, grava o edificios sin elevador | AG76: 35.031 | AH76: 135.6617 | AI76: https://www.otagiji.com/ | AJ76: Cambiante | AK76: HIDDEN GEM | AL76: fotografía, cultura, arte | AM76: 5 | AN76: 5 | AO76: 5 | AP76: 1 | AQ76: Imagen ideal: cada rostro es distinto; mezcla humor, oficio y memoria comunitaria. con luz de mañana, sin multitudes dominando el encuadre. | AR76: Adashino Nenbutsu-ji (~7 min a pie) | Giō-ji (~15 min a pie) | Ōkōchi Sansō Garden (~24 min a pie) | AS76: Hidden Gem real | AT76: Templos centrales saturados | AU76: https://www.google.com/maps/search/?api=1&query=Otagi%20Nenbutsu-ji%2C%20Kyoto%2C%20Japan | AV76: 2026-09-01 | AW76: CALENDARIO / CONDICIÓN PENDIENTE | AX76: No hay cierre específico confirmado para la ventana, pero horarios o acceso pueden variar. | AY76: Reconfirmar en la web oficial al fijar fechas.
A77: JP-076 | B77: Kioto | C77: Kansai | D77: Kioto | E77: Kyoto | F77: Saga-Toriimoto | G77: Arashiyama North | H77: Adashino Nenbutsu-ji | I77: 化野念仏寺 | J77: Adashino Nenbutsu-ji | K77: ⛩️ Templos y santuarios | L77: templo/cementerio | M77: A | N77: Miles de piedras memoriales y un pequeño bambusal ofrecen una alternativa más profunda. | O77: Templo funerario con Sai no Kawara y sendero de bambú. | P77: El paisaje habla de memoria y abandono, no solo de fotografía. | Q77: Templo funerario con Sai no Kawara y sendero de bambú. | R77: 1–1.5 h | S77: Mañana | T77: Otoño | U77: Medio | V77: Medio | W77: 500 | X77: 500 | Y77: =W77*'Configuración'!$B$4 | Z77: =X77*'Configuración'!$B$4 | AA77: No | AB77: — | AC77: 09:00–16:30 aprox. | AD77: Variable | AE77: Bus Toriimoto | AF77: Parcial; pueden existir escalones, grava o edificios sin elevador | AG77: 35.0268 | AH77: 135.6637 | AI77: http://www.nenbutsuji.jp/ | AJ77: Cambiante | AK77: ALTERNATIVE | AL77: historia, fotografía, cultura | AM77: 5 | AN77: 5 | AO77: 5 | AP77: 2 | AQ77: Imagen ideal: el paisaje habla de memoria y abandono, no solo de fotografía. con luz de mañana, sin multitudes dominando el encuadre. | AR77: Otagi Nenbutsu-ji (~7 min a pie) | Giō-ji (~8 min a pie) | Ōkōchi Sansō Garden (~17 min a pie) | AS77: Alternativa menos saturada | AT77: Arashiyama Bamboo Grove | AU77: https://www.google.com/maps/search/?api=1&query=Adashino%20Nenbutsu-ji%2C%20Kyoto%2C%20Japan | AV77: 2026-09-01 | AW77: CALENDARIO / CONDICIÓN PENDIENTE | AX77: No hay cierre específico confirmado para la ventana, pero horarios o acceso pueden variar. | AY77: Reconfirmar en la web oficial al fijar fechas.
A78: JP-077 | B78: Kioto | C78: Kansai | D78: Kioto | E78: Kyoto | F78: Nishikyo | G78: Nishikyo | H78: Katsura Imperial Villa | I78: 桂離宮 | J78: Katsura Imperial Villa | K78: 🌸 Jardines y paisajes | L78: villa/jardín | M78: S | N78: Obra maestra absoluta de arquitectura y jardín japonés; exige planificación. | O78: Villa imperial del siglo XVII visitable solo en tour oficial. | P78: La secuencia de vistas y casas de té influyó en la arquitectura moderna mundial. | Q78: Villa imperial del siglo XVII visitable solo en tour oficial. | R78: 1.5 h | S78: Mañana | T78: Todo el año; primavera/otoño | U78: Bajo | V78: Bajo | W78: 1000 | X78: 1000 | Y78: =W78*'Configuración'!$B$4 | Z78: =X78*'Configuración'!$B$4 | AA78: Sí | AB78: Semanas; cupo limitado | AC78: Tours en horas fijas | AD78: Lunes y calendario imperial | AE78: Hankyu Katsura + bus/taxi | AF78: Parcial; pueden existir escalones, grava o edificios sin elevador | AG78: 34.9837 | AH78: 135.709 | AI78: https://kyoto-gosho.kunaicho.go.jp/en/katsura-rikyu/visit | AJ78: Cambiante | AK78: MUST SEE / RESERVE | AL78: arquitectura, jardines, cultura | AM78: 5 | AN78: 5 | AO78: 4 | AP78: 1 | AQ78: Imagen ideal: la secuencia de vistas y casas de té influyó en la arquitectura moderna mundial. con luz de mañana, sin multitudes dominando el encuadre. | AR78: Saiho-ji (Koke-dera) (~33 min en transporte) | Kyoto Rakusai Bamboo Park (~53 min en transporte) | AS78: Lugar conocido pero excelente | AU78: https://www.google.com/maps/search/?api=1&query=Katsura%20Imperial%20Villa%2C%20Kyoto%2C%20Japan | AV78: 2026-09-01 | AW78: CALENDARIO / CONDICIÓN PENDIENTE | AX78: No hay cierre específico confirmado para la ventana, pero horarios o acceso pueden variar. | AY78: Reconfirmar en la web oficial al fijar fechas.
A79: JP-078 | B79: Kioto | C79: Kansai | D79: Kioto | E79: Kyoto | F79: Nishikyo | G79: Nishikyo | H79: Saiho-ji (Koke-dera) | I79: 西芳寺（苔寺） | J79: Saiho-ji (Koke-dera) | K79: 🌸 Jardines y paisajes | L79: templo/jardín de musgo | M79: A | N79: Jardín extraordinario con acceso controlado; caro pero sereno. | O79: Templo zen famoso por su musgo y práctica de sutra previa. | P79: La reserva y ritual filtran multitudes y cambian el ritmo de visita. | Q79: Templo zen famoso por su musgo y práctica de sutra previa. | R79: 1.5–2 h | S79: Mañana | T79: Temporada húmeda y otoño | U79: Bajo | V79: Medio | W79: 4000 | X79: 4000 | Y79: =W79*'Configuración'!$B$4 | Z79: =X79*'Configuración'!$B$4 | AA79: Sí | AB79: Semanas; según sistema oficial | AC79: Horario asignado | AD79: Variable | AE79: Bus Kokedera/Suzumushi-dera | AF79: Parcial; pueden existir escalones, grava o edificios sin elevador | AG79: 34.9911 | AH79: 135.6846 | AI79: https://saihoji-kokedera.com/en/ | AJ79: Cambiante | AK79: RESERVE / GARDEN | AL79: pareja, jardines, cultura | AM79: 5 | AN79: 5 | AO79: 3 | AP79: 2 | AQ79: Imagen ideal: la reserva y ritual filtran multitudes y cambian el ritmo de visita. con luz de mañana, sin multitudes dominando el encuadre. | AR79: Katsura Imperial Villa (~33 min en transporte) | Kyoto Rakusai Bamboo Park (~50 min en transporte) | AS79: Lugar conocido pero excelente | AU79: https://www.google.com/maps/search/?api=1&query=Saiho-ji%20(Koke-dera)%2C%20Kyoto%2C%20Japan | AV79: 2026-09-01 | AW79: CALENDARIO / CONDICIÓN PENDIENTE | AX79: No hay cierre específico confirmado para la ventana, pero horarios o acceso pueden variar. | AY79: Reconfirmar en la web oficial al fijar fechas.
A80: JP-079 | B80: Kioto | C80: Kansai | D80: Kioto | E80: Kyoto | F80: Nishikyo | G80: Nishikyo | H80: Kyoto Rakusai Bamboo Park | I80: 京都市洛西竹林公園 | J80: Kyoto Rakusai Bamboo Park | K80: 🌿 Naturaleza | L80: jardín/museo de bambú | M80: A | N80: Alternativa real con 110 variedades y un paseo de bambú largo y tranquilo. | O80: Parque gratuito especializado en bambú y museo. | P80: Es botánico y local, no una sola calle para fotos. | Q80: Parque gratuito especializado en bambú y museo. | R80: 1.5–3 h | S80: Mañana | T80: Todo el año | U80: Bajo | V80: Bajo | W80: 0 | X80: 0 | Y80: =W80*'Configuración'!$B$4 | Z80: =X80*'Configuración'!$B$4 | AA80: No | AB80: — | AC80: 09:00–17:00 aprox. | AD80: Miércoles y fin de año; verificar | AE80: Rakusai-guchi + bus/bici | AF80: Parcial; pueden existir escalones, grava o edificios sin elevador | AG80: 34.9589 | AH80: 135.6801 | AI80: https://kyoto.travel/en/hidden-gems/hidden-gems-of-kyoto-nishikyo/ | AJ80: Cambiante | AK80: HIDDEN GEM | AL80: naturaleza, fotografía, diseño | AM80: 4 | AN80: 5 | AO80: 5 | AP80: 1 | AQ80: Imagen ideal: es botánico y local, no una sola calle para fotos. con luz de mañana, sin multitudes dominando el encuadre. | AR80: Saiho-ji (Koke-dera) (~50 min en transporte) | Katsura Imperial Villa (~53 min en transporte) | AS80: Alternativa menos saturada | AT80: Arashiyama Bamboo Grove | AU80: https://www.google.com/maps/search/?api=1&query=Kyoto%20Rakusai%20Bamboo%20Park%2C%20Kyoto%2C%20Japan | AV80: 2026-09-01 | AW80: CALENDARIO / CONDICIÓN PENDIENTE | AX80: No hay cierre específico confirmado para la ventana, pero horarios o acceso pueden variar. | AY80: Reconfirmar en la web oficial al fijar fechas.
A81: JP-080 | B81: Kioto | C81: Kansai | D81: Kioto | E81: Kyoto | F81: Kinugasa | G81: North Kyoto | H81: Kinkaku-ji | I81: 金閣寺 | J81: Kinkaku-ji | K81: ⛩️ Templos y santuarios | L81: templo/jardín | M81: B | N81: La imagen es única, pero el recorrido es unidireccional y muy saturado. Clasificación v2: recomendable si encaja; su valor depende más de interés, saturación o logística. | O81: Pabellón dorado reflejado en un estanque dentro de un jardín. | P81: Es una obra visual instantánea más que una experiencia contemplativa larga. | Q81: Pabellón dorado reflejado en un estanque dentro de un jardín. | R81: 45–90 min | S81: Mañana | T81: Invierno con nieve; todo el año | U81: Extremo | V81: Extremo | W81: 500 | X81: 500 | Y81: =W81*'Configuración'!$B$4 | Z81: =X81*'Configuración'!$B$4 | AA81: No | AB81: — | AC81: 09:00–17:00 | AD81: Sin cierre ordinario | AE81: Bus Kinkakuji-michi | AF81: Parcial; pueden existir escalones, grava o edificios sin elevador | AG81: 35.0394 | AH81: 135.7292 | AI81: https://www.shokoku-ji.jp/en/kinkakuji/ | AJ81: Cambiante | AK81: ICON | AL81: fotografía, arquitectura, cultura | AM81: 5 | AN81: 3 | AO81: 3 | AP81: 5 | AQ81: Imagen ideal: es una obra visual instantánea más que una experiencia contemplativa larga. con luz de mañana, sin multitudes dominando el encuadre. | AR81: Ryōan-ji (~16 min a pie) | Genkō-an (~21 min a pie) | Daitoku-ji subtemples (~23 min a pie) | AS81: Popular / turístico | AU81: https://www.google.com/maps/search/?api=1&query=Kinkaku-ji%2C%20Kyoto%2C%20Japan | AV81: 2026-09-01 | AW81: CALENDARIO / CONDICIÓN PENDIENTE | AX81: No hay cierre específico confirmado para la ventana, pero horarios o acceso pueden variar. | AY81: Reconfirmar en la web oficial al fijar fechas.
A82: JP-081 | B82: Kioto | C82: Kansai | D82: Kioto | E82: Kyoto | F82: Kinugasa | G82: North Kyoto | H82: Ryōan-ji | I82: 龍安寺 | J82: Ryōan-ji | K82: 🌸 Jardines y paisajes | L82: templo/jardín zen | M82: A | N82: El jardín seco canónico merece verse, aunque la contemplación depende de la hora. | O82: Templo con el jardín de rocas zen más famoso del mundo. | P82: Su ambigüedad espacial es la experiencia, no un relato histórico. | Q82: Templo con el jardín de rocas zen más famoso del mundo. | R82: 1–1.5 h | S82: Mañana | T82: Todo el año | U82: Alto | V82: Alto | W82: 600 | X82: 600 | Y82: =W82*'Configuración'!$B$4 | Z82: =X82*'Configuración'!$B$4 | AA82: No | AB82: — | AC82: 08:00–17:00 según temporada | AD82: Sin cierre ordinario | AE82: Randen Ryoanji / bus | AF82: Parcial; pueden existir escalones, grava o edificios sin elevador | AG82: 35.0345 | AH82: 135.7183 | AI82: http://www.ryoanji.jp/smph/eng/ | AJ82: Cambiante | AK82: ZEN | AL82: diseño, cultura, jardines | AM82: 4 | AN82: 5 | AO82: 4 | AP82: 4 | AQ82: Imagen ideal: su ambigüedad espacial es la experiencia, no un relato histórico. con luz de mañana, sin multitudes dominando el encuadre. | AR82: Kinkaku-ji (~16 min a pie) | Uzumasa Kyoto Village / Toei Kyoto Studio Park (~31 min en transporte) | Genkō-an (~35 min en transporte) | AS82: Popular / turístico | AU82: https://www.google.com/maps/search/?api=1&query=Ry%C5%8Dan-ji%2C%20Kyoto%2C%20Japan | AV82: 2026-09-01 | AW82: CALENDARIO / CONDICIÓN PENDIENTE | AX82: No hay cierre específico confirmado para la ventana, pero horarios o acceso pueden variar. | AY82: Reconfirmar en la web oficial al fijar fechas.
A83: JP-082 | B83: Kioto | C83: Kansai | D83: Kioto | E83: Kyoto | F83: Murasakino | G83: North Kyoto | H83: Daitoku-ji subtemples | I83: 大徳寺塔頭 | J83: Daitoku-ji subtemples | K83: ⛩️ Templos y santuarios | L83: complejo zen | M83: A | N83: La mejor área para profundizar en jardines zen sin multitudes constantes. Clasificación v2: excelente y muy recomendable, pero no justifica por sí sola adaptar la ruta. | O83: Gran monasterio con subtemplos de aperturas y jardines distintos. | P83: La selección de un subtemplo cambia la experiencia; no es un circuito masivo. | Q83: Gran monasterio con subtemplos de aperturas y jardines distintos. | R83: 2–4 h | S83: Mañana | T83: Todo el año; otoño | U83: Bajo | V83: Bajo | W83: 0 | X83: 2000 | Y83: =W83*'Configuración'!$B$4 | Z83: =X83*'Configuración'!$B$4 | AA83: No | AB83: — | AC83: Subtemplos y aperturas variables | AD83: Muchos cierres/aperturas especiales | AE83: Bus Daitokuji-mae | AF83: Buena en áreas principales; confirmar detalles con el recinto | AG83: 35.0439 | AH83: 135.7464 | AI83: https://kyoto.travel/en/ | AJ83: Cambiante | AK83: HIDDEN GEM | AL83: jardines, cultura, arquitectura | AM83: 5 | AN83: 5 | AO83: 5 | AP83: 1 | AQ83: Imagen ideal: la selección de un subtemplo cambia la experiencia; no es un circuito masivo. con luz de mañana, sin multitudes dominando el encuadre. | AR83: Genkō-an (~18 min a pie) | Kinkaku-ji (~23 min a pie) | Ryōan-ji (~39 min en transporte) | AS83: Hidden Gem real | AU83: https://www.google.com/maps/search/?api=1&query=Daitoku-ji%20subtemples%2C%20Kyoto%2C%20Japan | AV83: 2026-09-01 | AW83: CALENDARIO / CONDICIÓN PENDIENTE | AX83: No hay cierre específico confirmado para la ventana, pero horarios o acceso pueden variar. | AY83: Reconfirmar en la web oficial al fijar fechas.
A84: JP-083 | B84: Kioto | C84: Kansai | D84: Kioto | E84: Kyoto | F84: Takagamine | G84: North Kyoto | H84: Genkō-an | I84: 源光庵 | J84: Genkō-an | K84: ⛩️ Templos y santuarios | L84: templo | M84: A | N84: Las ventanas circular y cuadrada enmarcan una experiencia visual y filosófica memorable. | O84: Templo sereno conocido por las ventanas de iluminación y confusión. | P84: Arquitectura simple convierte el jardín en dos imágenes conceptuales. | Q84: Templo sereno conocido por las ventanas de iluminación y confusión. | R84: 45–75 min | S84: Mañana | T84: Otoño | U84: Medio | V84: Bajo | W84: 500 | X84: 500 | Y84: =W84*'Configuración'!$B$4 | Z84: =X84*'Configuración'!$B$4 | AA84: No | AB84: — | AC84: 09:00–17:00 aprox. | AD84: Variable | AE84: Bus Takagamine Genkoan-mae | AF84: Parcial; pueden existir escalones, grava o edificios sin elevador | AG84: 35.0519 | AH84: 135.7363 | AI84: https://kyoto.travel/en/destinations/genko-an-temple/ | AJ84: Cambiante | AK84: HIDDEN GEM | AL84: fotografía, cultura, diseño | AM84: 5 | AN84: 5 | AO84: 5 | AP84: 1 | AQ84: Imagen ideal: arquitectura simple convierte el jardín en dos imágenes conceptuales. con luz de mañana, sin multitudes dominando el encuadre. | AR84: Daitoku-ji subtemples (~18 min a pie) | Kinkaku-ji (~21 min a pie) | Ryōan-ji (~35 min en transporte) | AS84: Hidden Gem real | AU84: https://www.google.com/maps/search/?api=1&query=Genk%C5%8D-an%2C%20Kyoto%2C%20Japan | AV84: 2026-09-01 | AW84: CALENDARIO / CONDICIÓN PENDIENTE | AX84: No hay cierre específico confirmado para la ventana, pero horarios o acceso pueden variar. | AY84: Reconfirmar en la web oficial al fijar fechas.
A85: JP-084 | B85: Kioto | C85: Kansai | D85: Kioto | E85: Kyoto | F85: Sakyo | G85: North Kyoto | H85: Shisen-dō | I85: 詩仙堂 | J85: Shisen-dō | K85: 🌸 Jardines y paisajes | L85: villa/templo | M85: A | N85: Jardín íntimo, sonido de shishi-odoshi y baja densidad turística. | O85: Retiro literario del siglo XVII con jardín de azaleas. | P85: La experiencia sonora y doméstica contrasta con los grandes templos. | Q85: Retiro literario del siglo XVII con jardín de azaleas. | R85: 1–1.5 h | S85: Mañana | T85: Mayo y otoño | U85: Bajo | V85: Bajo | W85: 500 | X85: 500 | Y85: =W85*'Configuración'!$B$4 | Z85: =X85*'Configuración'!$B$4 | AA85: No | AB85: — | AC85: 09:00–17:00 | AD85: 23 mayo y cierres; verificar | AE85: Bus Ichijoji-sagarimatsucho | AF85: Parcial; pueden existir escalones, grava o edificios sin elevador | AG85: 35.043 | AH85: 135.8003 | AI85: https://kyoto.travel/en/ | AJ85: Cambiante | AK85: HIDDEN GEM | AL85: pareja, jardines, cultura | AM85: 4 | AN85: 5 | AO85: 5 | AP85: 1 | AQ85: Imagen ideal: la experiencia sonora y doméstica contrasta con los grandes templos. con luz de mañana, sin multitudes dominando el encuadre. | AR85: Ginkaku-ji (~25 min a pie) | Philosopher's Path (~25 min en transporte) | Hōnen-in (~32 min en transporte) | AS85: Hidden Gem real | AU85: https://www.google.com/maps/search/?api=1&query=Shisen-d%C5%8D%2C%20Kyoto%2C%20Japan | AV85: 2026-09-01 | AW85: CALENDARIO / CONDICIÓN PENDIENTE | AX85: No hay cierre específico confirmado para la ventana, pero horarios o acceso pueden variar. | AY85: Reconfirmar en la web oficial al fijar fechas.
A86: JP-085 | B86: Kioto | C86: Kansai | D86: Kioto | E86: Kyoto | F86: Kurama | G86: Kurama–Kibune | H86: Kurama-dera to Kibune hike | I86: 鞍馬寺～貴船 | J86: Kurama-dera to Kibune hike | K86: 🥾 Senderismo/aventura | L86: sendero/templos | M86: A | N86: Une bosque sagrado, montaña y aldeas en una experiencia que no parece ciudad. Clasificación v2: excelente y muy recomendable, pero no justifica por sí sola adaptar la ruta. | O86: Ascenso por Kurama-dera y travesía forestal hacia Kibune. | P86: La secuencia espiritual y física es más rica que visitar ambos pueblos por separado. | Q86: Ascenso por Kurama-dera y travesía forestal hacia Kibune. | R86: 4–6 h | S86: Mañana | T86: Primavera y otoño | U86: Medio | V86: Medio | W86: 500 | X86: 1000 | Y86: =W86*'Configuración'!$B$4 | Z86: =X86*'Configuración'!$B$4 | AA86: No | AB86: — | AC86: Sendero diurno; transporte variable | AD86: Clima, mantenimiento | AE86: Eizan Kurama / Kibuneguchi | AF86: Parcial o baja; terreno irregular y condiciones naturales | AG86: 35.1217 | AH86: 135.7708 | AI86: https://kyoto.travel/en/areas/kurama-kibune/ | AJ86: Cambiante | AK86: NATURE + CULTURE | AL86: senderismo, naturaleza, cultura | AM86: 5 | AN86: 5 | AO86: 4 | AP86: 2 | AQ86: Imagen ideal: la secuencia espiritual y física es más rica que visitar ambos pueblos por separado. con luz de mañana, sin multitudes dominando el encuadre. | AS86: Lugar conocido pero excelente | AU86: https://www.google.com/maps/search/?api=1&query=Kurama-dera%20to%20Kibune%20hike%2C%20Kyoto%2C%20Japan | AV86: 2026-09-01 | AW86: RIESGO ESTACIONAL | AX86: Posibles nieve, hielo, barro, viento, cierres y menos horas de luz. | AY86: Revisar clima, sendero y último transporte 24–48 h antes.
A87: JP-086 | B87: Kioto | C87: Kansai | D87: Kioto | E87: Kyoto | F87: Ohara | G87: Ohara | H87: Sanzen-in | I87: 三千院 | J87: Sanzen-in | K87: ⛩️ Templos y santuarios | L87: templo/jardín | M87: A | N87: El conjunto más convincente de Ohara: musgo, estatuas, interiores y paisaje rural. Clasificación v2: excelente y muy recomendable, pero no justifica por sí sola adaptar la ruta. | O87: Templo Tendai con jardines de musgo y pequeñas figuras warabe jizō. | P87: La distancia filtra turismo y permite una experiencia estacional completa. | Q87: Templo Tendai con jardines de musgo y pequeñas figuras warabe jizō. | R87: 1.5–2.5 h | S87: Mañana | T87: Temporada húmeda y otoño | U87: Medio | V87: Medio | W87: 700 | X87: 700 | Y87: =W87*'Configuración'!$B$4 | Z87: =X87*'Configuración'!$B$4 | AA87: No | AB87: — | AC87: 09:00–17:00 aprox. | AD87: Sin cierre ordinario | AE87: Bus Ohara | AF87: Parcial; pueden existir escalones, grava o edificios sin elevador | AG87: 35.1196 | AH87: 135.8348 | AI87: https://kyoto.travel/en/areas/ohara/ | AJ87: Cambiante | AK87: DAY TRIP / HIDDEN | AL87: pareja, jardines, cultura, naturaleza | AM87: 5 | AN87: 5 | AO87: 5 | AP87: 2 | AQ87: Imagen ideal: la distancia filtra turismo y permite una experiencia estacional completa. con luz de mañana, sin multitudes dominando el encuadre. | AR87: Hōsen-in (~3 min a pie) | AS87: Semi-hidden | AU87: https://www.google.com/maps/search/?api=1&query=Sanzen-in%2C%20Kyoto%2C%20Japan | AV87: 2026-09-01 | AW87: CALENDARIO / CONDICIÓN PENDIENTE | AX87: No hay cierre específico confirmado para la ventana, pero horarios o acceso pueden variar. | AY87: Reconfirmar en la web oficial al fijar fechas.
A88: JP-087 | B88: Kioto | C88: Kansai | D88: Kioto | E88: Kyoto | F88: Ohara | G88: Ohara | H88: Hōsen-in | I88: 宝泉院 | J88: Hōsen-in | K88: 🌸 Jardines y paisajes | L88: templo/jardín | M88: A | N88: Jardín enmarcado desde el tatami con té incluido; íntimo y visual. | O88: Pequeño templo con pino antiguo y jardín visto como cuadro vivo. | P88: La visita se realiza sentada y cambia el ritmo del día. | Q88: Pequeño templo con pino antiguo y jardín visto como cuadro vivo. | R88: 45–75 min | S88: Mañana | T88: Otoño y temporada verde | U88: Bajo | V88: Bajo | W88: 900 | X88: 900 | Y88: =W88*'Configuración'!$B$4 | Z88: =X88*'Configuración'!$B$4 | AA88: No | AB88: — | AC88: 09:00–17:00 aprox. | AD88: Variable | AE88: Bus Ohara + paseo | AF88: Parcial; pueden existir escalones, grava o edificios sin elevador | AG88: 35.121 | AH88: 135.8355 | AI88: https://kyoto.travel/en/areas/ohara/ | AJ88: Cambiante | AK88: HIDDEN GEM | AL88: pareja, jardines, té, fotografía | AM88: 5 | AN88: 5 | AO88: 5 | AP88: 1 | AQ88: Imagen ideal: la visita se realiza sentada y cambia el ritmo del día. con luz de mañana, sin multitudes dominando el encuadre. | AR88: Sanzen-in (~3 min a pie) | AS88: Hidden Gem real | AU88: https://www.google.com/maps/search/?api=1&query=H%C5%8Dsen-in%2C%20Kyoto%2C%20Japan | AV88: 2026-09-01 | AW88: CALENDARIO / CONDICIÓN PENDIENTE | AX88: No hay cierre específico confirmado para la ventana, pero horarios o acceso pueden variar. | AY88: Reconfirmar en la web oficial al fijar fechas.
A89: JP-088 | B89: Kioto | C89: Kansai | D89: Kioto | E89: Kyoto | F89: Takao | G89: Takao | H89: Jingo-ji | I89: 神護寺 | J89: Jingo-ji | K89: ⛩️ Templos y santuarios | L89: templo de montaña | M89: A | N89: Gran paisaje de montaña y escaleras; mejor que muchos templos centrales en otoño. | O89: Templo antiguo sobre el valle Kiyotaki con vistas y kawarake-nage. | P89: El esfuerzo de acceso crea aislamiento real. | Q89: Templo antiguo sobre el valle Kiyotaki con vistas y kawarake-nage. | R89: 2–3 h | S89: Mañana | T89: Otoño | U89: Medio | V89: Bajo | W89: 1000 | X89: 1000 | Y89: =W89*'Configuración'!$B$4 | Z89: =X89*'Configuración'!$B$4 | AA89: No | AB89: — | AC89: 09:00–16:00 aprox. | AD89: Sin cierre ordinario | AE89: Bus Takao + escaleras | AF89: Parcial o baja; terreno irregular y condiciones naturales | AG89: 35.0549 | AH89: 135.6704 | AI89: https://kyoto.travel/en/areas/takao/ | AJ89: Cambiante | AK89: HIDDEN GEM / NATURE | AL89: senderismo, cultura, fotografía | AM89: 5 | AN89: 5 | AO89: 4 | AP89: 1 | AQ89: Imagen ideal: el esfuerzo de acceso crea aislamiento real. con luz de mañana, sin multitudes dominando el encuadre. | AS89: Semi-hidden | AU89: https://www.google.com/maps/search/?api=1&query=Jingo-ji%2C%20Kyoto%2C%20Japan | AV89: 2026-09-01 | AW89: RIESGO ESTACIONAL | AX89: Posibles nieve, hielo, barro, viento, cierres y menos horas de luz. | AY89: Revisar clima, sendero y último transporte 24–48 h antes.
A90: JP-089 | B90: Kioto | C90: Kansai | D90: Kioto | E90: Kyoto | F90: Central | G90: Central Kyoto | H90: Nijō Castle | I90: 二条城 | J90: Nijō Castle | K90: 🏯 Historia y patrimonio | L90: castillo/palacio | M90: S | N90: Interiores, jardines y poder político Tokugawa hacen imprescindible la visita. | O90: Palacio Ninomaru, pisos ruiseñor y fortificaciones del shogunato. | P90: Es un palacio de gobierno auténtico, no una torre reconstruida. | Q90: Palacio Ninomaru, pisos ruiseñor y fortificaciones del shogunato. | R90: 2–3 h | S90: Mañana | T90: Sakura y otoño | U90: Alto | V90: Alto | W90: 800 | X90: 1300 | Y90: =W90*'Configuración'!$B$4 | Z90: =X90*'Configuración'!$B$4 | AA90: Recomendable | AB90: Días en temporada | AC90: 08:45–17:00 aprox. | AD90: Martes en meses específicos; fin de año | AE90: Metro Nijojo-mae | AF90: Parcial; pueden existir escalones, grava o edificios sin elevador | AG90: 35.0142 | AH90: 135.7482 | AI90: https://nijo-jocastle.city.kyoto.lg.jp/?lang=en | AJ90: Cambiante | AK90: MUST SEE | AL90: historia, arquitectura, jardines | AM90: 5 | AN90: 5 | AO90: 5 | AP90: 4 | AQ90: Imagen ideal: es un palacio de gobierno auténtico, no una torre reconstruida. con luz de mañana, sin multitudes dominando el encuadre. | AR90: Kyoto International Manga Museum (~16 min a pie) | Kyoto Imperial Palace (~25 min a pie) | Nishiki Market (~26 min en transporte) | AS90: Popular / turístico | AU90: https://www.google.com/maps/search/?api=1&query=Nij%C5%8D%20Castle%2C%20Kyoto%2C%20Japan | AV90: 2026-09-01 | AW90: ABIERTO; FLORACIÓN NO GARANTIZADA | AX90: En Japón central la floración plena suele ser más tardía; finales de marzo es incierto. | AY90: No basar la visita en sakura hasta el pronóstico 2027.
A91: JP-090 | B91: Kioto | C91: Kansai | D91: Kioto | E91: Kyoto | F91: Central | G91: Central Kyoto | H91: Kyoto Imperial Palace | I91: 京都御所 | J91: Kyoto Imperial Palace | K91: 🏯 Historia y patrimonio | L91: palacio/parque | M91: A | N91: Gran vacío histórico y arquitectura imperial; gratuito y menos saturado. | O91: Antigua residencia imperial dentro del Kyoto Gyoen. | P91: Permite comprender la capital cortesana frente al poder shogunal de Nijo. | Q91: Antigua residencia imperial dentro del Kyoto Gyoen. | R91: 1.5–2.5 h | S91: Mañana | T91: Primavera y otoño | U91: Medio | V91: Medio | W91: 0 | X91: 0 | Y91: =W91*'Configuración'!$B$4 | Z91: =X91*'Configuración'!$B$4 | AA91: No | AB91: — | AC91: 09:00–16:00/17:00 según temporada | AD91: Lunes y actos; verificar | AE91: Imadegawa / Marutamachi | AF91: Buena en áreas principales; confirmar detalles con el recinto | AG91: 35.0254 | AH91: 135.7621 | AI91: https://sankan.kunaicho.go.jp/english/guide/kyoto.html | AJ91: Cambiante | AK91: HISTORY | AL91: historia, arquitectura, jardines | AM91: 4 | AN91: 4 | AO91: 5 | AP91: 2 | AQ91: Imagen ideal: permite comprender la capital cortesana frente al poder shogunal de nijo. con luz de mañana, sin multitudes dominando el encuadre. | AR91: Demachi Masugata Shopping Arcade (~12 min a pie) | Kyoto International Manga Museum (~24 min a pie) | Nijō Castle (~25 min a pie) | AS91: Lugar conocido pero excelente | AU91: https://www.google.com/maps/search/?api=1&query=Kyoto%20Imperial%20Palace%2C%20Kyoto%2C%20Japan | AV91: 2026-09-01 | AW91: CALENDARIO / CONDICIÓN PENDIENTE | AX91: No hay cierre específico confirmado para la ventana, pero horarios o acceso pueden variar. | AY91: Reconfirmar en la web oficial al fijar fechas.
A92: JP-091 | B92: Kioto | C92: Kansai | D92: Kioto | E92: Kyoto | F92: Central | G92: Central Kyoto | H92: Nishiki Market | I92: 錦市場 | J92: Nishiki Market | K92: 🍜 Gastronomía | L92: mercado | M92: C | N92: Histórico, pero muy angosto, saturado y orientado cada vez más a degustación turística. | O92: Galería comercial de alimentos y utensilios en el centro. | P92: Vale por especialistas concretos, no por recorrerlo sin objetivo. | Q92: Galería comercial de alimentos y utensilios en el centro. | R92: 1–1.5 h | S92: Mañana | T92: Días laborables | U92: Extremo | V92: Extremo | W92: 500 | X92: 4000 | Y92: =W92*'Configuración'!$B$4 | Z92: =X92*'Configuración'!$B$4 | AA92: No | AB92: — | AC92: Aprox. 10:00–18:00 | AD92: Miércoles variable | AE92: Karasuma / Kyoto-Kawaramachi | AF92: Buena en áreas principales; confirmar detalles con el recinto | AG92: 35.005 | AH92: 135.7649 | AI92: https://www.kyoto-nishiki.or.jp/en/ | AJ92: Cambiante | AK92: FOOD / TOURISTY | AL92: comida, compras | AM92: 3 | AN92: 3 | AO92: 2 | AP92: 5 | AQ92: Imagen ideal: vale por especialistas concretos, no por recorrerlo sin objetivo. con luz de mañana, sin multitudes dominando el encuadre. | AR92: Kyoto International Manga Museum (~11 min a pie) | Gion Shirakawa (~11 min a pie) | Kennin-ji (~13 min a pie) | AS92: Popular / turístico | AU92: https://www.google.com/maps/search/?api=1&query=Nishiki%20Market%2C%20Kyoto%2C%20Japan | AV92: 2026-09-01 | AW92: CALENDARIO / CONDICIÓN PENDIENTE | AX92: No hay cierre específico confirmado para la ventana, pero horarios o acceso pueden variar. | AY92: Reconfirmar en la web oficial al fijar fechas.
A93: JP-092 | B93: Kioto | C93: Kansai | D93: Kioto | E93: Kyoto | F93: Central | G93: Central Kyoto | H93: Kyoto International Manga Museum | I93: 京都国際マンガミュージアム | J93: Kyoto International Manga Museum | K93: 👾 Anime/manga | L93: museo/biblioteca | M93: A | N93: Gran archivo legible y relajado; más cultural que comercial. | O93: Antigua escuela convertida en museo con cientos de miles de mangas. | P93: Se puede leer libremente y entender la historia del medio. | Q93: Antigua escuela convertida en museo con cientos de miles de mangas. | R93: 2–4 h | S93: Tarde | T93: Todo el año | U93: Medio | V93: Medio | W93: 1200 | X93: 1200 | Y93: =W93*'Configuración'!$B$4 | Z93: =X93*'Configuración'!$B$4 | AA93: No | AB93: — | AC93: 10:30–17:30 aprox. | AD93: Miércoles; verificar | AE93: Karasuma Oike | AF93: Buena en áreas principales; confirmar detalles con el recinto | AG93: 35.0102 | AH93: 135.7595 | AI93: https://kyotomm.jp/en/ | AJ93: Cambiante | AK93: MANGA | AL93: anime, manga, cultura, lluvia | AM93: 3 | AN93: 5 | AO93: 5 | AP93: 2 | AQ93: Imagen ideal: se puede leer libremente y entender la historia del medio. con luz de tarde, sin multitudes dominando el encuadre. | AR93: Nishiki Market (~11 min a pie) | Nijō Castle (~16 min a pie) | Gion Shirakawa (~19 min a pie) | AS93: Lugar conocido pero excelente | AU93: https://www.google.com/maps/search/?api=1&query=Kyoto%20International%20Manga%20Museum%2C%20Kyoto%2C%20Japan | AV93: 2026-09-01 | AW93: CALENDARIO / CONDICIÓN PENDIENTE | AX93: No hay cierre específico confirmado para la ventana, pero horarios o acceso pueden variar. | AY93: Reconfirmar en la web oficial al fijar fechas.
A94: JP-093 | B94: Kioto | C94: Kansai | D94: Kioto | E94: Kyoto | F94: Kyoto Station | G94: Station–South | H94: Kyoto Railway Museum | I94: 京都鉄道博物館 | J94: Kyoto Railway Museum | K94: 🚂 Experiencias especiales | L94: museo ferroviario | M94: A | N94: Uno de los mejores museos ferroviarios de Japón, con material real y demostraciones. Clasificación v2: excelente y muy recomendable, pero no justifica por sí sola adaptar la ruta. | O94: Locomotoras, trenes bala, rotonda histórica y simuladores. | P94: La escala industrial y variedad hacen que funcione también sin ser fan. | Q94: Locomotoras, trenes bala, rotonda histórica y simuladores. | R94: 3–5 h | S94: Mañana | T94: Todo el año | U94: Alto | V94: Medio | W94: 1500 | X94: 1500 | Y94: =W94*'Configuración'!$B$4 | Z94: =X94*'Configuración'!$B$4 | AA94: Recomendable | AB94: Días en fin de semana | AC94: 10:00–17:00 aprox. | AD94: Miércoles; verificar | AE94: JR Umekoji-Kyotonishi | AF94: Buena en áreas principales; confirmar detalles con el recinto | AG94: 34.9876 | AH94: 135.743 | AI94: https://www.kyotorailwaymuseum.jp/en/ | AJ94: Cambiante | AK94: TRAIN | AL94: trenes, tecnología, familia, historia | AM94: 5 | AN94: 5 | AO94: 5 | AP94: 3 | AQ94: Imagen ideal: la escala industrial y variedad hacen que funcione también sin ser fan. con luz de mañana, sin multitudes dominando el encuadre. | AR94: teamLab Biovortex Kyoto (~35 min en transporte) | Sanjūsangen-dō (~37 min en transporte) | Kyoto National Museum (~38 min en transporte) | AS94: Lugar conocido pero excelente | AU94: https://www.google.com/maps/search/?api=1&query=Kyoto%20Railway%20Museum%2C%20Kyoto%2C%20Japan | AV94: 2026-09-01 | AW94: CALENDARIO / CONDICIÓN PENDIENTE | AX94: No hay cierre específico confirmado para la ventana, pero horarios o acceso pueden variar. | AY94: Reconfirmar en la web oficial al fijar fechas.
A95: JP-094 | B95: Kioto | C95: Kansai | D95: Kioto | E95: Kyoto | F95: Higashiyama | G95: Station–South | H95: Kyoto National Museum | I95: 京都国立博物館 | J95: Kyoto National Museum | K95: 🏛️ Museos | L95: museo nacional | M95: A | N95: Colecciones y exposiciones esenciales para profundizar en arte japonés. | O95: Museo nacional de arte, arqueología y tesoros de templos. | P95: Da contexto material a lo visto en santuarios y palacios. | Q95: Museo nacional de arte, arqueología y tesoros de templos. | R95: 2–4 h | S95: Tarde | T95: Todo el año | U95: Medio | V95: Medio | W95: 700 | X95: 2000 | Y95: =W95*'Configuración'!$B$4 | Z95: =X95*'Configuración'!$B$4 | AA95: Recomendable | AB95: Según exposición | AC95: 09:30–17:00 aprox. | AD95: Lunes; verificar | AE95: Bus Hakubutsukan Sanjusangendo-mae | AF95: Buena en áreas principales; confirmar detalles con el recinto | AG95: 34.99 | AH95: 135.773 | AI95: https://www.kyohaku.go.jp/eng/ | AJ95: Cambiante | AK95: ART / HISTORY | AL95: arte, historia, lluvia | AM95: 4 | AN95: 5 | AO95: 5 | AP95: 2 | AQ95: Imagen ideal: da contexto material a lo visto en santuarios y palacios. con luz de tarde, sin multitudes dominando el encuadre. | AR95: Sanjūsangen-dō (~4 min a pie) | Gion Corner (~16 min a pie) | Kennin-ji (~17 min a pie) | AS95: Lugar conocido pero excelente | AU95: https://www.google.com/maps/search/?api=1&query=Kyoto%20National%20Museum%2C%20Kyoto%2C%20Japan | AV95: 2026-09-01 | AW95: CIERRE PARCIAL DESDE 24 MAR | AX95: Galerías previstas abiertas 2 ene–22 mar 2027; 24 mar–18 abr solo jardines y exteriores. | AY95: Evitar después del 22 de marzo si interesan las colecciones interiores.
A96: JP-095 | B96: Kioto | C96: Kansai | D96: Kioto | E96: Kyoto | F96: Higashikujo | G96: Station–South | H96: teamLab Biovortex Kyoto | I96: チームラボ バイオヴォルテックス 京都 | J96: teamLab Biovortex Kyoto | K96: 🎨 Arte | L96: museo inmersivo | M96: A | N96: Es la mayor instalación permanente de teamLab en Japón y una experiencia física extensa. Clasificación v2: excelente y muy recomendable, pero no justifica por sí sola adaptar la ruta. | O96: Más de 50 obras inmersivas en unos 10,000 m². | P96: Mayor escala y componente atlético que las sedes de Tokio. | Q96: Más de 50 obras inmersivas en unos 10,000 m². | R96: 3–4.5 h | S96: Mañana | T96: Todo el año | U96: Extremo | V96: Alto | W96: 3400 | X96: 5000 | Y96: =W96*'Configuración'!$B$4 | Z96: =X96*'Configuración'!$B$4 | AA96: Sí | AB96: 2–4 semanas | AC96: 09:00–21:00 aprox.; verificar fecha | AD96: Variable | AE96: Kyoto Station Hachijo East + 10 min | AF96: Buena en áreas principales; confirmar detalles con el recinto | AG96: 34.9793 | AH96: 135.7686 | AI96: https://www.teamlab.art/e/kyoto/ | AJ96: Cambiante | AK96: MUST SEE / ART | AL96: pareja, arte, tecnología, fotografía | AM96: 5 | AN96: 5 | AO96: 4 | AP96: 4 | AQ96: Imagen ideal: mayor escala y componente atlético que las sedes de tokio. con luz de mañana, sin multitudes dominando el encuadre. | AR96: Tōfuku-ji (~8 min a pie) | Sanjūsangen-dō (~14 min a pie) | Kyoto National Museum (~18 min a pie) | AS96: Popular / turístico | AU96: https://www.google.com/maps/search/?api=1&query=teamLab%20Biovortex%20Kyoto%2C%20Kyoto%2C%20Japan | AV96: 2026-09-01 | AW96: CALENDARIO / CONDICIÓN PENDIENTE | AX96: No hay cierre específico confirmado para la ventana, pero horarios o acceso pueden variar. | AY96: Reconfirmar en la web oficial al fijar fechas.
A97: JP-096 | B97: Kioto | C97: Kansai | D97: Kioto | E97: Kyoto | F97: Higashiyama | G97: Station–South | H97: Sanjūsangen-dō | I97: 三十三間堂 | J97: Sanjūsangen-dō | K97: ⛩️ Templos y santuarios | L97: templo | M97: S | N97: Las 1,001 estatuas de Kannon crean uno de los interiores más impactantes de Japón. | O97: Salón de 120 m con filas de esculturas budistas. | P97: El impacto es acumulativo y no depende de fotografía —que está prohibida dentro. | Q97: Salón de 120 m con filas de esculturas budistas. | R97: 1–1.5 h | S97: Mañana | T97: Todo el año | U97: Alto | V97: Alto | W97: 600 | X97: 600 | Y97: =W97*'Configuración'!$B$4 | Z97: =X97*'Configuración'!$B$4 | AA97: No | AB97: — | AC97: 08:30–17:00 según temporada | AD97: Sin cierre ordinario | AE97: Bus Hakubutsukan Sanjusangendo-mae | AF97: Parcial; pueden existir escalones, grava o edificios sin elevador | AG97: 34.9879 | AH97: 135.7717 | AI97: https://www.sanjusangendo.jp/ | AJ97: Cambiante | AK97: MUST SEE | AL97: arte, cultura, historia | AM97: 4 | AN97: 5 | AO97: 5 | AP97: 4 | AQ97: Imagen ideal: el impacto es acumulativo y no depende de fotografía —que está prohibida dentro. con luz de mañana, sin multitudes dominando el encuadre. | AR97: Kyoto National Museum (~4 min a pie) | teamLab Biovortex Kyoto (~14 min a pie) | Tōfuku-ji (~18 min a pie) | AS97: Popular / turístico | AU97: https://www.google.com/maps/search/?api=1&query=Sanj%C5%ABsangen-d%C5%8D%2C%20Kyoto%2C%20Japan | AV97: 2026-09-01 | AW97: CALENDARIO / CONDICIÓN PENDIENTE | AX97: No hay cierre específico confirmado para la ventana, pero horarios o acceso pueden variar. | AY97: Reconfirmar en la web oficial al fijar fechas.
A98: JP-097 | B98: Kioto | C98: Kansai | D98: Kioto | E98: Uji | F98: Ogura | G98: Uji | H98: Nintendo Museum | I98: ニンテンドーミュージアム | J98: Nintendo Museum | K98: 🎮 Videojuegos | L98: museo/experiencia | M98: S | N98: La colección corporativa y juegos interactivos justifican el desvío para cualquier fan de Nintendo. | O98: Museo en una antigua planta de cartas y consolas de Nintendo. | P98: Une historia industrial, diseño de producto y juego físico. | Q98: Museo en una antigua planta de cartas y consolas de Nintendo. | R98: 3–4 h | S98: Mañana | T98: Todo el año | U98: Alto | V98: Alto | W98: 3300 | X98: 3300 | Y98: =W98*'Configuración'!$B$4 | Z98: =X98*'Configuración'!$B$4 | AA98: Sí | AB98: Lotería 3 meses antes; revisar liberaciones | AC98: Horario asignado | AD98: Martes y calendario | AE98: Kintetsu Ogura, 5–10 min | AF98: Buena en áreas principales; confirmar detalles con el recinto | AG98: 34.8899 | AH98: 135.7866 | AI98: https://museum.nintendo.com/en/index.html | AJ98: Cambiante | AK98: MUST SEE / GAMING | AL98: videojuegos, diseño, historia | AM98: 5 | AN98: 5 | AO98: 4 | AP98: 4 | AQ98: Imagen ideal: une historia industrial, diseño de producto y juego físico. con luz de mañana, sin multitudes dominando el encuadre. | AR98: Uji tea experience (~25 min a pie) | Byōdō-in (~27 min en transporte) | AS98: Popular / turístico | AU98: https://www.google.com/maps/search/?api=1&query=Nintendo%20Museum%2C%20Uji%2C%20Japan | AV98: 2026-09-01 | AW98: VENTA FUTURA / SORTEO | AX98: La solicitud oficial se realiza tres meses antes. | AY98: Si la regla sigue: noviembre de 2026 para febrero; diciembre para marzo.
A99: JP-098 | B99: Kioto | C99: Kansai | D99: Kioto | E99: Uji | F99: Uji | G99: Uji | H99: Byōdō-in | I99: 平等院 | J99: Byōdō-in | K99: 🏯 Historia y patrimonio | L99: templo/museo | M99: A | N99: La arquitectura del Salón Fénix y su reflejo justifican Uji incluso sin interés por el té. Clasificación v2: excelente y muy recomendable, pero no justifica por sí sola adaptar la ruta. | O99: Templo Heian representado en la moneda de 10 yenes. | P99: Conserva una imagen casi arquetípica del paraíso budista. | Q99: Templo Heian representado en la moneda de 10 yenes. | R99: 1.5–2.5 h | S99: Mañana | T99: Glicinas en primavera; otoño | U99: Alto | V99: Alto | W99: 700 | X99: 1000 | Y99: =W99*'Configuración'!$B$4 | Z99: =X99*'Configuración'!$B$4 | AA99: No | AB99: — | AC99: 08:30–17:30 aprox. | AD99: Sin cierre ordinario | AE99: JR/Keihan Uji | AF99: Parcial; pueden existir escalones, grava o edificios sin elevador | AG99: 34.8893 | AH99: 135.8077 | AI99: https://www.byodoin.or.jp/en/ | AJ99: Cambiante | AK99: MUST SEE | AL99: historia, fotografía, jardines | AM99: 5 | AN99: 5 | AO99: 5 | AP99: 4 | AQ99: Imagen ideal: conserva una imagen casi arquetípica del paraíso budista. con luz de mañana, sin multitudes dominando el encuadre. | AR99: Uji tea experience (~3 min a pie) | Nintendo Museum (~27 min en transporte) | AS99: Popular / turístico | AU99: https://www.google.com/maps/search/?api=1&query=By%C5%8Dd%C5%8D-in%2C%20Uji%2C%20Japan | AV99: 2026-09-01 | AW99: CALENDARIO / CONDICIÓN PENDIENTE | AX99: No hay cierre específico confirmado para la ventana, pero horarios o acceso pueden variar. | AY99: Reconfirmar en la web oficial al fijar fechas.
A100: JP-099 | B100: Kioto | C100: Kansai | D100: Kioto | E100: Uji | F100: Uji | G100: Uji | H100: Uji tea experience | I100: 宇治茶体験 | J100: Uji tea experience | K100: 🍵 Cultura tradicional | L100: experiencia gastronómica | M100: A | N100: Prueba el matcha en su contexto productivo y evita reducir Uji a postres virales. | O100: Catas, molienda de matcha y casas históricas de té. | P100: La calidad depende del productor y la explicación, no solo de la estética. | Q100: Catas, molienda de matcha y casas históricas de té. | R100: 1–2 h | S100: Tarde | T100: Todo el año; cosecha en primavera | U100: Medio | V100: Medio | W100: 1000 | X100: 5000 | Y100: =W100*'Configuración'!$B$4 | Z100: =X100*'Configuración'!$B$4 | AA100: Recomendable | AB100: Días/semanas para taller | AC100: Según productor | AD100: Según productor | AE100: JR/Keihan Uji | AF100: Buena en áreas principales; confirmar detalles con el recinto | AG100: 34.8908 | AH100: 135.806 | AI100: https://www.kyototourism.org/en/areas/uji/ | AJ100: Cambiante | AK100: FOOD / CULTURE | AL100: pareja, comida, cultura | AM100: 4 | AN100: 5 | AO100: 5 | AP100: 2 | AQ100: Imagen ideal: la calidad depende del productor y la explicación, no solo de la estética. con luz de tarde, sin multitudes dominando el encuadre. | AR100: Byōdō-in (~3 min a pie) | Nintendo Museum (~25 min a pie) | AS100: Lugar conocido pero excelente | AU100: https://www.google.com/maps/search/?api=1&query=Uji%20tea%20experience%2C%20Uji%2C%20Japan | AV100: 2026-09-01 | AW100: CALENDARIO / CONDICIÓN PENDIENTE | AX100: No hay cierre específico confirmado para la ventana, pero horarios o acceso pueden variar. | AY100: Reconfirmar en la web oficial al fijar fechas.
A101: JP-100 | B101: Kioto | C101: Kansai | D101: Kioto | E101: Kyoto | F101: Uzumasa | G101: Uzumasa | H101: Uzumasa Kyoto Village / Toei Kyoto Studio Park | I101: 太秦映画村 | J101: Uzumasa Kyoto Village | K101: 🎭 Cultura tradicional | L101: parque de cine | M101: B | N101: La renovación 2026 ofrece una forma lúdica de entrar a escenografías de época. Clasificación v2: recomendable si encaja; su valor depende más de interés, saturación o logística. | O101: Sets de cine jidaigeki, espectáculos y nueva zona inmersiva para adultos. | P101: Es patrimonio audiovisual vivo, no un pueblo histórico auténtico. | Q101: Sets de cine jidaigeki, espectáculos y nueva zona inmersiva para adultos. | R101: Medio día | S101: Tarde | T101: Todo el año | U101: Alto | V101: Alto | W101: 2800 | X101: 3800 | Y101: =W101*'Configuración'!$B$4 | Z101: =X101*'Configuración'!$B$4 | AA101: Recomendable | AB101: Días/semanas | AC101: Horario variable | AD101: Cierres programados | AE101: JR Uzumasa / Randen Uzumasa-Koryuji | AF101: Buena en áreas principales; confirmar detalles con el recinto | AG101: 35.0164 | AH101: 135.7083 | AI101: https://global.toei-eigamura.com/ | AJ101: Verificado | AK101: ENTERTAINMENT | AL101: cine, cultura, fotografía | AM101: 5 | AN101: 4 | AO101: 3 | AP101: 4 | AQ101: Imagen ideal: es patrimonio audiovisual vivo, no un pueblo histórico auténtico. con luz de tarde, sin multitudes dominando el encuadre. | AR101: Ryōan-ji (~31 min en transporte) | AS101: Popular / turístico | AU101: https://www.google.com/maps/search/?api=1&query=Uzumasa%20Kyoto%20Village%20%2F%20Toei%20Kyoto%20Studio%20Park%2C%20Kyoto%2C%20Japan | AV101: 2026-09-01 | AW101: CALENDARIO / CONDICIÓN PENDIENTE | AX101: No hay cierre específico confirmado para la ventana, pero horarios o acceso pueden variar. | AY101: Reconfirmar en la web oficial al fijar fechas.
A102: JP-101 | B102: Kioto | C102: Kansai | D102: Kioto | E102: Kyoto | F102: Gion | G102: Kiyomizu–Gion | H102: Gion Corner | I102: ギオンコーナー | J102: Gion Corner | K102: 🎭 Cultura tradicional | L102: espectáculo | M102: A | N102: Introducción eficiente a siete artes tradicionales; condensada y algo turística. | O102: Programa escénico con danza kyomai, teatro, música, té y arreglos florales. | P102: Permite comparar artes en una sola sesión, no sustituye una función completa. | Q102: Programa escénico con danza kyomai, teatro, música, té y arreglos florales. | R102: 1–1.5 h | S102: Noche | T102: Temporada de funciones | U102: Alto | V102: Alto | W102: 5500 | X102: 6500 | Y102: =W102*'Configuración'!$B$4 | Z102: =X102*'Configuración'!$B$4 | AA102: Sí | AB102: Días/semanas | AC102: Funciones programadas | AD102: Días sin función | AE102: Gion-Shijo | AF102: Buena en áreas principales; confirmar detalles con el recinto | AG102: 35 | AH102: 135.7755 | AI102: https://www.kyoto-gioncorner.com/global/en.html | AJ102: Cambiante | AK102: CULTURE / NIGHT | AL102: pareja, cultura, teatro | AM102: 4 | AN102: 4 | AO102: 4 | AP102: 4 | AQ102: Imagen ideal: permite comparar artes en una sola sesión, no sustituye una función completa. con luz de noche, sin multitudes dominando el encuadre. | AR102: Kennin-ji (~3 min a pie) | Yasaka Kōshin-dō (~7 min a pie) | Kōdai-ji (~7 min a pie) | AS102: Popular / turístico | AU102: https://www.google.com/maps/search/?api=1&query=Gion%20Corner%2C%20Kyoto%2C%20Japan | AV102: 2026-09-01 | AW102: CALENDARIO / CONDICIÓN PENDIENTE | AX102: No hay cierre específico confirmado para la ventana, pero horarios o acceso pueden variar. | AY102: Reconfirmar en la web oficial al fijar fechas.
A103: JP-102 | B103: Kioto | C103: Kansai | D103: Kioto | E103: Kyoto | F103: Sakyo | G103: Demachiyanagi | H103: Demachi Masugata Shopping Arcade | I103: 出町桝形商店街 | J103: Demachi Masugata Shopping Arcade | K103: 🍜 Gastronomía | L103: mercado local | M103: A | N103: Mercado vecinal real y excelente alternativa a Nishiki para observar vida cotidiana. | O103: Galería cubierta de alimentos, tiendas familiares y cultura local. | P103: No está escenificada para el turismo y mantiene precios cotidianos. | Q103: Galería cubierta de alimentos, tiendas familiares y cultura local. | R103: 45–90 min | S103: Mañana | T103: Días laborables/sábado | U103: Bajo | V103: Bajo | W103: 0 | X103: 2000 | Y103: =W103*'Configuración'!$B$4 | Z103: =X103*'Configuración'!$B$4 | AA103: No | AB103: — | AC103: Según comercio, diurno | AD103: Muchos domingos | AE103: Demachiyanagi | AF103: Buena en áreas principales; confirmar detalles con el recinto | AG103: 35.0302 | AH103: 135.7694 | AI103: https://kyoto.travel/en/ | AJ103: Cambiante | AK103: HIDDEN GEM / FOOD | AL103: comida, cultura local, fotografía | AM103: 3 | AN103: 5 | AO103: 5 | AP103: 1 | AQ103: Imagen ideal: no está escenificada para el turismo y mantiene precios cotidianos. con luz de mañana, sin multitudes dominando el encuadre. | AR103: Kyoto Imperial Palace (~12 min a pie) | Kyoto International Manga Museum (~34 min en transporte) | AS103: Alternativa menos saturada | AT103: Nishiki Market | AU103: https://www.google.com/maps/search/?api=1&query=Demachi%20Masugata%20Shopping%20Arcade%2C%20Kyoto%2C%20Japan | AV103: 2026-09-01 | AW103: CALENDARIO / CONDICIÓN PENDIENTE | AX103: No hay cierre específico confirmado para la ventana, pero horarios o acceso pueden variar. | AY103: Reconfirmar en la web oficial al fijar fechas.
A104: JP-103 | B104: Osaka | C104: Kansai | D104: Osaka | E104: Osaka | F104: Namba | G104: Namba–Dotonbori | H104: Dotonbori | I104: 道頓堀 | J104: Dotonbori | K104: 🌃 Nocturno | L104: barrio/canal | M104: A | N104: Es el gran icono nocturno de Osaka y concentra su energía popular. | O104: Canal, neón, fachadas mecánicas y restaurantes de Minami. | P104: La densidad visual y gastronómica no se replica en otra ciudad japonesa. | Q104: Canal, neón, fachadas mecánicas y restaurantes de Minami. | R104: 1.5–3 h | S104: Noche | T104: Todo el año | U104: Extremo | V104: Extremo | W104: 0 | X104: 0 | Y104: =W104*'Configuración'!$B$4 | Z104: =X104*'Configuración'!$B$4 | AA104: No | AB104: — | AC104: Espacio público 24 h | AD104: Sin cierre | AE104: Namba / Osaka-Namba / Nippombashi | AF104: Buena en áreas principales; confirmar detalles con el recinto | AG104: 34.6687 | AH104: 135.5013 | AI104: https://osaka-info.jp/en/ | AJ104: Cambiante | AK104: MUST SEE / NIGHT | AL104: pareja, comida, fotografía, noche | AM104: 5 | AN104: 4 | AO104: 4 | AP104: 5 | AQ104: Imagen ideal: la densidad visual y gastronómica no se replica en otra ciudad japonesa. con luz de noche, sin multitudes dominando el encuadre. | AR104: Glico Running Man sign (~3 min a pie) | Hozenji Yokocho (~3 min a pie) | Kuromon Ichiba Market (~8 min a pie) | AS104: Popular / turístico | AU104: https://www.google.com/maps/search/?api=1&query=Dotonbori%2C%20Osaka%2C%20Japan | AV104: 2026-09-01 | AW104: CALENDARIO / CONDICIÓN PENDIENTE | AX104: No hay cierre específico confirmado para la ventana, pero horarios o acceso pueden variar. | AY104: Reconfirmar en la web oficial al fijar fechas.
...

Sheet Clusters
A1: Cluster ID | B1: Hub | C1: Cluster | D1: N.º fichas | E1: S/A | F1: Lat centro | G1: Lon centro | H1: IDs | I1: Descripción UI
A2: CL-01 | B2: Tokio | C2: Shibuya | D2: 3 | E2: 3 | F2: 35.66 | G2: 139.7005 | H2: JP-001, JP-002, JP-008 | I2: Zona natural con 3 fichas; 3 clasificadas S/A.
A3: CL-02 | B3: Tokio | C3: Harajuku–Meiji | D3: 4 | E3: 3 | F3: 35.67097 | G3: 139.70412 | H3: JP-003, JP-004, JP-005, JP-007 | I3: Zona natural con 4 fichas; 3 clasificadas S/A.
A4: CL-03 | B4: Tokio | C4: Aoyama–Omotesando | D4: 1 | E4: 1 | F4: 35.6622 | G4: 139.7171 | H4: JP-006 | I4: Zona natural con 1 fichas; 1 clasificadas S/A.
A5: CL-04 | B5: Tokio | C5: Daikanyama–Ebisu | D5: 1 | E5: 1 | F5: 35.6488 | G5: 139.6997 | H5: JP-009 | I5: Zona natural con 1 fichas; 1 clasificadas S/A.
A6: CL-05 | B6: Tokio | C6: Shinjuku | D6: 5 | E6: 3 | F6: 35.69124 | G6: 139.70188 | H6: JP-010, JP-011, JP-012, JP-013, JP-014 | I6: Zona natural con 5 fichas; 3 clasificadas S/A.
A7: CL-06 | B7: Tokio | C7: Kagurazaka | D7: 1 | E7: 1 | F7: 35.7016 | G7: 139.7403 | H7: JP-015 | I7: Zona natural con 1 fichas; 1 clasificadas S/A.
A8: CL-07 | B8: Tokio | C8: Asakusa | D8: 3 | E8: 3 | F8: 35.71373 | G8: 139.79393 | H8: JP-016, JP-017, JP-018 | I8: Zona natural con 3 fichas; 3 clasificadas S/A.
A9: CL-08 | B9: Tokio | C9: Skytree–Sumida | D9: 2 | E9: 2 | F9: 35.7032 | G9: 139.8056 | H9: JP-019, JP-020 | I9: Zona natural con 2 fichas; 2 clasificadas S/A.
A10: CL-09 | B10: Tokio | C10: Ueno–Yanaka | D10: 4 | E10: 3 | F10: 35.71917 | G10: 139.76975 | H10: JP-021, JP-022, JP-023, JP-024 | I10: Zona natural con 4 fichas; 3 clasificadas S/A.
A11: CL-10 | B11: Tokio | C11: Akihabara–Kanda | D11: 3 | E11: 3 | F11: 35.7003 | G11: 139.7708 | H11: JP-025, JP-026, JP-027 | I11: Zona natural con 3 fichas; 3 clasificadas S/A.
A12: CL-11 | B12: Tokio | C12: Jimbocho | D12: 1 | E12: 1 | F12: 35.6956 | G12: 139.7576 | H12: JP-028 | I12: Zona natural con 1 fichas; 1 clasificadas S/A.
A13: CL-12 | B13: Tokio | C13: Marunouchi–Ginza | D13: 4 | E13: 3 | F13: 35.6729 | G13: 139.76353 | H13: JP-029, JP-030, JP-031, JP-032 | I13: Zona natural con 4 fichas; 3 clasificadas S/A.
... A89: CL-88 | B89: Fukuoka | C89: Yanagawa | D89: 1 | E89: 0 | F89: 33.163 | G89: 130.4056 | H89: JP-214 | I89: Paseo fluvial desde Fukuoka; operación variable.

Sheet Cercanos
A1: Desde ID | B1: Hacia ID | C1: Desde | D1: Hacia | E1: Distancia km | F1: Min aprox. | G1: Modo | H1: Relación | I1: Nota
A2: JP-001 | B2: JP-002 | C2: Shibuya Crossing | D2: SHIBUYA SKY | E2: 0.19 | F2: 3 | G2: A pie | H2: Mismo cluster | I2: Estimación geográfica; validar ruta real
A3: JP-001 | B3: JP-008 | C3: Shibuya Crossing | D3: Shibuya PARCO + Nintendo TOKYO | E3: 0.32 | F3: 4 | G3: A pie | H3: Mismo cluster | I3: Estimación geográfica; validar ruta real
A4: JP-001 | B4: JP-005 | C4: Shibuya Crossing | D4: Cat Street | E4: 0.98 | F4: 14 | G4: A pie | H4: Cercano | I4: Estimación geográfica; validar ruta real
A5: JP-002 | B5: JP-001 | C5: SHIBUYA SKY | D5: Shibuya Crossing | E5: 0.19 | F5: 3 | G5: A pie | H5: Mismo cluster | I5: Estimación geográfica; validar ruta real
A6: JP-002 | B6: JP-008 | C6: SHIBUYA SKY | D6: Shibuya PARCO + Nintendo TOKYO | E6: 0.5 | F6: 7 | G6: A pie | H6: Mismo cluster | I6: Estimación geográfica; validar ruta real
A7: JP-002 | B7: JP-005 | C7: SHIBUYA SKY | D7: Cat Street | E7: 0.95 | F7: 13 | G7: A pie | H7: Cercano | I7: Estimación geográfica; validar ruta real
A8: JP-003 | B8: JP-004 | C8: Meiji Jingu | D8: Takeshita Street | E8: 0.64 | F8: 9 | G8: A pie | H8: Mismo cluster | I8: Estimación geográfica; validar ruta real
A9: JP-003 | B9: JP-007 | C9: Meiji Jingu | D9: Ota Memorial Museum of Art | E9: 0.83 | F9: 12 | G9: A pie | H9: Mismo cluster | I9: Estimación geográfica; validar ruta real
A10: JP-003 | B10: JP-010 | C10: Meiji Jingu | D10: Shinjuku Gyoen National Garden | E10: 1.38 | F10: 19 | G10: A pie | H10: Cercano | I10: Estimación geográfica; validar ruta real
A11: JP-004 | B11: JP-007 | C11: Takeshita Street | D11: Ota Memorial Museum of Art | E11: 0.23 | F11: 3 | G11: A pie | H11: Mismo cluster | I11: Estimación geográfica; validar ruta real
A12: JP-004 | B12: JP-003 | C12: Takeshita Street | D12: Meiji Jingu | E12: 0.64 | F12: 9 | G12: A pie | H12: Mismo cluster | I12: Estimación geográfica; validar ruta real
A13: JP-004 | B13: JP-005 | C13: Takeshita Street | D13: Cat Street | E13: 0.87 | F13: 12 | G13: A pie | H13: Mismo cluster | I13: Estimación geográfica; validar ruta real
... A404: JP-204 | B404: JP-203 | C404: Tokyo DisneySea | D404: Tokyo Disneyland | E404: 0.8 | F404: 10 | G404: Disney Resort Line | H404: Alternativas/complementos | I404: No asumir que ambos son equivalentes.

Sheet Excursiones
A1: Base | B1: Excursión | C1: Prefectura | D1: Traslado real aprox. | E1: Interés | F1: Dificultad | G1: ¿Day trip? | H1: ¿Dormir? | I1: Compite con | J1: Grado | K1: Dictamen | L1: Fuente
A2: Tokio | B2: Kamakura + Enoshima | C2: Kanagawa | D2: 50–80 min | E2: Costa, templos, Enoden y miradores | F2: Fácil | G2: Sí | H2: Opcional | I2: Compite parcialmente con Nara por patrimonio; gana en costa | J2: A | K2: Combinar ambas solo con día completo | L2: https://trip.pref.kanagawa.jp/
A3: Tokio | B3: Yokohama | C3: Kanagawa | D3: 25–45 min | E3: Puerto, arquitectura, Chinatown, noche | F3: Fácil | G3: Sí | H3: No | I3: Compite con Odaiba por waterfront; Yokohama es ciudad real | J3: A | K3: Gran excursión de tarde-noche | L3: https://www.yokohamajapan.com/
A4: Tokio | B4: Hakone | C4: Kanagawa | D4: 90–120 min | E4: Onsen, arte, lago y Fuji | F4: Media | G4: Sí, largo | H4: Sí | I4: Compite con Kawaguchiko: Hakone gana en onsen/arte; pierde en Fuji | J4: S | K4: Dormir mejora mucho la experiencia | L4: https://www.hakonenavi.jp/international/en/
A5: Tokio | B5: Nikko | C5: Tochigi | D5: 110–140 min | E5: Patrimonio UNESCO y montaña | F5: Media | G5: Sí, largo | H5: Sí para naturaleza | I5: Compite con Kamakura: Nikko es más monumental y lejano | J5: S | K5: No reducirlo a Toshogu si se duerme | L5: https://www.visitnikko.jp/en/
A6: Tokio | B6: Kawaguchiko / Fuji Five Lakes | C6: Yamanashi | D6: 110–150 min | E6: Vistas de Fuji, lagos y cuevas | F6: Media | G6: Sí, largo | H6: Sí | I6: Compite con Hakone; elegir por clima e interés | J6: S | K6: La visibilidad de Fuji es incierta | L6: https://www.japan.travel/en/
A7: Tokio | B7: Kawagoe | C7: Saitama | D7: 35–60 min | E7: Paisaje Edo, almacenes y comida | F7: Fácil | G7: Sí | H7: No | I7: Compite con Yanaka; Kawagoe es más escenográfico | J7: A | K7: Muy eficiente, pero fines de semana saturado | L7: https://www.japan.travel/en/
A8: Tokio | B8: Chichibu + Nagatoro | C8: Saitama | D8: 90–120 min | E8: Río, montaña y festivales | F8: Media | G8: Sí | H8: Opcional | I8: Compite con Mitake; gana en paisaje regional | J8: A | K8: Mejor con estación o actividad concreta | L8: https://www.japan.travel/en/
A9: Tokio | B9: Mount Takao | C9: Tokio | D9: 50–70 min | E9: Senderismo accesible | F9: Fácil–media | G9: Sí | H9: No | I9: Compite con Mitake; Takao es más fácil y concurrido | J9: A | K9: Excelente primer escape natural | L9: https://www.japan.travel/en/
A10: Tokio | B10: Mount Mitake / Okutama | C10: Tokio | D10: 90–130 min | E10: Bosque, santuario, valles | F10: Media | G10: Sí | H10: Opcional | I10: Compite con Takao; gana en atmósfera y calma | J10: A | K10: Más tiempo de traslado, mejor naturaleza | L10: https://www.gotokyo.org/en/index.html
A11: Tokio | B11: Mount Nokogiri | C11: Chiba | D11: 120–170 min | E11: Canteras, budas y bahía | F11: Media | G11: Sí, largo | H11: Opcional | I11: Compite con Takao; más raro y costero | J11: A | K11: Day trip exigente sin auto | L11: https://www.visitchiba.jp/
A12: Tokio | B12: Sawara + Naritasan | C12: Chiba | D12: 70–120 min | E12: Canales Edo y templo | F12: Fácil | G12: Sí | H12: No | I12: Compite con Kawagoe; Sawara suele estar más tranquila | J12: A | K12: Muy buena hidden gem antes/después de NRT | L12: https://www.visitchiba.jp/
... A32: Okinawa | B32: Yaeyama Islands | C32: Okinawa | D32: Vuelo a Ishigaki + ferries | E32: Islas, cultura y selva | F32: Alta | G32: No | H32: Sí, 3–7 | I32: Compite con Miyako: Yaeyama gana en variedad y aventura | J32: S | K32: No es day trip | L32: https://visitokinawajapan.com/

Sheet Hidden Gems
A1: ID | B1: Hub | C1: Lugar | D1: Hidden Gem Status | E1: Alternativa a | F1: Grado | G1: Por qué | H1: Aglomeración | I1: Fuente
A2: JP-004 | B2: Tokio | C2: Takeshita Street | D2: Alternativa menos saturada | E2: Cat Street / Koenji | F2: C | G2: Es famosa, pero las multitudes y tiendas repetitivas reducen el valor. | H2: Extremo | I2: https://www.gotokyo.org/en/index.html
A3: JP-005 | B3: Tokio | C3: Cat Street | D3: Alternativa menos saturada | E3: Takeshita Street | F3: A | G3: Mejor paseo de moda urbana que Takeshita si se busca diseño y ambiente. | H3: Alto | I3: https://www.gotokyo.org/en/index.html
A4: JP-006 | B4: Tokio | C4: Nezu Museum | D4: Semi-hidden | F4: A | G4: Colección refinada y uno de los jardines museísticos más bellos de la ciudad. | H4: Medio | I4: https://www.nezu-muse.or.jp/en/
A5: JP-007 | B5: Tokio | C5: Ota Memorial Museum of Art | D5: Hidden Gem real | F5: A | G5: Pequeño, especializado y excelente para comprender el ukiyo-e sin invertir medio día. | H5: Bajo | I5: http://www.ukiyoe-ota-muse.jp/eng
A6: JP-009 | B6: Tokio | C6: Daikanyama T-SITE | D6: Semi-hidden | F6: A | G6: Gran pausa de diseño, libros y café fuera de los circuitos más ruidosos. | H6: Medio | I6: https://store.tsite.jp/daikanyama/english/
A7: JP-011 | B7: Tokio | C7: Tokyo Metropolitan Government Observatory | D7: Alternativa menos saturada | E7: SHIBUYA SKY | F7: A | G7: La mejor vista gratuita de la ciudad y excelente respaldo si otros miradores se agotan. | H7: Alto | I7: https://www.yokoso.metro.tokyo.lg.jp/en/tenbou/
A8: JP-015 | B8: Tokio | C8: Kagurazaka backstreets | D8: Semi-hidden | F8: A | G8: Alternativa elegante y menos obvia a los barrios tradicionales más saturados. | H8: Medio | I8: https://www.gotokyo.org/en/index.html
A9: JP-017 | B9: Tokio | C9: Asakusa Culture Tourist Information Center | D9: Hidden Gem real | F9: A | G9: Vista gratuita y perfectamente situada sobre Kaminarimon y Nakamise. | H9: Medio | I9: https://www.city.taito.lg.jp/bunka_kanko/kankoinfo/info/oyakudachi/kankocenter/a-tic-gaiyo.html
A10: JP-018 | B10: Tokio | C10: Kappabashi Kitchen Town | D10: Semi-hidden | F10: A | G10: Especialización real y objetos japoneses útiles, no solo recuerdos genéricos. | H10: Medio | I10: https://www.kappabashi.or.jp/en/
A11: JP-020 | B11: Tokio | C11: The Sumida Hokusai Museum | D11: Hidden Gem real | F11: A | G11: Museo especializado con gran arquitectura y relación directa con el barrio natal de Hokusai. | H11: Bajo | I11: https://hokusai-museum.jp/?lang=en
A12: JP-023 | B12: Tokio | C12: Yanaka Ginza and cemetery lanes | D12: Semi-hidden | F12: A | G12: Shitamachi tranquilo, vivido y fotogénico sin parecer un decorado. | H12: Medio | I12: https://www.gotokyo.org/en/index.html
A13: JP-024 | B13: Tokio | C13: Nezu Shrine | D13: Alternativa menos saturada | E13: Fushimi Inari (escala mucho menor) | F13: A | G13: Santuario histórico con túnel de torii y azaleas, mucho menos saturado que Fushimi Inari. | H13: Medio | I13: https://www.nedujinja.or.jp/
A14: JP-027 | B14: Tokio | C14: Kanda Myojin | D14: Semi-hidden | F14: A | G14: Puente convincente entre tradición, negocios y cultura anime. | H14: Medio | I14: https://www.kandamyoujin.or.jp/english/
A15: JP-028 | B15: Tokio | C15: Jimbocho Book Town | D15: Hidden Gem real | F15: A | G15: Especialización y atmósfera intelectual difíciles de encontrar en otra megaciudad. | H15: Bajo | I15: https://www.gotokyo.org/en/index.html
A16: JP-029 | B16: Tokio | C16: Imperial Palace East Gardens | D16: Lugar conocido pero excelente | F16: A | G16: Paisaje, murallas y vacío urbano de gran escala sin costo. | H16: Medio | I16: https://www.kunaicho.go.jp/e-event/higashigyoen.html
A17: JP-031 | B17: Tokio | C17: Hama-rikyu Gardens | D17: Semi-hidden | F17: A | G17: Uno de los mejores contrastes entre jardín feudal, agua salada y rascacielos. | H17: Medio | I17: https://www.tokyo-park.or.jp/park/hama-rikyu/
A18: JP-035 | B18: Tokio | C18: The National Art Center, Tokyo | D18: Lugar conocido pero excelente | F18: A | G18: Edificio extraordinario y exposiciones temporales de alto nivel; no tiene colección permanente. | H18: Medio | I18: https://www.nact.jp/english/
A19: JP-036 | B19: Tokio | C19: 21_21 DESIGN SIGHT | D19: Hidden Gem real | F19: A | G19: Pequeña pero conceptualmente fuerte; ideal para amantes de diseño. | H19: Bajo | I19: https://www.2121designsight.jp/en/
A20: JP-037 | B20: Tokio | C20: Zōjō-ji + Tokyo Tower view | D20: Alternativa menos saturada | E20: Subir a Tokyo Tower | F20: A | G20: Una de las composiciones visuales más claras entre Edo y Tokio moderno. | H20: Alto | I20: https://www.zojoji.or.jp/en/
A21: JP-040 | B21: Tokio | C21: Miraikan | D21: Lugar conocido pero excelente | F21: A | G21: El mejor museo general de ciencia y futuro para conectar robótica, espacio y sociedad. | H21: Medio | I21: https://www.miraikan.jst.go.jp/en/
A22: JP-043 | B22: Tokio | C22: SMALL WORLDS Miniature Museum | D22: Semi-hidden | F22: A | G22: Muy visual, detallado y diferente de los grandes museos convencionales. | H22: Medio | I22: https://smallworlds.jp/en/
A23: JP-045 | B23: Tokio | C23: Kichijoji + Inokashira Park | D23: Semi-hidden | F23: A | G23: Uno de los barrios con mejor equilibrio entre vida local, comida, tiendas y naturaleza. | H23: Alto | I23: https://www.gotokyo.org/en/index.html
A24: JP-046 | B24: Tokio | C24: Nakano Broadway | D24: Alternativa menos saturada | E24: Akihabara | F24: A | G24: Mejor para coleccionismo profundo y rarezas que muchos edificios de Akihabara. | H24: Alto | I24: https://nakano-broadway.com/
A25: JP-047 | B25: Tokio | C25: Edo-Tokyo Open Air Architectural Museum | D25: Hidden Gem real | F25: A | G25: La mejor inmersión arquitectónica en el Tokio desaparecido. Clasificación v2: excelente y muy recomendable, pero no justifica por sí sola adaptar la ruta. | H25: Bajo | I25: https://www.tatemonoen.jp/english/
A26: JP-048 | B26: Tokio | C26: Shimokitazawa | D26: Semi-hidden | F26: A | G26: Cultura independiente, segunda mano y música sin la escala corporativa de Shibuya. | H26: Alto | I26: https://www.gotokyo.org/en/index.html
A27: JP-049 | B27: Tokio | C27: Ikebukuro anime district | D27: Alternativa menos saturada | E27: Akihabara | F27: A | G27: Es la alternativa más completa a Akihabara para fandom femenino, Pokémon y gashapon. | H27: Extremo | I27: https://www.gotokyo.org/en/index.html
A28: JP-052 | B28: Tokio | C28: Mount Mitake and Musashi Mitake Shrine | D28: Semi-hidden | E28: Mount Takao | F28: A | G28: Más espiritual, boscoso y menos internacional que Takao. | H28: Medio | I28: https://www.gotokyo.org/en/index.html
A29: JP-058 | B29: Kioto | C29: Kennin-ji | D29: Semi-hidden | F29: A | G29: Excelente arte y jardines en pleno Gion con menos presión que los iconos mayores. | H29: Medio | I29: https://www.kenninji.jp/english/
A30: JP-061 | B30: Kioto | C30: Murin-an | D30: Hidden Gem real | F30: A | G30: Uno de los jardines más refinados y tranquilos del centro, con control de aforo. Clasificación v2: excelente y muy recomendable, pero no justifica por sí sola adaptar la ruta. | H30: Bajo | I30: https://murin-an.jp/en/
A31: JP-064 | B31: Kioto | C31: Hōnen-in | D31: Hidden Gem real | F31: A | G31: Pequeño, musgoso y genuinamente tranquilo a metros del eje turístico. | H31: Bajo | I31: https://kyoto.travel/en/
A32: JP-068 | B32: Kioto | C32: Fushimi Sake District | D32: Semi-hidden | F32: A | G32: Excelente contrapunto gastronómico y urbano a los templos. | H32: Medio | I32: https://kyoto.travel/en/areas/fushimi/
A33: JP-069 | B33: Kioto | C33: Bishamon-dō | D33: Hidden Gem real | F33: A | G33: Templo estacional excelente con muy poco turismo internacional. | H33: Medio | I33: https://kyoto.travel/en/hidden-gems/yamashina/
A34: JP-070 | B34: Kioto | C34: Yamashina Canal | D34: Hidden Gem real | E34: Philosopher's Path | F34: A | G34: Paseo local sencillo y bello, especialmente en floración. | H34: Bajo | I34: https://kyoto.travel/en/hidden-gems/yamashina/
A35: JP-073 | B35: Kioto | C35: Ōkōchi Sansō Garden | D35: Alternativa menos saturada | E35: Arashiyama Bamboo Grove | F35: A | G35: La mejor recompensa tras el bambusal: vistas, senderos y aforo moderado. | H35: Medio | I35: https://kyoto.travel/en/
A36: JP-074 | B36: Kioto | C36: Giō-ji | D36: Hidden Gem real | F36: A | G36: Uno de los recintos de musgo más íntimos y emocionales de Arashiyama. | H36: Bajo | I36: https://www.giouji.or.jp/en/
A37: JP-075 | B37: Kioto | C37: Otagi Nenbutsu-ji | D37: Hidden Gem real | E37: Templos centrales saturados | F37: A | G37: Más de mil rakan expresivos crean una experiencia artística y espiritual singular. Clasificación v2: excelente y muy recomendable, pero no justifica por sí sola adaptar la ruta. | H37: Bajo | I37: https://www.otagiji.com/
A38: JP-076 | B38: Kioto | C38: Adashino Nenbutsu-ji | D38: Alternativa menos saturada | E38: Arashiyama Bamboo Grove | F38: A | G38: Miles de piedras memoriales y un pequeño bambusal ofrecen una alternativa más profunda. | H38: Medio | I38: http://www.nenbutsuji.jp/
A39: JP-077 | B39: Kioto | C39: Katsura Imperial Villa | D39: Lugar conocido pero excelente | F39: S | G39: Obra maestra absoluta de arquitectura y jardín japonés; exige planificación. | H39: Bajo | I39: https://kyoto-gosho.kunaicho.go.jp/en/katsura-rikyu/visit
A40: JP-078 | B40: Kioto | C40: Saiho-ji (Koke-dera) | D40: Lugar conocido pero excelente | F40: A | G40: Jardín extraordinario con acceso controlado; caro pero sereno. | H40: Bajo | I40: https://saihoji-kokedera.com/en/
A41: JP-079 | B41: Kioto | C41: Kyoto Rakusai Bamboo Park | D41: Alternativa menos saturada | E41: Arashiyama Bamboo Grove | F41: A | G41: Alternativa real con 110 variedades y un paseo de bambú largo y tranquilo. | H41: Bajo | I41: https://kyoto.travel/en/hidden-gems/hidden-gems-of-kyoto-nishikyo/
A42: JP-082 | B42: Kioto | C42: Daitoku-ji subtemples | D42: Hidden Gem real | F42: A | G42: La mejor área para profundizar en jardines zen sin multitudes constantes. Clasificación v2: excelente y muy recomendable, pero no justifica por sí sola adaptar la ruta. | H42: Bajo | I42: https://kyoto.travel/en/
A43: JP-083 | B43: Kioto | C43: Genkō-an | D43: Hidden Gem real | F43: A | G43: Las ventanas circular y cuadrada enmarcan una experiencia visual y filosófica memorable. | H43: Medio | I43: https://kyoto.travel/en/destinations/genko-an-temple/
A44: JP-084 | B44: Kioto | C44: Shisen-dō | D44: Hidden Gem real | F44: A | G44: Jardín íntimo, sonido de shishi-odoshi y baja densidad turística. | H44: Bajo | I44: https://kyoto.travel/en/
A45: JP-085 | B45: Kioto | C45: Kurama-dera to Kibune hike | D45: Lugar conocido pero excelente | F45: A | G45: Une bosque sagrado, montaña y aldeas en una experiencia que no parece ciudad. Clasificación v2: excelente y muy recomendable, pero no justifica por sí sola adaptar la ruta. | H45: Medio | I45: https://kyoto.travel/en/areas/kurama-kibune/
A46: JP-086 | B46: Kioto | C46: Sanzen-in | D46: Semi-hidden | F46: A | G46: El conjunto más convincente de Ohara: musgo, estatuas, interiores y paisaje rural. Clasificación v2: excelente y muy recomendable, pero no justifica por sí sola adaptar la ruta. | H46: Medio | I46: https://kyoto.travel/en/areas/ohara/
A47: JP-087 | B47: Kioto | C47: Hōsen-in | D47: Hidden Gem real | F47: A | G47: Jardín enmarcado desde el tatami con té incluido; íntimo y visual. | H47: Bajo | I47: https://kyoto.travel/en/areas/ohara/
A48: JP-088 | B48: Kioto | C48: Jingo-ji | D48: Semi-hidden | F48: A | G48: Gran paisaje de montaña y escaleras; mejor que muchos templos centrales en otoño. | H48: Medio | I48: https://kyoto.travel/en/areas/takao/
A49: JP-090 | B49: Kioto | C49: Kyoto Imperial Palace | D49: Lugar conocido pero excelente | F49: A | G49: Gran vacío histórico y arquitectura imperial; gratuito y menos saturado. | H49: Medio | I49: https://sankan.kunaicho.go.jp/english/guide/kyoto.html
A50: JP-092 | B50: Kioto | C50: Kyoto International Manga Museum | D50: Lugar conocido pero excelente | F50: A | G50: Gran archivo legible y relajado; más cultural que comercial. | H50: Medio | I50: https://kyotomm.jp/en/
A51: JP-093 | B51: Kioto | C51: Kyoto Railway Museum | D51: Lugar conocido pero excelente | F51: A | G51: Uno de los mejores museos ferroviarios de Japón, con material real y demostraciones. Clasificación v2: excelente y muy recomendable, pero no justifica por sí sola adaptar la ruta. | H51: Alto | I51: https://www.kyotorailwaymuseum.jp/en/
A52: JP-094 | B52: Kioto | C52: Kyoto National Museum | D52: Lugar conocido pero excelente | F52: A | G52: Colecciones y exposiciones esenciales para profundizar en arte japonés. | H52: Medio | I52: https://www.kyohaku.go.jp/eng/
A53: JP-099 | B53: Kioto | C53: Uji tea experience | D53: Lugar conocido pero excelente | F53: A | G53: Prueba el matcha en su contexto productivo y evita reducir Uji a postres virales. | H53: Medio | I53: https://www.kyototourism.org/en/areas/uji/
A54: JP-102 | B54: Kioto | C54: Demachi Masugata Shopping Arcade | D54: Alternativa menos saturada | E54: Nishiki Market | F54: A | G54: Mercado vecinal real y excelente alternativa a Nishiki para observar vida cotidiana. | H54: Bajo | I54: https://kyoto.travel/en/
A55: JP-105 | B55: Osaka | C55: Hozenji Yokocho | D55: Semi-hidden | F55: A | G55: A pocos metros del neón ofrece escala íntima, piedra mojada y gastronomía. | H55: Alto | I55: https://osaka-info.jp/en/
A56: JP-107 | B56: Osaka | C56: Namba Yasaka Shrine | D56: Semi-hidden | F56: B | G56: La cabeza de león es muy fotogénica, pero la visita es corta y ya no es secreta. | H56: Alto | I56: https://nambayasaka.jp/
A57: JP-108 | B57: Osaka | C57: Den Den Town | D57: Alternativa menos saturada | E57: Akihabara | F57: A | G57: Más compacto y menos abrumador que Akihabara, con buenas tiendas retro y hobby. | H57: Alto | I57: https://osaka-info.jp/en/
A58: JP-113 | B58: Osaka | C58: Grand Green Osaka | D58: Lugar conocido pero excelente | F58: A | G58: Nuevo gran espacio público que cambia la experiencia de Umeda. | H58: Alto | I58: https://umekita.com/e_index/
A59: JP-114 | B59: Osaka | C59: Nakanoshima waterfront | D59: Semi-hidden | F59: A | G59: El mejor conjunto de arquitectura, río, museos y cafés de Osaka. Clasificación v2: excelente y muy recomendable, pero no justifica por sí sola adaptar la ruta. | H59: Medio | I59: https://osaka-info.jp/en/
A60: JP-115 | B60: Osaka | C60: Nakanoshima Museum of Art | D60: Lugar conocido pero excelente | F60: A | G60: Arquitectura fuerte y colecciones modernas vinculadas con Osaka. | H60: Medio | I60: https://nakka-art.jp/en/
A61: JP-116 | B61: Osaka | C61: Osaka Museum of Housing and Living | D61: Hidden Gem real | F61: A | G61: Reconstrucción a escala real que explica vida cotidiana mejor que muchos castillos. | H61: Medio | I61: https://www.osaka-angenet.jp/konjyakukan/
A62: JP-118 | B62: Osaka | C62: Osaka Museum of History | D62: Alternativa menos saturada | E62: Interior de Osaka Castle | F62: A | G62: Contextualiza la ciudad y ofrece vistas excelentes del castillo desde arriba. | H62: Bajo | I62: https://www.osakamushis.jp/eng/
A63: JP-119 | B63: Osaka | C63: Shitennō-ji | D63: Semi-hidden | F63: A | G63: Gran templo histórico activo y mucho menos saturado que equivalentes de Kioto. | H63: Medio | I63: https://www.shitennoji.or.jp/en/
A64: JP-121 | B64: Osaka | C64: Expo ’70 Park + Tower of the Sun | D64: Lugar conocido pero excelente | F64: A | G64: La Torre del Sol es una de las obras públicas más extrañas y potentes de Japón. Clasificación v2: excelente y muy recomendable, pero no justifica por sí sola adaptar la ruta. | H64: Medio | I64: https://www.expo70-park.jp/languages/english/
A65: JP-122 | B65: Osaka | C65: Minoh Falls | D65: Lugar conocido pero excelente | F65: A | G65: Escape natural muy accesible con un sendero agradable desde la estación. | H65: Alto | I65: https://osaka-info.jp/en/spot/minoh-park/
A66: JP-123 | B66: Osaka | C66: Church of the Light | D66: Hidden Gem real | F66: B | G66: Obra esencial de Tadao Ando, pero el acceso público es limitado y debe confirmarse. Clasificación v2: recomendable si encaja; su valor depende más de interés, saturación o logística. | H66: Bajo | I66: http://ibaraki-kasugaoka-church.jp/e-index.html
A67: JP-127 | B67: Osaka | C67: Sakai traditional knife experience | D67: Hidden Gem real | F67: A | G67: Experiencia artesanal vinculada a una industria real, no a souvenir genérico. | H67: Bajo | I67: https://www.sakai-tcb.or.jp/en/
A68: JP-128 | B68: Osaka | C68: Kishiwada Castle Hachijin Garden | D68: Hidden Gem real | F68: A | G68: Jardín seco moderno de Mirei Shigemori casi ignorado por turismo internacional. | H68: Bajo | I68: https://osaka-info.jp/en/osaka/basic/hidden-osaka/
A69: JP-132 | B69: Osaka | C69: Isuien Garden | D69: Semi-hidden | F69: A | G69: Jardín refinado con paisaje prestado del monte Wakakusa y menor saturación. | H69: Bajo | I69: https://isuien.or.jp/en/
A70: JP-133 | B70: Osaka | C70: Naramachi | D70: Semi-hidden | F70: A | G70: El mejor lugar para prolongar Nara más allá del parque y ver casas mercantiles. | H70: Medio | I70: https://www.visitnara.jp/
A71: JP-134 | B71: Osaka | C71: Hōryū-ji | D71: Lugar conocido pero excelente | F71: S | G71: Arquitectura de madera del siglo VII y contexto histórico de primer nivel mundial. | H71: Medio | I71: https://www.horyuji.or.jp/en/
A72: JP-136 | B72: Osaka | C72: Kōko-en | D72: Lugar conocido pero excelente | F72: A | G72: Complemento ideal del castillo y mucho más tranquilo que el recinto principal. | H72: Medio | I72: https://www.himeji-machishin.jp/ryokka/kokoen/en/
A73: JP-137 | B73: Osaka | C73: Engyō-ji on Mount Shosha | D73: Semi-hidden | F73: A | G73: Bosque, teleférico y arquitectura monástica crean una experiencia completa y poco saturada. Clasificación v2: excelente y muy recomendable, pero no justifica por sí sola adaptar la ruta. | H73: Medio | I73: https://www.shosha.or.jp/_en/
A74: JP-139 | B74: Osaka | C74: Nunobiki Falls and Herb Gardens | D74: Semi-hidden | F74: A | G74: Una combinación extraordinariamente accesible de montaña, jardín y vistas sobre el puerto. | H74: Medio | I74: https://www.kobeherb.com/en/
... A79: JP-147 | B79: Osaka | C79: Enryaku-ji | D79: Lugar conocido pero excelente | F79: A | G79: Montaña sagrada de enorme influencia histórica con vistas sobre Biwa y Kioto. Clasificación v2: excelente y muy recomendable, pero no justifica por sí sola adaptar la ruta. | H79: Medio | I79: https://www.hieizan.or.jp/_att/english.pdf
A80: JP-148 | B80: Osaka | C80: Hikone Castle | D80: Alternativa menos saturada | E80: Himeji Castle | F80: A | G80: Castillo original y mucho menos saturado que Himeji, con excelente jardín. | H80: Medio | I80: https://visit.hikoneshi.com/en/
A81: JP-149 | B81: Osaka | C81: MIHO Museum | D81: Hidden Gem real | F81: A | G81: La llegada por túnel y puente a la arquitectura de I.M. Pei justifica el viaje. Clasificación v2: excelente y muy recomendable, pero no justifica por sí sola adaptar la ruta. | H81: Bajo | I81: https://www.miho.jp/en/
A82: JP-151 | B82: Osaka | C82: Ine Funaya | D82: Semi-hidden | F82: A | G82: El frente continuo de casas para barcos es un paisaje cultural raro y hermoso. Clasificación v2: excelente y muy recomendable, pero no justifica por sí sola adaptar la ruta. | H82: Medio | I82: https://www.ine-kankou.jp/en
A83: JP-152 | B83: Osaka | C83: Naoshima art island | D83: Lugar conocido pero excelente | F83: S | G83: La fusión de arte, arquitectura y paisaje insular justifica al menos una noche. | H83: Alto | I83: https://benesse-artsite.jp/en/
A84: JP-155 | B84: Okinawa | C84: Tsuboya Yachimun Street | D84: Semi-hidden | F84: A | G84: Cerámica viva, talleres y arquitectura con menor ruido que Kokusai-dori. | H84: Medio | I84: https://visitokinawajapan.com/
A85: JP-156 | B85: Okinawa | C85: Sakaemachi Arcade nightlife | D85: Hidden Gem real | F85: A | G85: El mejor ambiente local nocturno de Naha, lejos de complejos turísticos. | H85: Medio | I85: https://visitokinawajapan.com/
A86: JP-158 | B86: Okinawa | C86: Tamaudun Royal Mausoleum | D86: Semi-hidden | F86: A | G86: Sitio compacto y poderoso para comprender la dinastía Ryukyu. | H86: Bajo | I86: https://visitokinawajapan.com/discover/world-heritage-top/tamaudun/
A87: JP-159 | B87: Okinawa | C87: Kinjo-cho Stone-Paved Road | D87: Hidden Gem real | F87: A | G87: Tramo urbano auténtico que muestra el Shuri residencial y su topografía. | H87: Bajo | I87: https://visitokinawajapan.com/
A88: JP-160 | B88: Okinawa | C88: Shikina-en Royal Garden | D88: Hidden Gem real | F88: A | G88: Paisaje real Ryukyu con arquitectura y agua, mucho menos saturado que Shurijo. | H88: Bajo | I88: https://visitokinawajapan.com/discover/world-heritage-top/shikinaen-royal-garden/
A89: JP-161 | B89: Okinawa | C89: Okinawa Prefectural Museum & Art Museum | D89: Lugar conocido pero excelente | F89: A | G89: La mejor base intelectual para entender geología, guerra, Ryukyu y arte contemporáneo. Clasificación v2: excelente y muy recomendable, pero no justifica por sí sola adaptar la ruta. | H89: Medio | I89: https://okimu.jp/sp/en/
A90: JP-163 | B90: Okinawa | C90: Valley of Gangala | D90: Lugar conocido pero excelente | F90: A | G90: Cueva colapsada, bosque y arqueología humana forman una experiencia muy distinta. Clasificación v2: excelente y muy recomendable, pero no justifica por sí sola adaptar la ruta. | H90: Bajo | I90: https://gangala.com/
A91: JP-164 | B91: Okinawa | C91: Cape Chinen Park | D91: Lugar conocido pero excelente | F91: A | G91: Gran vista gratuita del Pacífico y Kudaka, muy eficiente junto a Sefa Utaki. | H91: Medio | I91: https://visitokinawajapan.com/
A92: JP-165 | B92: Okinawa | C92: Kudaka Island | D92: Hidden Gem real | F92: A | G92: Isla de enorme significado espiritual y vida local; debe visitarse con respeto. Clasificación v2: excelente y muy recomendable, pero no justifica por sí sola adaptar la ruta. | H92: Bajo | I92: https://visitokinawajapan.com/destinations/okinawa-main-island/southern-okinawa-main-island/
